Workbook

Sheet 🏢 EMPRESAS
A1: IDEmpresa | B1: RazaoSocial | C1: CNPJ_CPF | D1: InscricaoEstadual | E1: Abertura | F1: TipoCliente | G1: RamoCliente | H1: SócioAdministrador | I1: Logradouro | J1: Numero | K1: Complemento | L1: Bairro | M1: CEP | N1: Municipio | O1: Estado | P1: EmailCliente | Q1: TelefoneCliente | R1: Idade
A2: 1 | B2: TKJ Gerenciamento LTDA | C2: 13.625.833/0001-90 | D2: 119116185115 | E2: 40669 | F2: PJ | G2: Aluguel de Máquinas e Equipamentos | H2: Karina R. Hornink | I2: Alameda Afonso Schmidt | J2: 119 | K2: Conj 67 Sala 02 | L2: Santa Teresinha | M2: 02450-000 | N2: São Paulo | O2: SP | P2: administrativo@tkjgerenciamento.com.br | Q2: (11) 2972-4277 | R2: =DATEDIF(E2,TODAY(),"y") & " Anos, " & DATEDIF(E2,TODAY(),"ym") & " meses e " & DATEDIF(E2,TODAY(),"md") & " dias" -> 15 Anos, 0 meses e 4 dias
A3: 2 | B3: Finita Gerenciamento e Participacoes SA | C3: 48.210.902/0001-89 | E3: 44840 | F3: PJ | G3: Holdings | H3: Karina R. Hornink | I3: Alameda Afonso Schmidt | J3: 119 | K3: Conj 67 Sala 03 | L3: Santa Teresinha | M3: 02450-000 | N3: São Paulo | O3: SP | P3: finitaempreendimentos@gmail.com | Q3: (11) 2972-4277 | R3: =DATEDIF(E3,TODAY(),"y") & " Anos, " & DATEDIF(E3,TODAY(),"ym") & " meses e " & DATEDIF(E3,TODAY(),"md") & " dias" -> 3 Anos, 7 meses e 4 dias
A4: 3 | B4: Landkraft Locacoes LTDA | C4: 61.866.923/0001-15 | E4: 45860 | F4: PJ | G4: Aluguel de Máquinas e Equipamentos | H4: Karina R. Hornink | I4: Rua Maj Dantas Cortez | J4: 118 | K4: Anexo 122 Esq Dr Jose N57 Sala 01 | L4: Vila Gustavo | M4: 02206-000 | N4: São Paulo | O4: SP | P4: administrativo@landkraft.com.br | Q4: (11) 99360-5870 | R4: =DATEDIF(E4,TODAY(),"y") & " Anos, " & DATEDIF(E4,TODAY(),"ym") & " meses e " & DATEDIF(E4,TODAY(),"md") & " dias" -> 0 Anos, 9 meses e 18 dias
A5: 4 | B5: Thais Regueira Hornink | C5: 395.164.688-88

Sheet 🚛 FROTA
A1: IDVeiculo | B1: Placa | C1: Renavam | D1: Marca | E1: Modelo | F1: Tipagem | G1: Especie | H1: AnoFabricacao | I1: AnoModelo | J1: TabelaFipe | K1: Implemento | L1: ValorImplemento | M1: ValorTotal | N1: Status | O1: ValorVenda | P1: StatusBancario | Q1: Restricoes | R1: Observacoes
A2: 1 | B2: CLH8437 | C2: 435742442 | D2: Ford | E2: Cargo 1415 | F2: Caminhão | G2: Toco | H2: 1987 | I2: 1987 | J2: 0 | K2: Prancha | L2: 0 | M2: =SUM(L2,J2) -> 0 | N2: Vendido | O2: 70000
A3: 2 | B3: LOX6E32 | C3: 814305121 | D3: Volkswagen | E3: 15.180 Worker | F3: Caminhão | G3: Toco | H3: 2003 | I3: 2004 | J3: 0 | K3: Prancha | L3: 0 | M3: =SUM(L3,J3) -> 0 | N3: Vendido | O3: 100000
A4: 3 | B4: EET8B32 | C4: 119604302 | D4: Fiat | E4: Palio Fire 1.0 | F4: Carro | H4: 2008 | I4: 2009 | J4: 0 | L4: 0 | M4: =SUM(L4,J4) -> 0 | N4: Vendido | O4: 15000
A5: 4 | B5: KJX8J96 | C5: 980404940 | D5: Volkswagen | E5: 8.150E Delivery | F5: Caminhão | G5: 3/4 | H5: 2008 | I5: 2009 | J5: 0 | K5: Baú | L5: 0 | M5: =SUM(L5,J5) -> 0 | N5: Vendido | O5: 92500
A6: 5 | B6: ANP7H74 | C6: 344934950 | D6: Volkswagen | E6: 13.180 Constellation | F6: Caminhão | G6: Toco | H6: 2011 | I6: 2011 | J6: 0 | K6: Tanque | L6: 0 | M6: =SUM(L6,J6) -> 0 | N6: Vendido | O6: 230000
A7: 6 | B7: EVF8I83 | C7: 324418264 | D7: Volkswagen | E7: 13.180 Constellation | F7: Caminhão | G7: Toco | H7: 2011 | I7: 2011 | J7: 189797 | K7: Munck | L7: 70000 | M7: =SUM(L7,J7) -> 259797 | N7: Frota | P7: Santander Leasing Reneg | Q7: Financeira | R7: Locado
A8: 7 | B8: EUK4135 | C8: 411870114 | D8: Volkswagen | E8: 9.150 Delivery | F8: Caminhão | G8: 3/4 | H8: 2011 | I8: 2012 | J8: 0 | K8: Carroceria | L8: 0 | M8: =SUM(L8,J8) -> 0 | N8: Vendido | O8: 133000
A9: 8 | B9: AWC3252 | C9: 492209359 | D9: Ford | E9: Cargo 1519 | F9: Caminhão | G9: Toco | H9: 2012 | I9: 2013 | J9: 211629 | K9: Basculante | L9: 25000 | M9: =SUM(L9,J9) -> 236629 | N9: Desativado | P9: Banco Bradesco | Q9: Financeira | R9: Retido
A10: 9 | B10: BAM0G65 | C10: 592303365 | D10: Volvo | E10: VM 270 | F10: Caminhão | G10: Toco | H10: 2013 | I10: 2013 | J10: 0 | K10: Carroceria | L10: 0 | M10: =SUM(L10,J10) -> 0 | N10: Vendido | O10: 110178
A11: 10 | B11: BAM0478 | C11: 996412590 | D11: Volvo | E11: VM 270 | F11: Caminhão | G11: Toco | H11: 2013 | I11: 2013 | J11: 0 | K11: Carroceria | L11: 0 | M11: =SUM(L11,J11) -> 0 | N11: Vendido | O11: 125000
A12: 11 | B12: FIH4496 | C12: 514567759 | D12: Toyota | E12: Etios HB 1.3 Manual | F12: Carro | H12: 2013 | I12: 2013 | J12: 40873 | L12: 0 | M12: =SUM(L12,J12) -> 40873 | N12: Desativado | P12: Nada Consta | Q12: Renajud | R12: Furtado
A13: 12 | B13: GAR0I46 | C13: 1073178045 | D13: Volkswagen | E13: Gol Comfortl. 1.6 | F13: Carro | H13: 2015 | I13: 2016 | J13: 0 | L13: 0 | M13: =SUM(L13,J13) -> 0 | N13: Vendido | O13: 21000
A14: 13 | B14: GHH0155 | C14: 1129174503 | D14: Chevrolet | E14: Prisma Sed. Joy 1.0 | F14: Carro | H14: 2017 | I14: 2018 | J14: 0 | L14: 0 | M14: =SUM(L14,J14) -> 0 | N14: Vendido | O14: 48880
A15: 14 | B15: GEE4D22 | C15: 1129176689 | D15: Chevrolet | E15: Onix Joy 1.0 | F15: Carro | H15: 2017 | I15: 2018 | J15: 0 | L15: 0 | M15: =SUM(L15,J15) -> 0 | N15: Vendido | O15: 27500
A16: 15 | B16: GJJ5485 | C16: 1131048358 | D16: Chevrolet | E16: Onix Joy 1.0 | F16: Carro | H16: 2017 | I16: 2018 | J16: 0 | L16: 0 | M16: =SUM(L16,J16) -> 0 | N16: Vendido | O16: 27500
A17: 16 | B17: GIL6H09 | C17: 1129174651 | D17: Chevrolet | E17: Onix Joy 1.0 | F17: Carro | H17: 2017 | I17: 2018 | J17: 0 | L17: 0 | M17: =SUM(L17,J17) -> 0 | N17: Vendido | O17: 31000
A18: 17 | B18: BQV5264 | C18: 1185265632 | D18: Caterpillar | E18: CAT 416F2 | F18: Retroescavadeira | G18: Máquina | H18: 2018 | I18: 2018 | J18: 180000 | L18: 0 | M18: =SUM(L18,J18) -> 180000 | N18: Frota | P18: Nada Consta | Q18: Renajud | R18: Locado
A19: 18 | B19: ERA6A58 | C19: 1181626088 | D19: Toyota | E19: Hilux SW4 SRV 2.7 Flex | F19: Carro | H19: 2018 | I19: 2019 | J19: 181130 | L19: 0 | M19: =SUM(L19,J19) -> 181130 | N19: Frota | P19: Nada Consta | Q19: Renajud | R19: Locado
A20: 19 | B20: EKJ0028 | C20: 1173726257 | D20: Toyota | E20: Etios 1.3 Aut. | F20: Carro | H20: 2018 | I20: 2019 | J20: 0 | L20: 0 | M20: =SUM(L20,J20) -> 0 | N20: Vendido | O20: 42000
A21: 20 | B21: MAX4116 | C21: 0 | D21: Jcb | E21: 3CX | F21: Retroescavadeira | G21: Máquina | H21: 2020 | I21: 2020 | J21: 230000 | L21: 0 | M21: =SUM(L21,J21) -> 230000 | N21: Frota | P21: Nada Consta | Q21: Nada Consta | R21: Locado
A22: 21 | B22: FZB8D94 | C22: 1232225905 | D22: Mercedes Benz | E22: GLA200FF Advanced | F22: Carro | H22: 2020 | I22: 2020 | J22: 0 | L22: 0 | M22: =SUM(L22,J22) -> 0 | N22: Vendido | O22: 130000
A23: 22 | B23: GIK6G75 | C23: 1234787137 | D23: MIMADO | E23: CARRETA REBOQUE | F23: Reboque | H23: 2020 | I23: 2020 | J23: 0 | L23: 0 | M23: =SUM(L23,J23) -> 0 | N23: Vendido | O23: 11000
A24: 23 | B24: BPB6D57 | C24: 1248267963 | D24: Volkswagen | E24: 24.260 Constellation | F24: Caminhão | G24: Truck | H24: 2020 | I24: 2021 | J24: 0 | K24: Prancha | L24: 0 | M24: =SUM(L24,J24) -> 0 | N24: Vendido | O24: 515000
A25: 24 | B25: DYG5G03 | C25: 1243478176 | D25: Volkswagen | E25: 14.190 Constellation | F25: Caminhão | G25: Toco | H25: 2020 | I25: 2021 | J25: 334654 | K25: Munck | L25: 72500 | M25: =SUM(L25,J25) -> 407154 | N25: Frota | P25: Nada Consta | Q25: Renajud | R25: Quebrado
A26: 25 | B26: CRN8D42 | C26: 1278843024 | D26: Fiat | E26: Fiorino Working | F26: Carro | G26: Utilitário | H26: 2021 | I26: 2021 | J26: 0 | L26: 0 | M26: =SUM(L26,J26) -> 0 | N26: Vendido | O26: 78681
A27: 26 | B27: BYJ1H22 | C27: 1278842958 | D27: Fiat | E27: Fiorino Working | F27: Carro | G27: Utilitário | H27: 2021 | I27: 2021 | J27: 0 | L27: 0 | M27: =SUM(L27,J27) -> 0 | N27: Vendido | O27: 51000
A28: 27 | B28: DRF4J54 | C28: 1278842990 | D28: Fiat | E28: Fiorino Working | F28: Carro | G28: Utilitário | H28: 2021 | I28: 2021 | J28: 0 | L28: 0 | M28: =SUM(L28,J28) -> 0 | N28: Vendido | O28: 51000
A29: 28 | B29: BSY5H86 | C29: 1278439576 | D29: Fiat | E29: Fiorino Working | F29: Carro | G29: Utilitário | H29: 2021 | I29: 2021 | J29: 0 | L29: 0 | M29: =SUM(L29,J29) -> 0 | N29: Vendido | O29: 51000
A30: 29 | B30: BZR7H61 | C30: 1278439584 | D30: Fiat | E30: Fiorino Working | F30: Carro | G30: Utilitário | H30: 2021 | I30: 2021 | J30: 0 | L30: 0 | M30: =SUM(L30,J30) -> 0 | N30: Vendido | O30: 47000
A31: 30 | B31: CUF6C08 | C31: 1278439673 | D31: Fiat | E31: Fiorino Working | F31: Carro | G31: Utilitário | H31: 2021 | I31: 2021 | J31: 0 | L31: 0 | M31: =SUM(L31,J31) -> 0 | N31: Vendido | O31: 51000
A32: 31 | B32: CFZ5I74 | C32: 1278439630 | D32: Fiat | E32: Fiorino Working | F32: Carro | G32: Utilitário | H32: 2021 | I32: 2021 | J32: 0 | L32: 0 | M32: =SUM(L32,J32) -> 0 | N32: Vendido | O32: 51000
A33: 32 | B33: BYQ6A32 | C33: 1278439550 | D33: Fiat | E33: Fiorino Working | F33: Carro | G33: Utilitário | H33: 2021 | I33: 2021 | J33: 0 | L33: 0 | M33: =SUM(L33,J33) -> 0 | N33: Vendido | O33: 51000
A34: 33 | B34: CCF9F13 | C34: 1278439657 | D34: Fiat | E34: Fiorino Working | F34: Carro | G34: Utilitário | H34: 2021 | I34: 2021 | J34: 0 | L34: 0 | M34: =SUM(L34,J34) -> 0 | N34: Vendido | O34: 50000
A35: 34 | B35: EXW7D65 | C35: 1262772548 | D35: Volkswagen | E35: 9.170 Delivery | F35: Caminhão | G35: 3/4 | H35: 2021 | I35: 2022 | J35: 311399 | K35: Basculante | L35: 25000 | M35: =SUM(L35,J35) -> 336399 | N35: Frota | P35: Santander Leasing Reneg | Q35: Financeira | R35: Locado
A36: 35 | B36: DYE3G22 | C36: 1262772343 | D36: Volkswagen | E36: 9.170 Delivery | F36: Caminhão | G36: 3/4 | H36: 2021 | I36: 2022 | J36: 0 | K36: Basculante | L36: 0 | M36: =SUM(L36,J36) -> 0 | N36: Vendido | O36: 240000
A37: 36 | B37: FPY0E65 | C37: 1262772297 | D37: Volkswagen | E37: 9.170 Delivery | F37: Caminhão | G37: 3/4 | H37: 2021 | I37: 2022 | J37: 0 | K37: Carroceria Cabinado | L37: 0 | M37: =SUM(L37,J37) -> 0 | N37: Vendido | O37: 250000
A38: 37 | B38: BWV8F67 | C38: 1262921489 | D38: Volkswagen | E38: 9.170 Delivery | F38: Caminhão | G38: 3/4 | H38: 2021 | I38: 2022 | J38: 0 | K38: Basculante | L38: 0 | M38: =SUM(L38,J38) -> 0 | N38: Vendido | O38: 250000
A39: 38 | B39: CUK9B55 | C39: 1262772424 | D39: Volkswagen | E39: 9.170 Delivery | F39: Caminhão | G39: 3/4 | H39: 2021 | I39: 2022 | J39: 0 | K39: Carroceria Cabinado | L39: 0 | M39: =SUM(L39,J39) -> 0 | N39: Vendido | O39: 240000
A40: 39 | B40: EJX0I24 | C40: 1262921586 | D40: Volkswagen | E40: Express Delivery | F40: Caminhonete | H40: 2021 | I40: 2022 | J40: 234519 | K40: Carroceria Cabinado | L40: 28700 | M40: =SUM(L40,J40) -> 263219 | N40: Frota | P40: Santander Leasing Reneg | Q40: Financeira | R40: Locado
A41: 40 | B41: DPB8E26 | C41: 1262921551 | D41: Volkswagen | E41: Express Delivery | F41: Caminhonete | H41: 2021 | I41: 2022 | J41: 234519 | K41: Carroceria Cabinado | L41: 28700 | M41: =SUM(L41,J41) -> 263219 | N41: Frota | P41: Santander Leasing Reneg | Q41: Financeira | R41: Locado
A42: 41 | B42: DLG0D92 | C42: 1262921454 | D42: Volkswagen | E42: Express Delivery | F42: Caminhonete | H42: 2021 | I42: 2022 | J42: 234519 | K42: Carroceria Cabinado | L42: 28700 | M42: =SUM(L42,J42) -> 263219 | N42: Frota | P42: Santander Leasing Reneg | Q42: Financeira | R42: Locado
A43: 42 | B43: BSX5H07 | C43: 1277427728 | D43: Volkswagen | E43: Express Delivery | F43: Caminhonete | H43: 2021 | I43: 2022 | J43: 234519 | K43: Carroceria | L43: 18850 | M43: =SUM(L43,J43) -> 253369 | N43: Frota | P43: Banco Volkswagen | Q43: Financeira | R43: Locado
A44: 43 | B44: CSU3F94 | C44: 1277433183 | D44: Volkswagen | E44: Express Delivery | F44: Caminhonete | H44: 2021 | I44: 2022 | J44: 234519 | K44: Carroceria | L44: 18850 | M44: =SUM(L44,J44) -> 253369 | N44: Frota | P44: Banco Volkswagen | Q44: Financeira | R44: Locado
A45: 44 | B45: FFS0D23 | C45: 1280040227 | D45: Volkswagen | E45: Express Delivery | F45: Caminhonete | H45: 2021 | I45: 2022 | J45: 234519 | K45: Carroceria | L45: 18850 | M45: =SUM(L45,J45) -> 253369 | N45: Frota | P45: Banco Itaú | Q45: Financeira | R45: Locado
A46: 45 | B46: EMN8B51 | C46: 1280040200 | D46: Volkswagen | E46: Express Delivery | F46: Caminhonete | H46: 2021 | I46: 2022 | J46: 234519 | K46: Carroceria | L46: 18850 | M46: =SUM(L46,J46) -> 253369 | N46: Frota | P46: Banco Itaú | Q46: Financeira | R46: Locado
A47: 46 | B47: CCU5G26 | C47: 1277433230 | D47: Volkswagen | E47: Express Delivery | F47: Caminhonete | H47: 2021 | I47: 2022 | J47: 234519 | K47: Carroceria | L47: 18850 | M47: =SUM(L47,J47) -> 253369 | N47: Frota | P47: Banco Volkswagen | Q47: Financeira | R47: Locado
A48: 47 | B48: CUG4B86 | C48: 1296304180 | D48: Mercedes Benz | E48: Atego 3026 | F48: Caminhão | G48: Bitruck | H48: 2021 | I48: 2022 | J48: 447966 | K48: Prancha | L48: 143000 | M48: =SUM(L48,J48) -> 590966 | N48: Frota | P48: Nada Consta | Q48: Renajud | R48: Locado
A49: 48 | B49: TJW7I85 | C49: 1419822680 | D49: Hyundai | E49: Creta Platinum 1.0 TGDI | F49: Carro | H49: 2024 | I49: 2025 | J49: 144866 | L49: 0 | M49: =SUM(L49,J49) -> 144866 | N49: Frota | P49: Nada Consta | Q49: Renajud | R49: Administração
A50: 49 | B50: BQU9B35 | D50: Volkswagen | E50: 14.190 Constellation | F50: Caminhão | G50: Toco | H50: 2020 | I50: 2021 | J50: 0 | K50: Caçamba | N50: Sublocado | R50: Devolvido
A51: 50 | B51: MAX0753 | D51: XCMG | E51: XZ200 | F51: Perfuratriz | G51: Máquina | H51: 2019 | I51: 2019 | J51: 0 | N51: Sublocado | R51: Devolvido

Sheet 🏢 CLIENTES
A1: IDCliente | B1: RazaoSocial | C1: CNPJ_CPF | D1: TipoCliente | E1: RamoCliente | F1: ServicoCliente | G1: MunicipioCliente | H1: EstadoCliente | I1: ContatoCliente | J1: EmailCliente | K1: TelefoneCliente | L1: StatusCliente
A2: 1 | B2: Celebre Obras e Servicos LTDA | C2: 12.609.247/0001-99 | D2: PJ | E2: Engenharia | F2: Saneamento | G2: São Paulo | H2: SP | I2: Raul | J2: tatiane@celebrecs.com.br | K2: (11) 2680-7631 | L2: Ativo
A3: 2 | B3: Jwr Construcoes LTDA | C3: 12.616.824/0001-70 | D3: PJ | E3: Engenharia | F3: Saneamento | G3: Barueri | H3: SP | I3: Raul | J3: tatiane@celebrecs.com.br | K3: (11) 3683-1062 | L3: Inativo
A4: 3 | B4: Sialdrill Engenharia e Construcoes LTDA | C4: 08.024.836/0001-38 | D4: PJ | E4: Engenharia | F4: Saneamento | G4: São Paulo | H4: SP | I4: Valdemir | J4: valdemir@sialdrill.com.br | K4: (11) 4440-7920 | L4: Inativo
A5: 4 | B5: Consorcio Gb Osasco Tiete | C5: 44.274.204/0001-96 | D5: PJ | E5: Engenharia | F5: Saneamento | G5: Barueri | H5: SP | I5: Dimitrius | J5: juridico@jobeng.com.br | K5: (11) 2602-2600 | L5: Inativo
A6: 5 | B6: Fbs Adelson Bispo Silva | C6: 37.709.324/0001-03 | D6: PJ | E6: Engenharia | F6: Saneamento | G6: Taboão da Serra | H6: SP | I6: Adelson | J6: fbs.polietileno20@gmail.com | K6: (11) 4139-2718 | L6: Inativo
A7: 6 | B7: Calibr Servicos Tecnicos LTDA | C7: 19.960.028/0001-07 | D7: PJ | E7: Engenharia | F7: Saneamento | G7: São José dos Campos | H7: SP | I7: Steffanie | J7: contato.hjtecnologia@gmail.com | K7: (11) 4764-5616 | L7: Inativo
A8: 7 | B8: Fibertec Engenharia LTDA | C8: 30.828.956/0001-47 | D8: PJ | E8: Engenharia | F8: Fibra | G8: São Paulo | H8: SP | I8: Donizete | J8: contato@fibertecengenharia.com | K8: (11) 3933-2130 | L8: Ativo
A9: 8 | B9: Consorcio Global Franca | C9: 55.070.909/0001-08 | D9: PJ | E9: Engenharia | F9: Saneamento | G9: São José dos Campos | H9: SP | I9: Luis | J9: contato@polemicaconstrutora.com.br | K9: (12) 3941-8555 | L9: Inativo
A10: 9 | B10: Polemica Servicos Basicos LTDA | C10: 61.870.101/0001-08 | D10: PJ | E10: Engenharia | F10: Saneamento | G10: São José dos Campos | H10: SP | I10: Rodrigo | J10: contato@polemicaconstrutora.com.br | K10: (12) 3941-8555 | L10: Ativo
A11: 10 | B11: Rlt Infraestrutura LTDA | C11: 06.949.131/0001-04 | D11: PJ | E11: Engenharia | F11: Saneamento | G11: São Paulo | H11: SP | I11: Jose Carlos | J11: supervisao@rilty.com.br | K11: (11) 2548-0599 | L11: Inativo
A12: 11 | B12: Zigurate Construcao LTDA | C12: 32.836.259/0001-63 | D12: PJ | E12: Engenharia | F12: Saneamento | G12: São Paulo | H12: SP | I12: Juscilana | J12: zigurate@zigurate.eng.br | K12: (11) 2387-1002 | L12: Ativo
A13: 12 | B13: Consorcio Global Franca II | C13: 61.065.464/0001-70 | D13: PJ | E13: Engenharia | F13: Saneamento | G13: São José dos Campos | H13: SP | I13: Ana | J13: contato@polemicaconstrutora.com.br | K13: (12) 3941-8555 | L13: Ativo
... A17: 16 | B17: Angra Construcoes e Saneamento LTDA | C17: 17.598.781/0001-60 | D17: PJ | E17: Engenharia | F17: Saneamento | G17: Barueri | H17: SP | I17: Kelvin | J17: comercial@angraconstrucoes.eng.br | K17: (11) 2970-1020 | L17: Ativo

Sheet 📄 CONTRATOS
A1: IDContrato | B1: IDEmpresa | C1: IDCliente | D1: NomeCliente | E1: OrigemContrato | F1: IDContratoOrigem | G1: ModeloContrato | H1: ResponsavelInterno | I1: CidadeOperacao | J1: EstadoOperacao | K1: DataInicio | L1: DataFimPrevista | M1: DataEncerramento | N1: IDVeiculo | O1: ItensContratados | P1: ValorMensal | Q1: StatusContrato | R1: MotivoEncerramento | S1: DocumentoRede | T1: Observacoes | U1: DiasTotais | V1: Alertas
A2: 1 | B2: 1 | C2: 2 | D2: Jwr Construcoes LTDA | E2: Concessão | G2: Mensal | H2: Antonio Deodato | I2: Campinas | J2: SP | K2: 45127 | L2: 45371 | M2: 45371 | N2: 17;20;24;26;27;28;29;34;39;42;43;45;49 | O2: 22 | P2: 70000 | Q2: Renovado | R2: Prazo | S2: https://tkjgerenciamento.sharepoint.com/:b:/s/REDE2/IQApjW3LPNBbTrl8LXYCvM9BARkL_VSSnOZjC1TZLg_BoLw?e=wZN6r8 | T2: Aditado | U2: =IF(OR(K2="",M2=""),"",M2-K2) -> 244 | V2: =IF(OR(K2="",L2=""),"",IF(Q2="Ativo",L2-TODAY(),""))
A3: 2 | B3: 1 | C3: 15 | D3: Leal Construcao de Redes de Telecomunicacoes LTDA | E3: Concessão | G3: Mensal | H3: Cleibson Leal | I3: São Paulo | J3: SP | K3: 45184 | L3: 45550 | M3: 45199 | N3: 15;38;40;41;44;46 | O3: 7 | P3: 47000 | Q3: Encerrado | R3: Retirada | S3: https://tkjgerenciamento.sharepoint.com/:b:/s/REDE2/IQBV1Tgoq-i6TbFOUgX2pW09AeGNIectu8XKr-C4U8ypzqI?e=NigWUD | T3: Encerrado por falta de pagamento | U3: =IF(OR(K3="",M3=""),"",M3-K3) -> 15 | V3: =IF(OR(K3="",L3=""),"",IF(Q3="Ativo",L3-TODAY(),""))
A4: 3 | B4: 1 | C4: 6 | D4: Calibr Servicos Tecnicos LTDA | E4: Comercial | G4: Mensal | H4: Steffanie Bianca | I4: Otalício Costa | J4: SC | K4: 45307 | L4: 45453 | M4: 45453 | N4: 16;41;47 | O4: 3 | P4: 32900 | Q4: Encerrado | R4: Encerramento de obra | S4: https://tkjgerenciamento.sharepoint.com/:b:/s/REDE2/IQBW2AHAK9DQQIjwr_-GuguKAT1hcvLMcwVsM6-6oJHbsE0?e=ZNoAPs | T4: Finalizado | U4: =IF(OR(K4="",M4=""),"",M4-K4) -> 146 | V4: =IF(OR(K4="",L4=""),"",IF(Q4="Ativo",L4-TODAY(),""))
A5: 4 | B5: 1 | C5: 3 | D5: Sialdrill Engenharia e Construcoes LTDA | E5: Comercial | G5: Mensal | H5: Valdemir Vieira | I5: São Paulo | J5: SP | K5: 45363 | L5: 45547 | M5: 45397 | N5: 23 | O5: 1 | P5: 15000 | Q5: Encerrado | R5: Venda | S5: https://tkjgerenciamento.sharepoint.com/:b:/s/REDE2/IQCuGiHGt9GETpqDu7swSl9kAQjFL2MXKf7GTmBLc9WLuJc?e=AezmTO | T5: Veículo vendido para a locatária BPB7D65 | U5: =IF(OR(K5="",M5=""),"",M5-K5) -> 34 | V5: =IF(OR(K5="",L5=""),"",IF(Q5="Ativo",L5-TODAY(),""))
A6: 5 | B6: 1 | C6: 2 | D6: Jwr Construcoes LTDA | E6: Comercial | F6: 1 | G6: Mensal | H6: Antonio Deodato | I6: Campinas | J6: SP | K6: 45397 | L6: 45397 | M6: 45505 | N6: 17;24;30;32;39;43;45;49 | O6: 12 | P6: 63300 | Q6: Encerrado | R6: Encerramento de obra | S6: https://tkjgerenciamento-my.sharepoint.com/shared?listurl=https%3A%2F%2Ftkjgerenciamento%2Esharepoint%2Ecom%2Fsites%2FREDE2%2FDocumentos%20Compartilhados&viewid=41f98fb8%2D92ae%2D4e59%2D9b01%2D6f58bb773280&id=%2Fsites%2FREDE2%2FDocumentos%20Compartilhados%2FGeneral%2F01%5FGEST%C3%83O%2DPATRIM%C3%94NIOS%2F03%5FContratos%2DLoca%C3%A7%C3%B5es%2FTKJ%2FJWR%20CONSTRU%C3%87%C3%95ES%2FAditivo%2FAditivo02%2DTKJxJWR%2DVeiculos%2D15%2E05%5Fassinado%2Epdf&parent=%2Fsites%2FREDE2%2FDocumentos%20Compartilhados%2FGeneral%2F01%5FGEST%C3%83O%2DPATRIM%C3%94NIOS%2F03%5FContratos%2DLoca%C3%A7%C3%B5es%2FTKJ%2FJWR%20CONSTRU%C3%87%C3%95ES%2FAditivo | T6: Finalizado | U6: =IF(OR(K6="",M6=""),"",M6-K6) -> 108 | V6: =IF(OR(K6="",L6=""),"",IF(Q6="Ativo",L6-TODAY(),""))
A7: 6 | B7: 1 | C7: 1 | D7: Celebre Obras e Servicos LTDA | E7: Comercial | G7: Mensal | H7: Lincoln Ribeiro | I7: São Carlos | J7: SP | K7: 45358 | L7: 45723 | M7: 45723 | N7: 40;44;45;46 | O7: 3 | P7: 20000 | Q7: Renovado | R7: Prazo | S7: https://tkjgerenciamento.sharepoint.com/sites/REDE2/Documentos%20Compartilhados/Forms/AllItems.aspx?id=%2Fsites%2FREDE2%2FDocumentos%20Compartilhados%2FGeneral%2F01%5FGEST%C3%83O%2DPATRIM%C3%94NIOS%2F03%5FContratos%2DLoca%C3%A7%C3%B5es%2FTKJ%2FCELEBRE%20OBRAS%20E%20SERVI%C3%87OS%2FS%C3%A3o%20Carlos%2FContrato%2DCELEBRExTKJ%2DS%2EC%2E%5FCCU5G26%5FFFS0D23%5FDPB8E26%5FCCF9F13%5Fassinado%2Epdf&parent=%2Fsites%2FREDE2%2FDocumentos%20Compartilhados%2FGeneral%2F01%5FGEST%C3%83O%2DPATRIM%C3%94NIOS%2F03%5FContratos%2DLoca%C3%A7%C3%B5es%2FTKJ%2FCELEBRE%20OBRAS%20E%20SERVI%C3%87OS%2FS%C3%A3o%20Carlos&p=true&ga=1 | T7: Saída CCU5G26 em 27/06/24 | U7: =IF(OR(K7="",M7=""),"",M7-K7) -> 365 | V7: =IF(OR(K7="",L7=""),"",IF(Q7="Ativo",L7-TODAY(),""))
A8: 7 | B8: 1 | C8: 2 | D8: Jwr Construcoes LTDA | E8: Comercial | G8: Mensal | H8: Raul Monegalia | I8: Barueri | J8: SP | K8: 45358 | L8: 45723 | M8: 45679 | N8: 33 | O8: 1 | P8: 2900 | Q8: Encerrado | R8: Devolução | S8: https://tkjgerenciamento.sharepoint.com/sites/REDE2/Documentos%20Compartilhados/Forms/AllItems.aspx?id=%2Fsites%2FREDE2%2FDocumentos%20Compartilhados%2FGeneral%2F01%5FGEST%C3%83O%2DPATRIM%C3%94NIOS%2F03%5FContratos%2DLoca%C3%A7%C3%B5es%2FTKJ%2FCELEBRE%20OBRAS%20E%20SERVI%C3%87OS%2FS%C3%A3o%20Carlos%2FContrato%2DCELEBRExTKJ%2DS%2EC%2E%5FCCU5G26%5FFFS0D23%5FDPB8E26%5FCCF9F13%5Fassinado%2Epdf&parent=%2Fsites%2FREDE2%2FDocumentos%20Compartilhados%2FGeneral%2F01%5FGEST%C3%83O%2DPATRIM%C3%94NIOS%2F03%5FContratos%2DLoca%C3%A7%C3%B5es%2FTKJ%2FCELEBRE%20OBRAS%20E%20SERVI%C3%87OS%2FS%C3%A3o%20Carlos&p=true&ga=1 | T8: Locatária devolveu o veículo CCF9F13 | U8: =IF(OR(K8="",M8=""),"",M8-K8) -> 321 | V8: =IF(OR(K8="",L8=""),"",IF(Q8="Ativo",L8-TODAY(),""))
A9: 8 | B9: 1 | C9: 4 | D9: Consorcio Gb Osasco Tiete | E9: Concessão | G9: Mensal | H9: Heitor Defavari | I9: Osasco | J9: SP | K9: 45393 | L9: 45576 | M9: 45597 | N9: 4;6 | O9: 2 | P9: 14000 | Q9: Encerrado | R9: Retirada | S9: https://tkjgerenciamento.sharepoint.com/:b:/s/REDE2/IQCtx1qMqr3YR6_z_jvpo6uSAaiwb1zWxqOhDgRhqojSONw?e=leJ8BQ | T9: Locadora retirou o veículo KJX8J96 | U9: =IF(OR(K9="",M9=""),"",M9-K9) -> 204 | V9: =IF(OR(K9="",L9=""),"",IF(Q9="Ativo",L9-TODAY(),""))
A10: 9 | B10: 1 | C10: 4 | D10: Consorcio Gb Osasco Tiete | E10: Concessão | F10: 8 | G10: Mensal | H10: Andrews Pereira | I10: Osasco | J10: SP | K10: 45393 | L10: 45576 | M10: 45930 | N10: 4;6 | O10: 1 | P10: 9000 | Q10: Encerrado | R10: Devolução | S10: https://tkjgerenciamento.sharepoint.com/:b:/s/REDE2/IQCtx1qMqr3YR6_z_jvpo6uSAaiwb1zWxqOhDgRhqojSONw?e=leJ8BQ | T10: Locatária devolveu o veículo EVF8883 | U10: =IF(OR(K10="",M10=""),"",M10-K10) -> 537 | V10: =IF(OR(K10="",L10=""),"",IF(Q10="Ativo",L10-TODAY(),""))
A11: 10 | B11: 1 | C11: 9 | D11: Polemica Servicos Basicos LTDA | E11: Comercial | G11: Mensal | H11: Lincoln Rennó | I11: Presidente Prudente | J11: SP | K11: 45399 | L11: 45794 | M11: 45778 | N11: 34;42;43 | O11: 3 | P11: 23200 | Q11: Renovado | R11: Prazo | S11: https://tkjgerenciamento.sharepoint.com/:b:/s/REDE2/IQBbFmsH7Y-cSY9ZAs-tj0mqAfwynEe4Cu8D8oS1HxW_Q7Q?e=PXXqot | T11: Aditado | U11: =IF(OR(K11="",M11=""),"",M11-K11) -> 379 | V11: =IF(OR(K11="",L11=""),"",IF(Q11="Ativo",L11-TODAY(),""))
A12: 11 | B12: 1 | C12: 11 | D12: Zigurate Construcao LTDA | E12: Comercial | G12: Mensal | H12: Juscilana Carvalho | I12: Suzano | J12: SP | K12: 45414 | L12: 45779 | M12: 45869 | N12: 9;10 | O12: 1 | P12: 14000 | Q12: Encerrado | R12: Devolução | S12: https://tkjgerenciamento.sharepoint.com/:b:/s/REDE2/IQAPOjMBC39OQLgkIfslRkboAe9Uu0KK1RX6S1R2vKrUsI8?e=opzCkH | T12: Locatária devolveu o veículo | U12: =IF(OR(K12="",M12=""),"",M12-K12) -> 455 | V12: =IF(OR(K12="",L12=""),"",IF(Q12="Ativo",L12-TODAY(),""))
A13: 12 | B13: 1 | C13: 1 | D13: Celebre Obras e Servicos LTDA | E13: Comercial | G13: Mensal | H13: Raul Monegalia | I13: São Paulo | J13: SP | K13: 45442 | L13: 45807 | M13: 45534 | N13: 17 | O13: 1 | P13: 12000 | Q13: Encerrado | R13: Devolução | S13: https://tkjgerenciamento.sharepoint.com/:b:/s/REDE2/IQDKeaNq1ZH8Q77jcA_hEVNnAQ-RTufc6ou9xHaSW3yAAW8?e=0nswPE | T13: Locatária devolveu a máquina | U13: =IF(OR(K13="",M13=""),"",M13-K13) -> 92 | V13: =IF(OR(K13="",L13=""),"",IF(Q13="Ativo",L13-TODAY(),""))
A14: 13 | B14: 1 | C14: 9 | D14: Polemica Servicos Basicos LTDA | E14: Comercial | G14: Mensal | H14: Rodrigo Rodrigues | I14: Presidente Prudente | J14: SP | K14: 45488 | L14: 45853 | M14: 45853 | N14: 46 | O14: 1 | P14: 7100 | Q14: Renovado | R14: Prazo | S14: https://tkjgerenciamento.sharepoint.com/:b:/s/REDE2/IQCI4mduATVxR5T4PXPy38SpAfspslgu4zRrBr4VZShvmks?e=dqj0gS | T14: Aditado | U14: =IF(OR(K14="",M14=""),"",M14-K14) -> 365 | V14: =IF(OR(K14="",L14=""),"",IF(Q14="Ativo",L14-TODAY(),""))
A15: 14 | B15: 1 | C15: 11 | D15: Zigurate Construcao LTDA | E15: Comercial | G15: Mensal | H15: Juscilana Carvalho | I15: Suzano | J15: SP | K15: 45506 | L15: 45871 | M15: 45870 | N15: 24 | O15: 1 | P15: 12000 | Q15: Renovado | R15: Migração de locadora | S15: https://tkjgerenciamento.sharepoint.com/:b:/s/REDE2/IQAww3mRUnL5QJV2chuirBhpAcn_yjT9gdlaO0u4lS23krE?e=iTa8Ac | T15: Aditado via Landkraft | U15: =IF(OR(K15="",M15=""),"",M15-K15) -> 364 | V15: =IF(OR(K15="",L15=""),"",IF(Q15="Ativo",L15-TODAY(),""))
A16: 15 | B16: 1 | C16: 1 | D16: Celebre Obras e Servicos LTDA | E16: Comercial | G16: Mensal | H16: Luis Lacerda | I16: Mogi das Cruzes | J16: SP | K16: 45509 | L16: 45580 | M16: 45580 | N16: 39;41 | O16: 2 | P16: 16000 | Q16: Renovado | R16: Prazo | S16: https://tkjgerenciamento.sharepoint.com/:b:/s/REDE2/IQCWY2mRzYvNRarhGyJqpHzuAZ-QvgBI_avNUjpsUGUp5oc?e=VYgomG | T16: Aditado | U16: =IF(OR(K16="",M16=""),"",M16-K16) -> 71 | V16: =IF(OR(K16="",L16=""),"",IF(Q16="Ativo",L16-TODAY(),""))
A17: 16 | B17: 1 | C17: 7 | D17: Fibertec Engenharia LTDA | E17: Comercial | G17: Mensal | H17: Donizete Pereira | I17: Osasco | J17: SP | K17: 45532 | L17: 45897 | M17: 45897 | N17: 47 | O17: 1 | P17: 15000 | Q17: Renovado | R17: Prazo | S17: https://tkjgerenciamento.sharepoint.com/:b:/s/REDE2/IQAayBdoruDnRJbTXZW2mqBbAUsP3vXUpZDitUPwaZYZSOw?e=TpyfK3 | T17: Aditado via Landkraft | U17: =IF(OR(K17="",M17=""),"",M17-K17) -> 365 | V17: =IF(OR(K17="",L17=""),"",IF(Q17="Ativo",L17-TODAY(),""))
A18: 17 | B18: 1 | C18: 11 | D18: Zigurate Construcao LTDA | E18: Comercial | G18: Mensal | H18: Juscilana Carvalho | I18: Suzano | J18: SP | K18: 45534 | L18: 45899 | M18: 45899 | N18: 17 | O18: 1 | P18: 10000 | Q18: Renovado | R18: Migração de locadora | S18: https://tkjgerenciamento.sharepoint.com/:b:/s/REDE2/IQDpGXpjWA1BTrgnfwlXIFz_ARb8lqqf8OGmYgG-2vJjB8g?e=aqP7Iz | T18: Aditado via Landkraft | U18: =IF(OR(K18="",M18=""),"",M18-K18) -> 365 | V18: =IF(OR(K18="",L18=""),"",IF(Q18="Ativo",L18-TODAY(),""))
A19: 18 | B19: 1 | C19: 10 | D19: Rlt Infraestrutura LTDA | E19: Comercial | G19: Mensal | H19: Eduardo Marques | I19: Joinville | J19: SC | K19: 45534 | L19: 45717 | M19: 45574 | N19: 20 | O19: 1 | P19: 12000 | Q19: Encerrado | R19: Inadimplência | S19: https://tkjgerenciamento.sharepoint.com/:b:/s/REDE2/IQArCx9Je28HSYWk9TxbfxZBAUbPa9sKGKWCeOkouslX0pk?e=as68hL | T19: Locadora retirou a máquina | U19: =IF(OR(K19="",M19=""),"",M19-K19) -> 40 | V19: =IF(OR(K19="",L19=""),"",IF(Q19="Ativo",L19-TODAY(),""))
A20: 19 | B20: 1 | C20: 7 | D20: Fibertec Engenharia LTDA | E20: Comercial | G20: Mensal | H20: Donizete Pereira | I20: Resende | J20: RJ | K20: 45603 | L20: 45784 | M20: 45724 | N20: 6 | O20: 1 | P20: 12000 | Q20: Encerrado | R20: Devolução | S20: https://tkjgerenciamento.sharepoint.com/:b:/s/REDE2/IQBBe_nRyKeJS6FQZvU1lWiAAQDZlK7P7Yku9Q-veN0WgtQ?e=wzKal8 | T20: Locadora devolveu o veículo | U20: =IF(OR(K20="",M20=""),"",M20-K20) -> 121
A21: 20 | B21: 1 | C21: 8 | D21: Consorcio Global Franca | E21: Comercial | G21: Mensal | H21: Luis Gustavo | I21: Franca | J21: SP | K21: 45576 | L21: 46306 | M21: 45901 | N21: 20 | O21: 1 | P21: 12000 | Q21: Encerrado | R21: Migração de empresas | S21: Contrato-C.G.FRANCAxTKJ_JCB3cx_assinado | T21: Transição de empresas | U21: =IF(OR(K21="",M21=""),"",M21-K21) -> 325 | V21: =IF(OR(K21="",L21=""),"",IF(Q21="Ativo",L21-TODAY(),""))
A22: 21 | B22: 1 | C22: 1 | D22: Celebre Obras e Servicos LTDA | E22: Comercial | F22: 15 | G22: Mensal | H22: Luis Lacerda | I22: Mogi das Cruzes | J22: SP | K22: 45580 | L22: 45703 | M22: 45703 | N22: 39;41 | O22: 2 | P22: 16000 | Q22: Renovado | R22: Prazo | S22: Aditivo1-1224_Contrato-CELEBRExTKJ-DLG0G92_EJX0I24 | T22: Aditado | U22: =IF(OR(K22="",M22=""),"",M22-K22) -> 123 | V22: =IF(OR(K22="",L22=""),"",IF(Q22="Ativo",L22-TODAY(),""))
A23: 22 | B23: 1 | C23: 1 | D23: Celebre Obras e Servicos LTDA | E23: Comercial | F23: 15 | G23: Mensal | H23: Luis Lacerda | I23: Mogi das Cruzes | J23: SP | K23: 45703 | L23: 45823 | M23: 45976 | N23: 39;41 | O23: 2 | P23: 17000 | Q23: Renovado | R23: Prazo | S23: Aditivo_2-0325-CELEBRExTKJ_DLG0D92-EJX0I24 | T23: Aditado | U23: =IF(OR(K23="",M23=""),"",M23-K23) -> 273 | V23: =IF(OR(K23="",L23=""),"",IF(Q23="Ativo",L23-TODAY(),""))
A24: 23 | B24: 1 | C24: 1 | D24: Celebre Obras e Servicos LTDA | E24: Comercial | F24: 6 | G24: Mensal | H24: Lincoln Ribeiro | I24: São Carlos | J24: SP | K24: 45748 | L24: 46113 | M24: 46113 | N24: 40;44;45 | O24: 3 | P24: 21550 | Q24: Renovado | R24: Prazo | S24: Aditivo_1-0325-CELEBRExTKJ_S.C. | T24: Aguardando assinatura de aditivo | U24: =IF(OR(K24="",M24=""),"",M24-K24) -> 365 | V24: =IF(OR(K24="",L24=""),"",IF(Q24="Ativo",L24-TODAY(),""))
A25: 24 | B25: 1 | C25: 9 | D25: Polemica Servicos Basicos LTDA | E25: Comercial | F25: 10 | G25: Mensal | H25: Rodrigo Rodrigues | I25: Presidente Prudente | J25: SP | K25: 45778 | L25: 46143 | M25: 45901 | N25: 34;42;43 | O25: 3 | P25: 25520 | Q25: Renovado | R25: Migração de locadora | S25: Aditivo2025-TKJxPolemica-CSU3F94_BSX5H07_EXW7D56_assinado.pdf | T25: Transferido para Landkraft | U25: =IF(OR(K25="",M25=""),"",M25-K25) -> 123 | V25: =IF(OR(K25="",L25=""),"",IF(Q25="Ativo",L25-TODAY(),""))
A26: 25 | B26: 1 | C26: 9 | D26: Polemica Servicos Basicos LTDA | E26: Comercial | F26: 13 | G26: Mensal | H26: Rodrigo Rodrigues | I26: Presidente Prudente | J26: SP | K26: 45853 | L26: 46143 | M26: 45901 | N26: 46 | O26: 1 | P26: 7810 | Q26: Renovado | R26: Migração de locadora | S26: Aditivo_1-0725-TKJxPOLÊMICA_CCU5G26 | T26: Transferido para Landkraft | U26: =IF(OR(K26="",M26=""),"",M26-K26) -> 48 | V26: =IF(OR(K26="",L26=""),"",IF(Q26="Ativo",L26-TODAY(),""))
A27: 26 | B27: 3 | C27: 11 | D27: Zigurate Construcao LTDA | E27: Comercial | F27: 14;17 | G27: Mensal | H27: Juscilana Carvalho | I27: Suzano | J27: SP | K27: 45870 | L27: 46235 | N27: 17;24 | O27: 2 | P27: 27500 | Q27: Ativo | S27: LANDKRAFTxZIGURATE_08.2025-Assinado | T27: Em andamento com valor atualizado | U27: =IF(OR(K27="",M27=""),"",M27-K27) | V27: =IF(OR(K27="",L27=""),"",IF(Q27="Ativo",L27-TODAY(),"")) -> 83
A28: 27 | B28: 3 | C28: 7 | D28: Fibertec Engenharia LTDA | E28: Comercial | F28: 16 | G28: Mensal | H28: Donizete Pereira | I28: Osasco | J28: SP | K28: 45897 | L28: 46022 | M28: 46022 | N28: 47 | O28: 1 | P28: 18500 | Q28: Renovado | R28: Prazo | S28: LANDKRAFTxFIBERTEC_08.25-Assinado | T28: Aguardando assinatura de aditivo | U28: =IF(OR(K28="",M28=""),"",M28-K28) -> 125 | V28: =IF(OR(K28="",L28=""),"",IF(Q28="Ativo",L28-TODAY(),""))
A29: 28 | B29: 3 | C29: 12 | D29: Consorcio Global Franca II | E29: Comercial | F29: 19 | G29: Mensal | H29: Luis Gustavo | I29: Franca | J29: SP | K29: 45901 | L29: 46266 | N29: 20 | O29: 1 | P29: 12550 | Q29: Ativo | S29: LANDKRAFTxC.G.F.II_09.2025_assinado | T29: Em andamento com valor atualizado | U29: =IF(OR(K29="",M29=""),"",M29-K29) | V29: =IF(OR(K29="",L29=""),"",IF(Q29="Ativo",L29-TODAY(),"")) -> 114
A30: 29 | B30: 3 | C30: 9 | D30: Polemica Servicos Basicos LTDA | E30: Comercial | F30: 10;13 | G30: Mensal | H30: Rodrigo Rodrigues | I30: Presidente Prudente | J30: SP | K30: 45901 | L30: 46143 | M30: 46143 | N30: 34;42;43;46 | O30: 4 | P30: 33330 | Q30: Renovado | S30: LANDKRAFTxPOLÊMICA_09.25 | T30: Em andamento com valor atualizado | U30: =IF(OR(K30="",M30=""),"",M30-K30) -> 242 | V30: =IF(OR(K30="",L30=""),"",IF(Q30="Ativo",L30-TODAY(),""))
A31: 30 | B31: 1 | C31: 13 | D31: Consorcio Manutencao Guarapiranga | E31: Comercial | G31: Mensal | H31: Georlando Maciel | I31: Itapecirica da Serra | J31: SP | K31: 45968 | L31: 46149 | M31: 45994 | N31: 6 | O31: 1 | P31: 14000 | Q31: Encerrado | R31: Retirada | S31: TKJxC.M.G._11.2025v2 | T31: Locadora retirou o veículo | U31: =IF(OR(K31="",M31=""),"",M31-K31) -> 26 | V31: =IF(OR(K31="",L31=""),"",IF(Q31="Ativo",L31-TODAY(),""))
A32: 31 | B32: 1 | C32: 1 | D32: Celebre Obras e Servicos LTDA | E32: Comercial | F32: 15 | G32: Mensal | H32: Luis Lacerda | I32: Mogi das Cruzes | J32: SP | K32: 45976 | L32: 46157 | M32: 46077 | N32: 39;41 | O32: 2 | P32: 22100 | Q32: Encerrado | R32: Devolução | S32: Aditivo3-0126_Contrato-CELEBRExTKJ-DLG0G92_EJX0I24-N.Assinado | T32: Valor praticado porém, aditivo sem assinatura | U32: =IF(OR(K32="",M32=""),"",M32-K32) -> 101 | V32: =IF(OR(K32="",L32=""),"",IF(Q32="Ativo",L32-TODAY(),""))
A33: 32 | B33: 1 | C33: 16 | D33: Angra Construcoes e Saneamento LTDA | E33: Comercial | G33: Mensal | H33: Lincoln Ribeiro | I33: São Carlos | J33: SP | K33: 46062 | L33: 46243 | N33: 39 | O33: 1 | P33: 9500 | Q33: Ativo | S33: Contrato_TKJxAngra-S.C._Assinado | T33: Pagamento atualizado para dia 30 | U33: =IF(OR(K33="",M33=""),"",M33-K33) | V33: =IF(OR(K33="",L33=""),"",IF(Q33="Ativo",L33-TODAY(),"")) -> 91
A34: 33 | B34: 3 | C34: 7 | D34: Fibertec Engenharia LTDA | E34: Comercial | F34: 16 | G34: Mensal | H34: Donizete Pereira | I34: Osasco | J34: SP | K34: 46082 | L34: 46447 | N34: 47 | O34: 1 | P34: 20550 | Q34: Ativo | S34: Aditivo-LANDKRAFTxFIBERTEC_03.2026 | T34: Aguardando assinatura | U34: =IF(OR(K34="",M34=""),"",M34-K34) | V34: =IF(OR(K34="",L34=""),"",IF(Q34="Ativo",L34-TODAY(),"")) -> 295
A35: 34 | B35: 3 | C35: 9 | D35: Polemica Servicos Basicos LTDA | E35: Comercial | G35: Mensal | H35: Rodrigo Rodrigues | I35: Presidente Prudente | J35: SP | K35: 46083 | L35: 46448 | N35: 41 | O35: 1 | P35: 9550 | Q35: Ativo | S35: Contrato_LandkraftXPolêmica-02.2026 | T35: Chegada em 05/03/2026 | U35: =IF(OR(K35="",M35=""),"",M35-K35) | V35: =IF(OR(K35="",L35=""),"",IF(Q35="Ativo",L35-TODAY(),"")) -> 296
A36: 35 | B36: 1 | C36: 1 | D36: Celebre Obras e Servicos LTDA | E36: Comercial | F36: 6 | G36: Mensal | H36: Lincoln Ribeiro | I36: São Carlos | J36: SP | K36: 46088 | L36: 46453 | N36: 40;44;45 | O36: 3 | P36: 25500 | Q36: Ativo | S36: Aditivo_2-0326-CELEBRExTKJ_S.C. | T36: Aguardando assinatura | U36: =IF(OR(K36="",M36=""),"",M36-K36) | V36: =IF(OR(K36="",L36=""),"",IF(Q36="Ativo",L36-TODAY(),"")) -> 301
A37: 36 | B37: 3 | C37: 9 | D37: Polemica Servicos Basicos LTDA | E37: Comercial | F37: 10;13 | G37: Mensal | H37: Rodrigo Rodrigues | I37: Presidente Prudente | J37: SP | K37: 46143 | L37: 46508 | N37: 34;42;43;46 | O37: 4 | P37: 38000 | Q37: Ativo | S37: Aditivo1_LandkraftXPolêmica-04.2026 | T37: Aguardando encerramento contrato 26 | U37: =IF(OR(K37="",M37=""),"",M37-K37) | V37: =IF(OR(K37="",L37=""),"",IF(Q37="Ativo",L37-TODAY(),"")) -> 356

Sheet 💰 FAT_UNITARIO
A1: IDFatUnitario | B1: Mes | C1: IDVeiculo | D1: IDEmpresa | E1: Placa | F1: Modelo | G1: Implemento | H1: IDContrato | I1: Diaria | J1: Trabalhado | K1: Parado | L1: Medicao | M1: Contrato
A2: 1 | B2: 45658 | C2: 24 | D2: 1 | E2: DYG5G03 | F2: VW 14-190 | G2: Munck | H2: 11 | I2: =12000/30 -> 400 | J2: 30 | K2: =IF(J2="", 0, 30 - J2) -> 0 | L2: =I2*J2 -> 12000 | M2: Suzano
A3: 2 | B3: 45658 | C3: 17 | D3: 1 | E3: BQV5264 | F3: CAT 416f2 | G3: Retroescavadeira | H3: 17 | I3: =10000/30 -> 333.33333 | J3: 30 | K3: =IF(J3="", 0, 30 - J3) -> 0 | L3: =I3*J3 -> 10000 | M3: Suzano
A4: 3 | B4: 45658 | C4: 20 | D4: 1 | E4: MAX4116 | F4: JCB 3CX | G4: Retroescavadeira | H4: 20 | I4: =12000/30 -> 400 | J4: 30 | K4: =IF(J4="", 0, 30 - J4) -> 0 | L4: =I4*J4 -> 12000 | M4: Franca
A5: 4 | B5: 45658 | C5: 43 | D5: 1 | E5: CSU3F94 | F5: VW EXPRESS | G5: Carroceria | H5: 10 | I5: =7100/30 -> 236.66667 | J5: 30 | K5: =IF(J5="", 0, 30 - J5) -> 0 | L5: =I5*J5 -> 7100 | M5: Presidente Prudente
A6: 5 | B6: 45658 | C6: 42 | D6: 1 | E6: BSX5H07 | F6: VW EXPRESS | G6: Carroceria | H6: 10 | I6: =7100/30 -> 236.66667 | J6: 30 | K6: =IF(J6="", 0, 30 - J6) -> 0 | L6: =I6*J6 -> 7100 | M6: Presidente Prudente
A7: 6 | B7: 45658 | C7: 46 | D7: 1 | E7: CCU5G26 | F7: VW EXPRESS | G7: Carroceria | H7: 13 | I7: =7100/30 -> 236.66667 | J7: 30 | K7: =IF(J7="", 0, 30 - J7) -> 0 | L7: =I7*J7 -> 7100 | M7: Presidente Prudente
A8: 7 | B8: 45658 | C8: 34 | D8: 1 | E8: EXW7D65 | F8: VW 9-170 | G8: Caçamba | H8: 10 | I8: =9000/30 -> 300 | J8: 30 | K8: =IF(J8="", 0, 30 - J8) -> 0 | L8: =I8*J8 -> 9000 | M8: Presidente Prudente
A9: 8 | B9: 45658 | C9: 45 | D9: 1 | E9: EMN8B51 | F9: VW EXPRESS | G9: Carroceria | H9: 6 | I9: =6500/30 -> 216.66667 | J9: 30 | K9: =IF(J9="", 0, 30 - J9) -> 0 | L9: =I9*J9 -> 6500 | M9: São Carlos
A10: 9 | B10: 45658 | C10: 44 | D10: 1 | E10: FFS0D23 | F10: VW EXPRESS | G10: Carroceria | H10: 6 | I10: =6500/30 -> 216.66667 | J10: 30 | K10: =IF(J10="", 0, 30 - J10) -> 0 | L10: =I10*J10 -> 6500 | M10: São Carlos
A11: 10 | B11: 45658 | C11: 40 | D11: 1 | E11: DPB8E26 | F11: VW EXPRESS | G11: Carroceria Cabinado | H11: 6 | I11: =7000/30 -> 233.33333 | J11: 30 | K11: =IF(J11="", 0, 30 - J11) -> 0 | L11: =I11*J11 -> 7000 | M11: São Carlos
A12: 11 | B12: 45658 | C12: 41 | D12: 1 | E12: DLG0D92 | F12: VW EXPRESS | G12: Carroceria Cabinado | H12: 21 | I12: =8000/30 -> 266.66667 | J12: 28 | K12: =IF(J12="", 0, 30 - J12) -> 2 | L12: =I12*J12 -> 7466.6667 | M12: Mogi das Cruzes
A13: 12 | B13: 45658 | C13: 39 | D13: 1 | E13: EJX0I24 | F13: VW EXPRESS | G13: Carroceria Cabinado | H13: 21 | I13: =8000/30 -> 266.66667 | J13: 30 | K13: =IF(J13="", 0, 30 - J13) -> 0 | L13: =I13*J13 -> 8000 | M13: Mogi das Cruzes
A14: 13 | B14: 45658 | C14: 47 | D14: 1 | E14: CUG4B86 | F14: MB ATEGO | G14: Prancha Hidráulica | H14: 16 | I14: =15000/30 -> 500 | J14: 30 | K14: =IF(J14="", 0, 30 - J14) -> 0 | L14: =I14*J14 -> 15000 | M14: Osasco
A15: 14 | B15: 45658 | C15: 33 | D15: 1 | E15: CCF9F13 | F15: FIAT FIORINO | G15: Furgão | H15: 7 | I15: =2900/30 -> 96.666667 | J15: 22 | K15: =IF(J15="", 0, 30 - J15) -> 8 | L15: =I15*J15 -> 2126.6667 | M15: Barueri
A16: 15 | B16: 45658 | C16: 6 | D16: 1 | E16: EVF8I83 | F16: VW 13-180 | G16: Munck | H16: 19 | I16: =12000/30 -> 400 | J16: 22 | K16: =IF(J16="", 0, 30 - J16) -> 8 | L16: =I16*J16 -> 8800 | M16: Osasco
A17: 16 | B17: 45658 | C17: 7 | D17: 1 | E17: EUK4135 | F17: VW 9-150 | G17: Chassi | I17: 0 | J17: 0 | K17: =IF(J17="", 0, 30 - J17) -> 30 | L17: =I17*J17 -> 0 | M17: Parado
A18: 18 | B18: 45689 | C18: 24 | D18: 1 | E18: DYG5G03 | F18: VW 14-190 | G18: Munck | H18: 11 | I18: =12000/30 -> 400 | J18: 30 | K18: =IF(J18="", 0, 30 - J18) -> 0 | L18: =I18*J18 -> 12000 | M18: Suzano
A19: 19 | B19: 45689 | C19: 17 | D19: 1 | E19: BQV5264 | F19: CAT 416f2 | G19: Retroescavadeira | H19: 17 | I19: =10000/30 -> 333.33333 | J19: 30 | K19: =IF(J19="", 0, 30 - J19) -> 0 | L19: =I19*J19 -> 10000 | M19: Suzano
A20: 20 | B20: 45689 | C20: 20 | D20: 1 | E20: MAX4116 | F20: JCB 3CX | G20: Retroescavadeira | H20: 20 | I20: =12000/30 -> 400 | J20: 28 | K20: =IF(J20="", 0, 30 - J20) -> 2 | L20: 11100 | M20: Franca
A21: 21 | B21: 45689 | C21: 43 | D21: 1 | E21: CSU3F94 | F21: VW EXPRESS | G21: Carroceria | H21: 10 | I21: =7100/30 -> 236.66667 | J21: 30 | K21: =IF(J21="", 0, 30 - J21) -> 0 | L21: =I21*J21 -> 7100 | M21: Presidente Prudente
A22: 22 | B22: 45689 | C22: 42 | D22: 1 | E22: BSX5H07 | F22: VW EXPRESS | G22: Carroceria | H22: 10 | I22: =7100/30 -> 236.66667 | J22: 30 | K22: =IF(J22="", 0, 30 - J22) -> 0 | L22: =I22*J22 -> 7100 | M22: Presidente Prudente
A23: 23 | B23: 45689 | C23: 46 | D23: 1 | E23: CCU5G26 | F23: VW EXPRESS | G23: Carroceria | H23: 13 | I23: =7100/30 -> 236.66667 | J23: 30 | K23: =IF(J23="", 0, 30 - J23) -> 0 | L23: =I23*J23 -> 7100 | M23: Presidente Prudente
A24: 24 | B24: 45689 | C24: 34 | D24: 1 | E24: EXW7D65 | F24: VW 9-170 | G24: Caçamba | H24: 10 | I24: =9000/30 -> 300 | J24: 30 | K24: =IF(J24="", 0, 30 - J24) -> 0 | L24: =I24*J24 -> 9000 | M24: Presidente Prudente
A25: 25 | B25: 45689 | C25: 45 | D25: 1 | E25: EMN8B51 | F25: VW EXPRESS | G25: Carroceria | H25: 6 | I25: =6500/30 -> 216.66667 | J25: 30 | K25: =IF(J25="", 0, 30 - J25) -> 0 | L25: =I25*J25 -> 6500 | M25: São Carlos
A26: 26 | B26: 45689 | C26: 44 | D26: 1 | E26: FFS0D23 | F26: VW EXPRESS | G26: Carroceria | H26: 6 | I26: =6500/30 -> 216.66667 | J26: 30 | K26: =IF(J26="", 0, 30 - J26) -> 0 | L26: =I26*J26 -> 6500 | M26: São Carlos
A27: 27 | B27: 45689 | C27: 40 | D27: 1 | E27: DPB8E26 | F27: VW EXPRESS | G27: Carroceria Cabinado | H27: 6 | I27: =7000/30 -> 233.33333 | J27: 30 | K27: =IF(J27="", 0, 30 - J27) -> 0 | L27: =I27*J27 -> 7000 | M27: São Carlos
A28: 28 | B28: 45689 | C28: 41 | D28: 1 | E28: DLG0D92 | F28: VW EXPRESS | G28: Carroceria Cabinado | H28: 21 | I28: =8000/30 -> 266.66667 | J28: 30 | K28: =IF(J28="", 0, 30 - J28) -> 0 | L28: =I28*J28 -> 8000 | M28: Mogi das Cruzes
A29: 29 | B29: 45689 | C29: 39 | D29: 1 | E29: EJX0I24 | F29: VW EXPRESS | G29: Carroceria Cabinado | H29: 21 | I29: =8000/30 -> 266.66667 | J29: 30 | K29: =IF(J29="", 0, 30 - J29) -> 0 | L29: =I29*J29 -> 8000 | M29: Mogi das Cruzes
A30: 30 | B30: 45689 | C30: 47 | D30: 1 | E30: CUG4B86 | F30: MB ATEGO | G30: Prancha Hidráulica | H30: 16 | I30: =15000/30 -> 500 | J30: 30 | K30: =IF(J30="", 0, 30 - J30) -> 0 | L30: =I30*J30 -> 15000 | M30: Osasco
A31: 31 | B31: 45689 | C31: 6 | D31: 1 | E31: EVF8I83 | F31: VW 13-180 | G31: Munck | H31: 19 | I31: =12000/30 -> 400 | J31: 30 | K31: =IF(J31="", 0, 30 - J31) -> 0 | L31: =I31*J31 -> 12000 | M31: Osasco
A32: 32 | B32: 45689 | C32: 7 | D32: 1 | E32: EUK4135 | F32: VW 9-150 | G32: Chassi | I32: 0 | J32: 0 | K32: =IF(J32="", 0, 30 - J32) -> 30 | L32: =I32*J32 -> 0 | M32: Parado
A33: 33 | B33: 45717 | C33: 24 | D33: 1 | E33: DYG5G03 | F33: VW 14-190 | G33: Munck | H33: 11 | I33: =12000/30 -> 400 | J33: 30 | K33: =IF(J33="", 0, 30 - J33) -> 0 | L33: =I33*J33 -> 12000 | M33: Suzano
A34: 34 | B34: 45717 | C34: 17 | D34: 1 | E34: BQV5264 | F34: CAT 416f2 | G34: Retroescavadeira | H34: 17 | I34: =10000/30 -> 333.33333 | J34: 30 | K34: =IF(J34="", 0, 30 - J34) -> 0 | L34: =I34*J34 -> 10000 | M34: Suzano
A35: 35 | B35: 45717 | C35: 20 | D35: 1 | E35: MAX4116 | F35: JCB 3CX | G35: Retroescavadeira | H35: 20 | I35: =12000/30 -> 400 | J35: 30 | K35: =IF(J35="", 0, 30 - J35) -> 0 | L35: =I35*J35 -> 12000 | M35: Franca
A36: 36 | B36: 45717 | C36: 43 | D36: 1 | E36: CSU3F94 | F36: VW EXPRESS | G36: Carroceria | H36: 10 | I36: =7100/30 -> 236.66667 | J36: 30 | K36: =IF(J36="", 0, 30 - J36) -> 0 | L36: =I36*J36 -> 7100 | M36: Presidente Prudente
A37: 37 | B37: 45717 | C37: 42 | D37: 1 | E37: BSX5H07 | F37: VW EXPRESS | G37: Carroceria | H37: 10 | I37: =7100/30 -> 236.66667 | J37: 30 | K37: =IF(J37="", 0, 30 - J37) -> 0 | L37: =I37*J37 -> 7100 | M37: Presidente Prudente
A38: 38 | B38: 45717 | C38: 46 | D38: 1 | E38: CCU5G26 | F38: VW EXPRESS | G38: Carroceria | H38: 13 | I38: =7100/30 -> 236.66667 | J38: 30 | K38: =IF(J38="", 0, 30 - J38) -> 0 | L38: =I38*J38 -> 7100 | M38: Presidente Prudente
A39: 39 | B39: 45717 | C39: 34 | D39: 1 | E39: EXW7D65 | F39: VW 9-170 | G39: Caçamba | H39: 10 | I39: =9000/30 -> 300 | J39: 30 | K39: =IF(J39="", 0, 30 - J39) -> 0 | L39: =I39*J39 -> 9000 | M39: Presidente Prudente
A40: 40 | B40: 45717 | C40: 45 | D40: 1 | E40: EMN8B51 | F40: VW EXPRESS | G40: Carroceria | H40: 6 | I40: =6500/30 -> 216.66667 | J40: 30 | K40: =IF(J40="", 0, 30 - J40) -> 0 | L40: =I40*J40 -> 6500 | M40: São Carlos
A41: 41 | B41: 45717 | C41: 44 | D41: 1 | E41: FFS0D23 | F41: VW EXPRESS | G41: Carroceria | H41: 6 | I41: =6500/30 -> 216.66667 | J41: 30 | K41: =IF(J41="", 0, 30 - J41) -> 0 | L41: =I41*J41 -> 6500 | M41: São Carlos
A42: 42 | B42: 45717 | C42: 40 | D42: 1 | E42: DPB8E26 | F42: VW EXPRESS | G42: Carroceria Cabinado | H42: 23 | I42: =7000/30 -> 233.33333 | J42: 30 | K42: =IF(J42="", 0, 30 - J42) -> 0 | L42: =I42*J42 -> 7000 | M42: São Carlos
A43: 43 | B43: 45717 | C43: 41 | D43: 1 | E43: DLG0D92 | F43: VW EXPRESS | G43: Carroceria Cabinado | H43: 22 | I43: =8500/30 -> 283.33333 | J43: 30 | K43: =IF(J43="", 0, 30 - J43) -> 0 | L43: =I43*J43 -> 8500 | M43: Mogi das Cruzes
A44: 44 | B44: 45717 | C44: 39 | D44: 1 | E44: EJX0I24 | F44: VW EXPRESS | G44: Carroceria Cabinado | H44: 22 | I44: =8500/30 -> 283.33333 | J44: 30 | K44: =IF(J44="", 0, 30 - J44) -> 0 | L44: =I44*J44 -> 8500 | M44: Mogi das Cruzes
A45: 45 | B45: 45717 | C45: 47 | D45: 1 | E45: CUG4B86 | F45: MB ATEGO | G45: Prancha Hidráulica | H45: 16 | I45: =15000/30 -> 500 | J45: 30 | K45: =IF(J45="", 0, 30 - J45) -> 0 | L45: =I45*J45 -> 15000 | M45: Osasco
A46: 46 | B46: 45717 | C46: 6 | D46: 1 | E46: EVF8I83 | F46: VW 13-180 | G46: Munck | H46: 19 | I46: =12000/30 -> 400 | J46: 8 | K46: =IF(J46="", 0, 30 - J46) -> 22 | L46: =I46*J46 -> 3200 | M46: Osasco
A47: 47 | B47: 45717 | C47: 7 | D47: 1 | E47: EUK4135 | F47: VW 9-150 | G47: Chassi | I47: 0 | J47: 0 | K47: =IF(J47="", 0, 30 - J47) -> 30 | L47: =I47*J47 -> 0 | M47: Parado
A48: 48 | B48: 45748 | C48: 24 | D48: 1 | E48: DYG5G03 | F48: VW 14-190 | G48: Munck | H48: 11 | I48: =12000/30 -> 400 | J48: 30 | K48: =IF(J48="", 0, 30 - J48) -> 0 | L48: =I48*J48 -> 12000 | M48: Suzano
A49: 49 | B49: 45748 | C49: 17 | D49: 1 | E49: BQV5264 | F49: CAT 416f2 | G49: Retroescavadeira | H49: 17 | I49: =10000/30 -> 333.33333 | J49: 30 | K49: =IF(J49="", 0, 30 - J49) -> 0 | L49: =I49*J49 -> 10000 | M49: Suzano
A50: 50 | B50: 45748 | C50: 20 | D50: 1 | E50: MAX4116 | F50: JCB 3CX | G50: Retroescavadeira | H50: 20 | I50: =12000/30 -> 400 | J50: 30 | K50: =IF(J50="", 0, 30 - J50) -> 0 | L50: =I50*J50 -> 12000 | M50: Franca
A51: 51 | B51: 45748 | C51: 43 | D51: 1 | E51: CSU3F94 | F51: VW EXPRESS | G51: Carroceria | H51: 10 | I51: =7100/30 -> 236.66667 | J51: 30 | K51: =IF(J51="", 0, 30 - J51) -> 0 | L51: =I51*J51 -> 7100 | M51: Presidente Prudente
A52: 52 | B52: 45748 | C52: 42 | D52: 1 | E52: BSX5H07 | F52: VW EXPRESS | G52: Carroceria | H52: 10 | I52: =7100/30 -> 236.66667 | J52: 30 | K52: =IF(J52="", 0, 30 - J52) -> 0 | L52: =I52*J52 -> 7100 | M52: Presidente Prudente
A53: 53 | B53: 45748 | C53: 46 | D53: 1 | E53: CCU5G26 | F53: VW EXPRESS | G53: Carroceria | H53: 13 | I53: =7100/30 -> 236.66667 | J53: 30 | K53: =IF(J53="", 0, 30 - J53) -> 0 | L53: =I53*J53 -> 7100 | M53: Presidente Prudente
A54: 54 | B54: 45748 | C54: 34 | D54: 1 | E54: EXW7D65 | F54: VW 9-170 | G54: Caçamba | H54: 10 | I54: =9000/30 -> 300 | J54: 30 | K54: =IF(J54="", 0, 30 - J54) -> 0 | L54: =I54*J54 -> 9000 | M54: Presidente Prudente
A55: 55 | B55: 45748 | C55: 45 | D55: 1 | E55: EMN8B51 | F55: VW EXPRESS | G55: Carroceria | H55: 23 | I55: =7000/30 -> 233.33333 | J55: 30 | K55: =IF(J55="", 0, 30 - J55) -> 0 | L55: =I55*J55 -> 7000 | M55: São Carlos
A56: 56 | B56: 45748 | C56: 44 | D56: 1 | E56: FFS0D23 | F56: VW EXPRESS | G56: Carroceria | H56: 23 | I56: =7000/30 -> 233.33333 | J56: 30 | K56: =IF(J56="", 0, 30 - J56) -> 0 | L56: =I56*J56 -> 7000 | M56: São Carlos
A57: 57 | B57: 45748 | C57: 40 | D57: 1 | E57: DPB8E26 | F57: VW EXPRESS | G57: Carroceria Cabinado | H57: 23 | I57: =7550/30 -> 251.66667 | J57: 30 | K57: =IF(J57="", 0, 30 - J57) -> 0 | L57: =I57*J57 -> 7550 | M57: São Carlos
A58: 58 | B58: 45748 | C58: 41 | D58: 1 | E58: DLG0D92 | F58: VW EXPRESS | G58: Carroceria Cabinado | H58: 22 | I58: =8500/30 -> 283.33333 | J58: 30 | K58: =IF(J58="", 0, 30 - J58) -> 0 | L58: =I58*J58 -> 8500 | M58: Mogi das Cruzes
A59: 59 | B59: 45748 | C59: 39 | D59: 1 | E59: EJX0I24 | F59: VW EXPRESS | G59: Carroceria Cabinado | H59: 22 | I59: =8500/30 -> 283.33333 | J59: 30 | K59: =IF(J59="", 0, 30 - J59) -> 0 | L59: =I59*J59 -> 8500 | M59: Mogi das Cruzes
A60: 60 | B60: 45748 | C60: 47 | D60: 1 | E60: CUG4B86 | F60: MB ATEGO | G60: Prancha Hidráulica | H60: 16 | I60: =15000/30 -> 500 | J60: 30 | K60: =IF(J60="", 0, 30 - J60) -> 0 | L60: =I60*J60 -> 15000 | M60: Osasco
A61: 61 | B61: 45748 | C61: 6 | D61: 1 | E61: EVF8I83 | F61: VW 13-180 | G61: Munck | H61: 14 | I61: =12000/30 -> 400 | J61: 5 | K61: =IF(J61="", 0, 30 - J61) -> 25 | L61: =I61*J61 -> 2000 | M61: Suzano
A62: 62 | B62: 45748 | C62: 7 | D62: 1 | E62: EUK4135 | F62: VW 9-150 | G62: Chassi | I62: 0 | J62: 0 | K62: =IF(J62="", 0, 30 - J62) -> 30 | L62: =I62*J62 -> 0 | M62: Parado
A63: 63 | B63: 45778 | C63: 24 | D63: 1 | E63: DYG5G03 | F63: VW 14-190 | G63: Munck | H63: 11 | I63: =12000/30 -> 400 | J63: 15 | K63: =IF(J63="", 0, 30 - J63) -> 15 | L63: =I63*J63 -> 6000 | M63: Suzano
A64: 64 | B64: 45778 | C64: 17 | D64: 1 | E64: BQV5264 | F64: CAT 416f2 | G64: Retroescavadeira | H64: 17 | I64: =10000/30 -> 333.33333 | J64: 30 | K64: =IF(J64="", 0, 30 - J64) -> 0 | L64: =I64*J64 -> 10000 | M64: Suzano
A65: 65 | B65: 45778 | C65: 20 | D65: 1 | E65: MAX4116 | F65: JCB 3CX | G65: Retroescavadeira | H65: 20 | I65: =12000/30 -> 400 | J65: 23 | K65: =IF(J65="", 0, 30 - J65) -> 7 | L65: 9333.34 | M65: Franca
A66: 66 | B66: 45778 | C66: 43 | D66: 1 | E66: CSU3F94 | F66: VW EXPRESS | G66: Carroceria | H66: 24 | I66: =7810/30 -> 260.33333 | J66: 30 | K66: =IF(J66="", 0, 30 - J66) -> 0 | L66: =I66*J66 -> 7810 | M66: Presidente Prudente
A67: 67 | B67: 45778 | C67: 42 | D67: 1 | E67: BSX5H07 | F67: VW EXPRESS | G67: Carroceria | H67: 24 | I67: =7810/30 -> 260.33333 | J67: 30 | K67: =IF(J67="", 0, 30 - J67) -> 0 | L67: =I67*J67 -> 7810 | M67: Presidente Prudente
A68: 68 | B68: 45778 | C68: 46 | D68: 1 | E68: CCU5G26 | F68: VW EXPRESS | G68: Carroceria | H68: 13 | I68: =7100/30 -> 236.66667 | J68: 30 | K68: =IF(J68="", 0, 30 - J68) -> 0 | L68: =I68*J68 -> 7100 | M68: Presidente Prudente
A69: 69 | B69: 45778 | C69: 34 | D69: 1 | E69: EXW7D65 | F69: VW 9-170 | G69: Caçamba | H69: 24 | I69: =9900/30 -> 330 | J69: 30 | K69: =IF(J69="", 0, 30 - J69) -> 0 | L69: =I69*J69 -> 9900 | M69: Presidente Prudente
A70: 70 | B70: 45778 | C70: 45 | D70: 1 | E70: EMN8B51 | F70: VW EXPRESS | G70: Carroceria | H70: 23 | I70: =7000/30 -> 233.33333 | J70: 30 | K70: =IF(J70="", 0, 30 - J70) -> 0 | L70: =I70*J70 -> 7000 | M70: São Carlos
A71: 71 | B71: 45778 | C71: 44 | D71: 1 | E71: FFS0D23 | F71: VW EXPRESS | G71: Carroceria | H71: 23 | I71: =7000/30 -> 233.33333 | J71: 30 | K71: =IF(J71="", 0, 30 - J71) -> 0 | L71: =I71*J71 -> 7000 | M71: São Carlos
A72: 72 | B72: 45778 | C72: 40 | D72: 1 | E72: DPB8E26 | F72: VW EXPRESS | G72: Carroceria Cabinado | H72: 23 | I72: =7550/30 -> 251.66667 | J72: 30 | K72: =IF(J72="", 0, 30 - J72) -> 0 | L72: =I72*J72 -> 7550 | M72: São Carlos
A73: 73 | B73: 45778 | C73: 41 | D73: 1 | E73: DLG0D92 | F73: VW EXPRESS | G73: Carroceria Cabinado | H73: 22 | I73: =8500/30 -> 283.33333 | J73: 30 | K73: =IF(J73="", 0, 30 - J73) -> 0 | L73: =I73*J73 -> 8500 | M73: Mogi das Cruzes
A74: 74 | B74: 45778 | C74: 39 | D74: 1 | E74: EJX0I24 | F74: VW EXPRESS | G74: Carroceria Cabinado | H74: 22 | I74: =8500/30 -> 283.33333 | J74: 30 | K74: =IF(J74="", 0, 30 - J74) -> 0 | L74: =I74*J74 -> 8500 | M74: Mogi das Cruzes
A75: 75 | B75: 45778 | C75: 47 | D75: 1 | E75: CUG4B86 | F75: MB ATEGO | G75: Prancha Hidráulica | H75: 16 | I75: =15000/30 -> 500 | J75: 30 | K75: =IF(J75="", 0, 30 - J75) -> 0 | L75: =I75*J75 -> 15000 | M75: Osasco
A76: 76 | B76: 45778 | C76: 7 | D76: 1 | E76: EUK4135 | F76: VW 9-150 | G76: Chassi | I76: 0 | J76: 0 | K76: =IF(J76="", 0, 30 - J76) -> 30 | L76: =I76*J76 -> 0 | M76: Parado
A77: 77 | B77: 45778 | C77: 6 | D77: 1 | E77: EVF8I83 | F77: VW 13-180 | G77: Munck | I77: 0 | J77: 0 | K77: =IF(J77="", 0, 30 - J77) -> 30 | L77: =I77*J77 -> 0 | M77: Parado
A78: 78 | B78: 45809 | C78: 24 | D78: 1 | E78: DYG5G03 | F78: VW 14-190 | G78: Munck | H78: 11 | I78: =12000/30 -> 400 | J78: 10 | K78: =IF(J78="", 0, 30 - J78) -> 20 | L78: =I78*J78 -> 4000 | M78: Suzano
A79: 79 | B79: 45809 | C79: 17 | D79: 1 | E79: BQV5264 | F79: CAT 416f2 | G79: Retroescavadeira | H79: 17 | I79: =10000/30 -> 333.33333 | J79: 30 | K79: =IF(J79="", 0, 30 - J79) -> 0 | L79: =I79*J79 -> 10000 | M79: Suzano
A80: 80 | B80: 45809 | C80: 20 | D80: 1 | E80: MAX4116 | F80: JCB 3CX | G80: Retroescavadeira | H80: 20 | I80: =12000/30 -> 400 | J80: 23 | K80: =IF(J80="", 0, 30 - J80) -> 7 | L80: 9334.34 | M80: Franca
A81: 81 | B81: 45809 | C81: 43 | D81: 1 | E81: CSU3F94 | F81: VW EXPRESS | G81: Carroceria | H81: 24 | I81: =7810/30 -> 260.33333 | J81: 30 | K81: =IF(J81="", 0, 30 - J81) -> 0 | L81: =I81*J81 -> 7810 | M81: Presidente Prudente
A82: 82 | B82: 45809 | C82: 42 | D82: 1 | E82: BSX5H07 | F82: VW EXPRESS | G82: Carroceria | H82: 24 | I82: =7810/30 -> 260.33333 | J82: 30 | K82: =IF(J82="", 0, 30 - J82) -> 0 | L82: =I82*J82 -> 7810 | M82: Presidente Prudente
A83: 83 | B83: 45809 | C83: 46 | D83: 1 | E83: CCU5G26 | F83: VW EXPRESS | G83: Carroceria | H83: 13 | I83: =7100/30 -> 236.66667 | J83: 30 | K83: =IF(J83="", 0, 30 - J83) -> 0 | L83: =I83*J83 -> 7100 | M83: Presidente Prudente
A84: 84 | B84: 45809 | C84: 34 | D84: 1 | E84: EXW7D65 | F84: VW 9-170 | G84: Caçamba | H84: 24 | I84: =9900/30 -> 330 | J84: 30 | K84: =IF(J84="", 0, 30 - J84) -> 0 | L84: =I84*J84 -> 9900 | M84: Presidente Prudente
A85: 85 | B85: 45809 | C85: 45 | D85: 1 | E85: EMN8B51 | F85: VW EXPRESS | G85: Carroceria | H85: 23 | I85: =7000/30 -> 233.33333 | J85: 30 | K85: =IF(J85="", 0, 30 - J85) -> 0 | L85: =I85*J85 -> 7000 | M85: São Carlos
A86: 86 | B86: 45809 | C86: 44 | D86: 1 | E86: FFS0D23 | F86: VW EXPRESS | G86: Carroceria | H86: 23 | I86: =7000/30 -> 233.33333 | J86: 30 | K86: =IF(J86="", 0, 30 - J86) -> 0 | L86: =I86*J86 -> 7000 | M86: São Carlos
A87: 87 | B87: 45809 | C87: 40 | D87: 1 | E87: DPB8E26 | F87: VW EXPRESS | G87: Carroceria Cabinado | H87: 23 | I87: =7550/30 -> 251.66667 | J87: 30 | K87: =IF(J87="", 0, 30 - J87) -> 0 | L87: =I87*J87 -> 7550 | M87: São Carlos
A88: 88 | B88: 45809 | C88: 41 | D88: 1 | E88: DLG0D92 | F88: VW EXPRESS | G88: Carroceria Cabinado | H88: 22 | I88: =8500/30 -> 283.33333 | J88: 18 | K88: =IF(J88="", 0, 30 - J88) -> 12 | L88: =I88*J88 -> 5100 | M88: Mogi das Cruzes
A89: 89 | B89: 45809 | C89: 39 | D89: 1 | E89: EJX0I24 | F89: VW EXPRESS | G89: Carroceria Cabinado | H89: 22 | I89: =8500/30 -> 283.33333 | J89: 16 | K89: =IF(J89="", 0, 30 - J89) -> 14 | L89: =I89*J89 -> 4533.3333 | M89: Mogi das Cruzes
A90: 90 | B90: 45809 | C90: 47 | D90: 1 | E90: CUG4B86 | F90: MB ATEGO | G90: Prancha Hidráulica | H90: 16 | I90: =15000/30 -> 500 | J90: 30 | K90: =IF(J90="", 0, 30 - J90) -> 0 | L90: =I90*J90 -> 15000 | M90: Osasco
A91: 91 | B91: 45809 | C91: 6 | D91: 1 | E91: EVF8I83 | F91: VW 13-180 | G91: Munck | H91: 14 | I91: =12000/30 -> 400 | J91: 8 | K91: =IF(J91="", 0, 30 - J91) -> 22 | L91: =I91*J91 -> 3200 | M91: Suzano
A92: 92 | B92: 45839 | C92: 24 | D92: 1 | E92: DYG5G03 | F92: VW 14-190 | G92: Munck | H92: 11 | I92: =12000/30 -> 400 | J92: 25 | K92: =IF(J92="", 0, 30 - J92) -> 5 | L92: =I92*J92 -> 10000 | M92: Suzano
A93: 93 | B93: 45839 | C93: 17 | D93: 1 | E93: BQV5264 | F93: CAT 416f2 | G93: Retroescavadeira | H93: 17 | I93: =10000/30 -> 333.33333 | J93: 30 | K93: =IF(J93="", 0, 30 - J93) -> 0 | L93: =I93*J93 -> 10000 | M93: Suzano
A94: 94 | B94: 45839 | C94: 20 | D94: 1 | E94: MAX4116 | F94: JCB 3CX | G94: Retroescavadeira | H94: 20 | I94: =12000/30 -> 400 | J94: 23 | K94: =IF(J94="", 0, 30 - J94) -> 7 | L94: 9333.32 | M94: Franca
A95: 95 | B95: 45839 | C95: 43 | D95: 1 | E95: CSU3F94 | F95: VW EXPRESS | G95: Carroceria | H95: 24 | I95: =7810/30 -> 260.33333 | J95: 30 | K95: =IF(J95="", 0, 30 - J95) -> 0 | L95: =I95*J95 -> 7810 | M95: Presidente Prudente
A96: 96 | B96: 45839 | C96: 42 | D96: 1 | E96: BSX5H07 | F96: VW EXPRESS | G96: Carroceria | H96: 24 | I96: =7810/30 -> 260.33333 | J96: 30 | K96: =IF(J96="", 0, 30 - J96) -> 0 | L96: =I96*J96 -> 7810 | M96: Presidente Prudente
A97: 97 | B97: 45839 | C97: 46 | D97: 1 | E97: CCU5G26 | F97: VW EXPRESS | G97: Carroceria | H97: 25 | I97: =7810/30 -> 260.33333 | J97: 30 | K97: =IF(J97="", 0, 30 - J97) -> 0 | L97: =I97*J97 -> 7810 | M97: Presidente Prudente
A98: 98 | B98: 45839 | C98: 34 | D98: 1 | E98: EXW7D65 | F98: VW 9-170 | G98: Caçamba | H98: 24 | I98: =9900/30 -> 330 | J98: 30 | K98: =IF(J98="", 0, 30 - J98) -> 0 | L98: =I98*J98 -> 9900 | M98: Presidente Prudente
A99: 99 | B99: 45839 | C99: 45 | D99: 1 | E99: EMN8B51 | F99: VW EXPRESS | G99: Carroceria | H99: 23 | I99: =7000/30 -> 233.33333 | J99: 30 | K99: =IF(J99="", 0, 30 - J99) -> 0 | L99: =I99*J99 -> 7000 | M99: São Carlos
A100: 100 | B100: 45839 | C100: 44 | D100: 1 | E100: FFS0D23 | F100: VW EXPRESS | G100: Carroceria | H100: 23 | I100: =7000/30 -> 233.33333 | J100: 30 | K100: =IF(J100="", 0, 30 - J100) -> 0 | L100: =I100*J100 -> 7000 | M100: São Carlos
...

Sheet 🧾 FATURAMENTO
A1: IDFatura | B1: Medicao | C1: IDEmpresa | D1: IDContrato | E1: IDCliente | F1: Fatura | G1: Emissão | H1: Vencimento | I1: Empresa | J1: ValorLocacoes | K1: DataEntrada | L1: ValorRecebido | M1: Encargos | N1: FormaRecebimento | O1: StatusRecebimento | P1: DocumentoRede
A2: 1 | B2: 45627 | C2: 1 | D2: 10;13 | E2: 9 | F2: 256 | G2: 45659 | H2: 45663 | I2: =IF(E2="","",_xlfn.XLOOKUP(E2,'🏢 CLIENTES'!A:A,'🏢 CLIENTES'!B:B,"")) -> Polemica Servicos Basicos LTDA | J2: 30300 | K2: 45663 | L2: 30300 | M2: =IF(OR(L2=0,L2=""),0,L2-J2) -> 0 | N2: Boleto | O2: Recebido
A3: 2 | B3: 45627 | C3: 1 | D3: 20 | E3: 8 | F3: 257 | G3: 45659 | H3: 45663 | I3: =IF(E3="","",_xlfn.XLOOKUP(E3,'🏢 CLIENTES'!A:A,'🏢 CLIENTES'!B:B,"")) -> Consorcio Global Franca | J3: 12000 | K3: 45663 | L3: 12000 | M3: =IF(OR(L3=0,L3=""),0,L3-J3) -> 0 | N3: Boleto | O3: Recebido
A4: 4 | B4: 45627 | C4: 1 | D4: 14;17 | E4: 11 | F4: 255 | G4: 45659 | H4: 45663 | I4: =IF(E4="","",_xlfn.XLOOKUP(E4,'🏢 CLIENTES'!A:A,'🏢 CLIENTES'!B:B,"")) -> Zigurate Construcao LTDA | J4: 22000 | K4: 45678 | L4: 23100 | M4: =IF(OR(L4=0,L4=""),0,L4-J4) -> 1100 | N4: Pix | O4: Recebido
A5: 6 | B5: 45627 | C5: 1 | D5: 7 | E5: 2 | F5: 260 | G5: 45659 | H5: 45663 | I5: =IF(E5="","",_xlfn.XLOOKUP(E5,'🏢 CLIENTES'!A:A,'🏢 CLIENTES'!B:B,"")) -> Jwr Construcoes LTDA | J5: 2900 | K5: 45687 | L5: 2900 | M5: =IF(OR(L5=0,L5=""),0,L5-J5) -> 0 | N5: Pix | O5: Recebido
A6: 8 | B6: 45627 | C6: 1 | D6: 9 | E6: 4 | F6: 262 | G6: 45659 | H6: 45663 | I6: =IF(E6="","",_xlfn.XLOOKUP(E6,'🏢 CLIENTES'!A:A,'🏢 CLIENTES'!B:B,"")) -> Consorcio Gb Osasco Tiete | J6: 3000 | K6: =TODAY() -> 46152 | L6: 0 | M6: =IF(OR(L6=0,L6=""),0,L6-J6) -> 0 | N6: Pix | O6: Vencido
A7: 3 | B7: 45627 | C7: 1 | D7: 16 | E7: 7 | F7: 258 | G7: 45659 | H7: 45667 | I7: =IF(E7="","",_xlfn.XLOOKUP(E7,'🏢 CLIENTES'!A:A,'🏢 CLIENTES'!B:B,"")) -> Fibertec Engenharia LTDA | J7: 15000 | K7: 45667 | L7: 15000 | M7: =IF(OR(L7=0,L7=""),0,L7-J7) -> 0 | N7: Boleto | O7: Recebido
A8: 5 | B8: 45627 | C8: 1 | D8: 6 | E8: 1 | F8: 259 | G8: 45659 | H8: 45687 | I8: =IF(E8="","",_xlfn.XLOOKUP(E8,'🏢 CLIENTES'!A:A,'🏢 CLIENTES'!B:B,"")) -> Celebre Obras e Servicos LTDA | J8: 20000 | K8: 45687 | L8: 20000 | M8: =IF(OR(L8=0,L8=""),0,L8-J8) -> 0 | N8: Pix | O8: Recebido
A9: 7 | B9: 45627 | C9: 1 | D9: 15 | E9: 1 | F9: 261 | G9: 45659 | H9: 45691 | I9: =IF(E9="","",_xlfn.XLOOKUP(E9,'🏢 CLIENTES'!A:A,'🏢 CLIENTES'!B:B,"")) -> Celebre Obras e Servicos LTDA | J9: 16000 | K9: 45705 | L9: 16000 | M9: =IF(OR(L9=0,L9=""),0,L9-J9) -> 0 | N9: Pix | O9: Recebido
A10: 9 | B10: 45658 | C10: 1 | D10: 10;13 | E10: 9 | F10: 264 | G10: 45691 | H10: 45693 | I10: =IF(E10="","",_xlfn.XLOOKUP(E10,'🏢 CLIENTES'!A:A,'🏢 CLIENTES'!B:B,"")) -> Polemica Servicos Basicos LTDA | J10: 30300 | K10: 45693 | L10: 30300 | M10: =IF(OR(L10=0,L10=""),0,L10-J10) -> 0 | N10: Boleto | O10: Recebido
A11: 10 | B11: 45658 | C11: 1 | D11: 20 | E11: 8 | F11: 266 | G11: 45691 | H11: 45693 | I11: =IF(E11="","",_xlfn.XLOOKUP(E11,'🏢 CLIENTES'!A:A,'🏢 CLIENTES'!B:B,"")) -> Consorcio Global Franca | J11: 12000 | K11: 45693 | L11: 12000 | M11: =IF(OR(L11=0,L11=""),0,L11-J11) -> 0 | N11: Boleto | O11: Recebido
A12: 12 | B12: 45658 | C12: 1 | D12: 14;17 | E12: 11 | F12: 265 | G12: 45691 | H12: 45693 | I12: =IF(E12="","",_xlfn.XLOOKUP(E12,'🏢 CLIENTES'!A:A,'🏢 CLIENTES'!B:B,"")) -> Zigurate Construcao LTDA | J12: 22000 | K12: 45705 | L12: 24384.8 | M12: =IF(OR(L12=0,L12=""),0,L12-J12) -> 2384.8 | N12: Boleto | O12: Recebido
A13: 11 | B13: 45658 | C13: 1 | D13: 16 | E13: 7 | F13: 263 | G13: 45691 | H13: 45698 | I13: =IF(E13="","",_xlfn.XLOOKUP(E13,'🏢 CLIENTES'!A:A,'🏢 CLIENTES'!B:B,"")) -> Fibertec Engenharia LTDA | J13: 15000 | K13: 45702 | L13: 15759.76 | M13: =IF(OR(L13=0,L13=""),0,L13-J13) -> 759.76 | N13: Pix | O13: Recebido
A14: 14 | B14: 45658 | C14: 1 | D14: 19 | E14: 7 | F14: 267 | G14: 45698 | H14: 45708 | I14: =IF(E14="","",_xlfn.XLOOKUP(E14,'🏢 CLIENTES'!A:A,'🏢 CLIENTES'!B:B,"")) -> Fibertec Engenharia LTDA | J14: 8800 | K14: 45708 | L14: 8800 | M14: =IF(OR(L14=0,L14=""),0,L14-J14) -> 0 | N14: Boleto | O14: Recebido
A15: 13 | B15: 45658 | C15: 1 | D15: 6 | E15: 1 | F15: 268 | G15: 45691 | H15: 45716 | I15: =IF(E15="","",_xlfn.XLOOKUP(E15,'🏢 CLIENTES'!A:A,'🏢 CLIENTES'!B:B,"")) -> Celebre Obras e Servicos LTDA | J15: 20000 | K15: 45716 | L15: 20000 | M15: =IF(OR(L15=0,L15=""),0,L15-J15) -> 0 | N15: Boleto | O15: Recebido
A16: 15 | B16: 45658 | C16: 1 | D16: 7 | E16: 2 | F16: 269 | G16: 45698 | H16: 45716 | I16: =IF(E16="","",_xlfn.XLOOKUP(E16,'🏢 CLIENTES'!A:A,'🏢 CLIENTES'!B:B,"")) -> Jwr Construcoes LTDA | J16: 2126.67 | K16: 45716 | L16: 2126.67 | M16: =IF(OR(L16=0,L16=""),0,L16-J16) -> 0 | N16: Boleto | O16: Recebido
A17: 16 | B17: 45658 | C17: 1 | D17: 21 | E17: 1 | F17: 270 | G17: 45705 | H17: 45719 | I17: =IF(E17="","",_xlfn.XLOOKUP(E17,'🏢 CLIENTES'!A:A,'🏢 CLIENTES'!B:B,"")) -> Celebre Obras e Servicos LTDA | J17: 15466.67 | K17: 45728 | L17: 15466.67 | M17: =IF(OR(L17=0,L17=""),0,L17-J17) -> 0 | N17: Pix | O17: Recebido
A18: 17 | B18: 45689 | C18: 1 | D18: 10;13 | E18: 9 | F18: 271 | G18: 45717 | H18: 45721 | I18: =IF(E18="","",_xlfn.XLOOKUP(E18,'🏢 CLIENTES'!A:A,'🏢 CLIENTES'!B:B,"")) -> Polemica Servicos Basicos LTDA | J18: 30300 | K18: 45721 | L18: 30300 | M18: =IF(OR(L18=0,L18=""),0,L18-J18) -> 0 | N18: Boleto | O18: Recebido
A19: 18 | B19: 45689 | C19: 1 | D19: 20 | E19: 8 | F19: 273 | G19: 45717 | H19: 45721 | I19: =IF(E19="","",_xlfn.XLOOKUP(E19,'🏢 CLIENTES'!A:A,'🏢 CLIENTES'!B:B,"")) -> Consorcio Global Franca | J19: 11100 | K19: 45721 | L19: 11100 | M19: =IF(OR(L19=0,L19=""),0,L19-J19) -> 0 | N19: Boleto | O19: Recebido
A20: 19 | B20: 45689 | C20: 1 | D20: 16 | E20: 7 | F20: 274 | G20: 45717 | H20: 45726 | I20: =IF(E20="","",_xlfn.XLOOKUP(E20,'🏢 CLIENTES'!A:A,'🏢 CLIENTES'!B:B,"")) -> Fibertec Engenharia LTDA | J20: 15000 | K20: 45726 | L20: 15000 | M20: =IF(OR(L20=0,L20=""),0,L20-J20) -> 0 | N20: Boleto | O20: Recebido
A21: 20 | B21: 45689 | C21: 1 | D21: 14;17 | E21: 11 | F21: 272 | G21: 45717 | H21: 45726 | I21: =IF(E21="","",_xlfn.XLOOKUP(E21,'🏢 CLIENTES'!A:A,'🏢 CLIENTES'!B:B,"")) -> Zigurate Construcao LTDA | J21: 22000 | K21: 45735 | L21: 23100 | M21: =IF(OR(L21=0,L21=""),0,L21-J21) -> 1100 | N21: Pix | O21: Recebido
A22: 22 | B22: 45689 | C22: 1 | D22: 19 | E22: 7 | F22: 275 | G22: 45721 | H22: 45736 | I22: =IF(E22="","",_xlfn.XLOOKUP(E22,'🏢 CLIENTES'!A:A,'🏢 CLIENTES'!B:B,"")) -> Fibertec Engenharia LTDA | J22: 12000 | K22: 45750 | L22: 12000 | M22: =IF(OR(L22=0,L22=""),0,L22-J22) -> 0 | N22: Boleto | O22: Recebido
A23: 21 | B23: 45689 | C23: 1 | D23: 6 | E23: 1 | F23: 276 | G23: 45721 | H23: 45747 | I23: =IF(E23="","",_xlfn.XLOOKUP(E23,'🏢 CLIENTES'!A:A,'🏢 CLIENTES'!B:B,"")) -> Celebre Obras e Servicos LTDA | J23: 20000 | K23: 45747 | L23: 20000 | M23: =IF(OR(L23=0,L23=""),0,L23-J23) -> 0 | N23: Pix | O23: Recebido
A24: 23 | B24: 45689 | C24: 1 | D24: 21 | E24: 1 | F24: 277 | G24: 45733 | H24: 45748 | I24: =IF(E24="","",_xlfn.XLOOKUP(E24,'🏢 CLIENTES'!A:A,'🏢 CLIENTES'!B:B,"")) -> Celebre Obras e Servicos LTDA | J24: 16000 | K24: 45754 | L24: 16000 | M24: =IF(OR(L24=0,L24=""),0,L24-J24) -> 0 | N24: Pix | O24: Recebido
A25: 24 | B25: 45717 | C25: 1 | D25: 10;13 | E25: 9 | F25: 278 | G25: 45748 | H25: 45752 | I25: =IF(E25="","",_xlfn.XLOOKUP(E25,'🏢 CLIENTES'!A:A,'🏢 CLIENTES'!B:B,"")) -> Polemica Servicos Basicos LTDA | J25: 30300 | K25: 45752 | L25: 30300 | M25: =IF(OR(L25=0,L25=""),0,L25-J25) -> 0 | N25: Boleto | O25: Recebido
A26: 25 | B26: 45717 | C26: 1 | D26: 20 | E26: 8 | F26: 280 | G26: 45748 | H26: 45755 | I26: =IF(E26="","",_xlfn.XLOOKUP(E26,'🏢 CLIENTES'!A:A,'🏢 CLIENTES'!B:B,"")) -> Consorcio Global Franca | J26: 12000 | K26: 45755 | L26: 12000 | M26: =IF(OR(L26=0,L26=""),0,L26-J26) -> 0 | N26: Boleto | O26: Recebido
A27: 26 | B27: 45717 | C27: 1 | D27: 16 | E27: 7 | F27: 282 | G27: 45748 | H27: 45757 | I27: =IF(E27="","",_xlfn.XLOOKUP(E27,'🏢 CLIENTES'!A:A,'🏢 CLIENTES'!B:B,"")) -> Fibertec Engenharia LTDA | J27: 15000 | K27: 45757 | L27: 15000 | M27: =IF(OR(L27=0,L27=""),0,L27-J27) -> 0 | N27: Boleto | O27: Recebido
A28: 27 | B28: 45717 | C28: 1 | D28: 14;17 | E28: 11 | F28: 279 | G28: 45748 | H28: 45757 | I28: =IF(E28="","",_xlfn.XLOOKUP(E28,'🏢 CLIENTES'!A:A,'🏢 CLIENTES'!B:B,"")) -> Zigurate Construcao LTDA | J28: 22000 | K28: 45763 | L28: 24273.32 | M28: =IF(OR(L28=0,L28=""),0,L28-J28) -> 2273.32 | N28: Boleto | O28: Recebido
A29: 28 | B29: 45717 | C29: 1 | D29: 19 | E29: 7 | F29: 283 | G29: 45748 | H29: 45767 | I29: =IF(E29="","",_xlfn.XLOOKUP(E29,'🏢 CLIENTES'!A:A,'🏢 CLIENTES'!B:B,"")) -> Fibertec Engenharia LTDA | J29: 3200 | K29: 45770 | L29: 3200 | M29: =IF(OR(L29=0,L29=""),0,L29-J29) -> 0 | N29: Boleto | O29: Recebido
A30: 29 | B30: 45717 | C30: 1 | D30: 6 | E30: 1 | F30: 281 | G30: 45748 | H30: 45777 | I30: =IF(E30="","",_xlfn.XLOOKUP(E30,'🏢 CLIENTES'!A:A,'🏢 CLIENTES'!B:B,"")) -> Celebre Obras e Servicos LTDA | J30: 20000 | K30: 45777 | L30: 20000 | M30: =IF(OR(L30=0,L30=""),0,L30-J30) -> 0 | N30: Pix | O30: Recebido
A31: 30 | B31: 45717 | C31: 1 | D31: 22 | E31: 1 | F31: 284 | G31: 45764 | H31: 45778 | I31: =IF(E31="","",_xlfn.XLOOKUP(E31,'🏢 CLIENTES'!A:A,'🏢 CLIENTES'!B:B,"")) -> Celebre Obras e Servicos LTDA | J31: 17000 | K31: 45783 | L31: 17000 | M31: =IF(OR(L31=0,L31=""),0,L31-J31) -> 0 | N31: Pix | O31: Recebido
A32: 31 | B32: 45748 | C32: 1 | D32: 10;13 | E32: 9 | F32: 285 | G32: 45778 | H32: 45782 | I32: =IF(E32="","",_xlfn.XLOOKUP(E32,'🏢 CLIENTES'!A:A,'🏢 CLIENTES'!B:B,"")) -> Polemica Servicos Basicos LTDA | J32: 30300 | K32: 45782 | L32: 30300 | M32: =IF(OR(L32=0,L32=""),0,L32-J32) -> 0 | N32: Boleto | O32: Recebido
A33: 32 | B33: 45748 | C33: 1 | D33: 20 | E33: 8 | F33: 287 | G33: 45778 | H33: 45785 | I33: =IF(E33="","",_xlfn.XLOOKUP(E33,'🏢 CLIENTES'!A:A,'🏢 CLIENTES'!B:B,"")) -> Consorcio Global Franca | J33: 12000 | K33: 45785 | L33: 12000 | M33: =IF(OR(L33=0,L33=""),0,L33-J33) -> 0 | N33: Boleto | O33: Recebido
A34: 34 | B34: 45748 | C34: 1 | D34: 14;17 | E34: 11 | F34: 286 | G34: 45778 | H34: 45786 | I34: =IF(E34="","",_xlfn.XLOOKUP(E34,'🏢 CLIENTES'!A:A,'🏢 CLIENTES'!B:B,"")) -> Zigurate Construcao LTDA | J34: 24000 | K34: 45796 | L34: 26560 | M34: =IF(OR(L34=0,L34=""),0,L34-J34) -> 2560 | N34: Boleto | O34: Recebido
A35: 33 | B35: 45748 | C35: 1 | D35: 16 | E35: 7 | F35: 289 | G35: 45778 | H35: 45787 | I35: =IF(E35="","",_xlfn.XLOOKUP(E35,'🏢 CLIENTES'!A:A,'🏢 CLIENTES'!B:B,"")) -> Fibertec Engenharia LTDA | J35: 15000 | K35: 45792 | L35: 16560 | M35: =IF(OR(L35=0,L35=""),0,L35-J35) -> 1560 | N35: Pix | O35: Recebido
A36: 35 | B36: 45748 | C36: 1 | D36: 23 | E36: 1 | F36: 288 | G36: 45778 | H36: 45807 | I36: =IF(E36="","",_xlfn.XLOOKUP(E36,'🏢 CLIENTES'!A:A,'🏢 CLIENTES'!B:B,"")) -> Celebre Obras e Servicos LTDA | J36: 21550 | K36: 45807 | L36: 21550 | M36: =IF(OR(L36=0,L36=""),0,L36-J36) -> 0 | N36: Pix | O36: Recebido
A37: 36 | B37: 45748 | C37: 1 | D37: 22 | E37: 1 | F37: 290 | G37: 45793 | H37: 45809 | I37: =IF(E37="","",_xlfn.XLOOKUP(E37,'🏢 CLIENTES'!A:A,'🏢 CLIENTES'!B:B,"")) -> Celebre Obras e Servicos LTDA | J37: 17000 | K37: 45814 | L37: 17000 | M37: =IF(OR(L37=0,L37=""),0,L37-J37) -> 0 | N37: Pix | O37: Recebido
A38: 37 | B38: 45778 | C38: 1 | D38: 13;24 | E38: 9 | F38: 291 | G38: 45809 | H38: 45813 | I38: =IF(E38="","",_xlfn.XLOOKUP(E38,'🏢 CLIENTES'!A:A,'🏢 CLIENTES'!B:B,"")) -> Polemica Servicos Basicos LTDA | J38: 32620 | K38: 45813 | L38: 32620 | M38: =IF(OR(L38=0,L38=""),0,L38-J38) -> 0 | N38: Boleto | O38: Recebido
A39: 38 | B39: 45778 | C39: 1 | D39: 20 | E39: 8 | F39: 293 | G39: 45809 | H39: 45816 | I39: =IF(E39="","",_xlfn.XLOOKUP(E39,'🏢 CLIENTES'!A:A,'🏢 CLIENTES'!B:B,"")) -> Consorcio Global Franca | J39: 9333.34 | K39: 45819 | L39: 9538.65 | M39: =IF(OR(L39=0,L39=""),0,L39-J39) -> 205.31 | N39: Boleto | O39: Recebido
A40: 39 | B40: 45778 | C40: 1 | D40: 14;17 | E40: 11 | F40: 292 | G40: 45809 | H40: 45817 | I40: =IF(E40="","",_xlfn.XLOOKUP(E40,'🏢 CLIENTES'!A:A,'🏢 CLIENTES'!B:B,"")) -> Zigurate Construcao LTDA | J40: 16000 | K40: 45825 | L40: 17685.28 | M40: =IF(OR(L40=0,L40=""),0,L40-J40) -> 1685.28 | N40: Pix | O40: Recebido
A41: 40 | B41: 45778 | C41: 1 | D41: 16 | E41: 7 | F41: 295 | G41: 45809 | H41: 45818 | I41: =IF(E41="","",_xlfn.XLOOKUP(E41,'🏢 CLIENTES'!A:A,'🏢 CLIENTES'!B:B,"")) -> Fibertec Engenharia LTDA | J41: 15000 | K41: 45831 | L41: 16550 | M41: =IF(OR(L41=0,L41=""),0,L41-J41) -> 1550 | N41: Pix | O41: Recebido
A42: 41 | B42: 45778 | C42: 1 | D42: 23 | E42: 1 | F42: 294 | G42: 45810 | H42: 45838 | I42: =IF(E42="","",_xlfn.XLOOKUP(E42,'🏢 CLIENTES'!A:A,'🏢 CLIENTES'!B:B,"")) -> Celebre Obras e Servicos LTDA | J42: 21550 | K42: 45838 | L42: 21550 | M42: =IF(OR(L42=0,L42=""),0,L42-J42) -> 0 | N42: Pix | O42: Recebido
A43: 42 | B43: 45778 | C43: 1 | D43: 22 | E43: 1 | F43: 296 | G43: 45824 | H43: 45839 | I43: =IF(E43="","",_xlfn.XLOOKUP(E43,'🏢 CLIENTES'!A:A,'🏢 CLIENTES'!B:B,"")) -> Celebre Obras e Servicos LTDA | J43: 17000 | K43: 45840 | L43: 17000 | M43: =IF(OR(L43=0,L43=""),0,L43-J43) -> 0 | N43: Pix | O43: Recebido
A44: 43 | B44: 45809 | C44: 1 | D44: 13;24 | E44: 9 | F44: 297 | G44: 45839 | H44: 45843 | I44: =IF(E44="","",_xlfn.XLOOKUP(E44,'🏢 CLIENTES'!A:A,'🏢 CLIENTES'!B:B,"")) -> Polemica Servicos Basicos LTDA | J44: 32620 | K44: 45843 | L44: 32620 | M44: =IF(OR(L44=0,L44=""),0,L44-J44) -> 0 | N44: Boleto | O44: Recebido
A45: 44 | B45: 45809 | C45: 1 | D45: 14;17 | E45: 11 | F45: 298 | G45: 45839 | H45: 45845 | I45: =IF(E45="","",_xlfn.XLOOKUP(E45,'🏢 CLIENTES'!A:A,'🏢 CLIENTES'!B:B,"")) -> Zigurate Construcao LTDA | J45: 17200 | K45: 45845 | L45: 17200 | M45: =IF(OR(L45=0,L45=""),0,L45-J45) -> 0 | N45: Boleto | O45: Recebido
A46: 45 | B46: 45809 | C46: 1 | D46: 20 | E46: 8 | F46: 299 | G46: 45839 | H46: 45846 | I46: =IF(E46="","",_xlfn.XLOOKUP(E46,'🏢 CLIENTES'!A:A,'🏢 CLIENTES'!B:B,"")) -> Consorcio Global Franca | J46: 9334.34 | K46: 45846 | L46: 9334.34 | M46: =IF(OR(L46=0,L46=""),0,L46-J46) -> 0 | N46: Boleto | O46: Recebido
A47: 46 | B47: 45809 | C47: 1 | D47: 16 | E47: 7 | F47: 300 | G47: 45839 | H47: 45848 | I47: =IF(E47="","",_xlfn.XLOOKUP(E47,'🏢 CLIENTES'!A:A,'🏢 CLIENTES'!B:B,"")) -> Fibertec Engenharia LTDA | J47: 15000 | K47: 45854 | L47: 15000 | M47: =IF(OR(L47=0,L47=""),0,L47-J47) -> 0 | N47: Pix | O47: Recebido
A48: 47 | B48: 45809 | C48: 1 | D48: 23 | E48: 1 | F48: 301 | G48: 45839 | H48: 45868 | I48: =IF(E48="","",_xlfn.XLOOKUP(E48,'🏢 CLIENTES'!A:A,'🏢 CLIENTES'!B:B,"")) -> Celebre Obras e Servicos LTDA | J48: 21550 | K48: 45868 | L48: 21550 | M48: =IF(OR(L48=0,L48=""),0,L48-J48) -> 0 | N48: Pix | O48: Recebido
A49: 48 | B49: 45809 | C49: 1 | D49: 22 | E49: 1 | F49: 302 | G49: 45861 | H49: 45870 | I49: =IF(E49="","",_xlfn.XLOOKUP(E49,'🏢 CLIENTES'!A:A,'🏢 CLIENTES'!B:B,"")) -> Celebre Obras e Servicos LTDA | J49: 9633.33 | K49: 45874 | L49: 9633.33 | M49: =IF(OR(L49=0,L49=""),0,L49-J49) -> 0 | N49: Pix | O49: Recebido
A50: 49 | B50: 45839 | C50: 1 | D50: 24;25 | E50: 9 | F50: 303 | G50: 45870 | H50: 45874 | I50: =IF(E50="","",_xlfn.XLOOKUP(E50,'🏢 CLIENTES'!A:A,'🏢 CLIENTES'!B:B,"")) -> Polemica Servicos Basicos LTDA | J50: 33330 | K50: 45875 | L50: 33330 | M50: =IF(OR(L50=0,L50=""),0,L50-J50) -> 0 | N50: Pix | O50: Recebido
A51: 50 | B51: 45839 | C51: 1 | D51: 14;17 | E51: 11 | F51: 304 | G51: 45870 | H51: 45877 | I51: =IF(E51="","",_xlfn.XLOOKUP(E51,'🏢 CLIENTES'!A:A,'🏢 CLIENTES'!B:B,"")) -> Zigurate Construcao LTDA | J51: 29200 | K51: 45877 | L51: 29200 | M51: =IF(OR(L51=0,L51=""),0,L51-J51) -> 0 | N51: Boleto | O51: Recebido
A52: 51 | B52: 45839 | C52: 1 | D52: 20 | E52: 8 | F52: 305 | G52: 45870 | H52: 45877 | I52: =IF(E52="","",_xlfn.XLOOKUP(E52,'🏢 CLIENTES'!A:A,'🏢 CLIENTES'!B:B,"")) -> Consorcio Global Franca | J52: 9333.32 | K52: 45877 | L52: 9333.32 | M52: =IF(OR(L52=0,L52=""),0,L52-J52) -> 0 | N52: Boleto | O52: Recebido
A53: 52 | B53: 45839 | C53: 1 | D53: 16 | E53: 7 | F53: 307 | G53: 45870 | H53: 45879 | I53: =IF(E53="","",_xlfn.XLOOKUP(E53,'🏢 CLIENTES'!A:A,'🏢 CLIENTES'!B:B,"")) -> Fibertec Engenharia LTDA | J53: 15000 | K53: 45884 | L53: 15000 | M53: =IF(OR(L53=0,L53=""),0,L53-J53) -> 0 | N53: Pix | O53: Recebido
A54: 53 | B54: 45839 | C54: 1 | D54: 23 | E54: 1 | F54: 306 | G54: 45870 | H54: 45899 | I54: =IF(E54="","",_xlfn.XLOOKUP(E54,'🏢 CLIENTES'!A:A,'🏢 CLIENTES'!B:B,"")) -> Celebre Obras e Servicos LTDA | J54: 21550 | K54: 45899 | L54: 21550 | M54: =IF(OR(L54=0,L54=""),0,L54-J54) -> 0 | N54: Pix | O54: Recebido
A55: 54 | B55: 45839 | C55: 1 | D55: 22 | E55: 1 | F55: 308 | G55: 45887 | H55: 45901 | I55: =IF(E55="","",_xlfn.XLOOKUP(E55,'🏢 CLIENTES'!A:A,'🏢 CLIENTES'!B:B,"")) -> Celebre Obras e Servicos LTDA | J55: 17000 | K55: 45901 | L55: 17000 | M55: =IF(OR(L55=0,L55=""),0,L55-J55) -> 0 | N55: Pix | O55: Recebido
A56: 55 | B56: 45870 | C56: 1 | D56: 24;25 | E56: 9 | F56: 310 | G56: 45901 | H56: 45905 | I56: =IF(E56="","",_xlfn.XLOOKUP(E56,'🏢 CLIENTES'!A:A,'🏢 CLIENTES'!B:B,"")) -> Polemica Servicos Basicos LTDA | J56: 33330 | K56: 45905 | L56: 33330 | M56: =IF(OR(L56=0,L56=""),0,L56-J56) -> 0 | N56: Pix | O56: Recebido
A57: 56 | B57: 45870 | C57: 3 | D57: 28 | E57: 12 | F57: 103 | G57: 45901 | H57: 45908 | I57: =IF(E57="","",_xlfn.XLOOKUP(E57,'🏢 CLIENTES'!A:A,'🏢 CLIENTES'!B:B,"")) -> Consorcio Global Franca II | J57: 12000 | K57: 45908 | L57: 12000 | M57: =IF(OR(L57=0,L57=""),0,L57-J57) -> 0 | N57: Boleto | O57: Recebido
A58: 57 | B58: 45870 | C58: 1 | D58: 14;17 | E58: 11 | F58: 311 | G58: 45901 | H58: 45908 | I58: =IF(E58="","",_xlfn.XLOOKUP(E58,'🏢 CLIENTES'!A:A,'🏢 CLIENTES'!B:B,"")) -> Zigurate Construcao LTDA | J58: 27500 | K58: 45909 | L58: 28187.5 | M58: =IF(OR(L58=0,L58=""),0,L58-J58) -> 687.5 | N58: Boleto | O58: Recebido
A59: 58 | B59: 45870 | C59: 3 | D59: 27 | E59: 7 | F59: 101 | G59: 45901 | H59: 45910 | I59: =IF(E59="","",_xlfn.XLOOKUP(E59,'🏢 CLIENTES'!A:A,'🏢 CLIENTES'!B:B,"")) -> Fibertec Engenharia LTDA | J59: 18500 | K59: 45918 | L59: 20436.31 | M59: =IF(OR(L59=0,L59=""),0,L59-J59) -> 1936.31 | N59: Boleto | O59: Recebido
A60: 60 | B60: 45870 | C60: 3 | D60: 14;17 | E60: 11 | F60: 102 | G60: 45901 | H60: 45910 | I60: =IF(E60="","",_xlfn.XLOOKUP(E60,'🏢 CLIENTES'!A:A,'🏢 CLIENTES'!B:B,"")) -> Zigurate Construcao LTDA | J60: 0 | K60: 45910 | L60: 0 | M60: =IF(OR(L60=0,L60=""),0,L60-J60) -> 0 | N60: Boleto | O60: Cancelado
A61: 59 | B61: 45870 | C61: 1 | D61: 23 | E61: 1 | F61: 309 | G61: 45901 | H61: 45930 | I61: =IF(E61="","",_xlfn.XLOOKUP(E61,'🏢 CLIENTES'!A:A,'🏢 CLIENTES'!B:B,"")) -> Celebre Obras e Servicos LTDA | J61: 21550 | K61: 45940 | L61: 21550 | M61: =IF(OR(L61=0,L61=""),0,L61-J61) -> 0 | N61: Pix | O61: Recebido
A62: 61 | B62: 45870 | C62: 1 | D62: 22 | E62: 1 | F62: 312 | G62: 45917 | H62: 45931 | I62: =IF(E62="","",_xlfn.XLOOKUP(E62,'🏢 CLIENTES'!A:A,'🏢 CLIENTES'!B:B,"")) -> Celebre Obras e Servicos LTDA | J62: 17000 | K62: 45931 | L62: 17000 | M62: =IF(OR(L62=0,L62=""),0,L62-J62) -> 0 | N62: Pix | O62: Recebido
A63: 62 | B63: 45901 | C63: 3 | D63: 29 | E63: 9 | F63: 104 | G63: 45931 | H63: 45935 | I63: =IF(E63="","",_xlfn.XLOOKUP(E63,'🏢 CLIENTES'!A:A,'🏢 CLIENTES'!B:B,"")) -> Polemica Servicos Basicos LTDA | J63: 33330 | K63: 45935 | L63: 33330 | M63: =IF(OR(L63=0,L63=""),0,L63-J63) -> 0 | N63: Boleto | O63: Recebido
A64: 63 | B64: 45901 | C64: 3 | D64: 28 | E64: 12 | F64: 106 | G64: 45931 | H64: 45938 | I64: =IF(E64="","",_xlfn.XLOOKUP(E64,'🏢 CLIENTES'!A:A,'🏢 CLIENTES'!B:B,"")) -> Consorcio Global Franca II | J64: 12000 | K64: 45938 | L64: 12000 | M64: =IF(OR(L64=0,L64=""),0,L64-J64) -> 0 | N64: Boleto | O64: Recebido
A65: 65 | B65: 45901 | C65: 3 | D65: 26 | E65: 11 | F65: 105 | G65: 45931 | H65: 45938 | I65: =IF(E65="","",_xlfn.XLOOKUP(E65,'🏢 CLIENTES'!A:A,'🏢 CLIENTES'!B:B,"")) -> Zigurate Construcao LTDA | J65: 27500 | K65: 45950 | L65: 28875 | M65: =IF(OR(L65=0,L65=""),0,L65-J65) -> 1375 | N65: Boleto | O65: Recebido
A66: 64 | B66: 45901 | C66: 3 | D66: 27 | E66: 7 | F66: 107 | G66: 45931 | H66: 45940 | I66: =IF(E66="","",_xlfn.XLOOKUP(E66,'🏢 CLIENTES'!A:A,'🏢 CLIENTES'!B:B,"")) -> Fibertec Engenharia LTDA | J66: 18500 | K66: 45940 | L66: 18500 | M66: =IF(OR(L66=0,L66=""),0,L66-J66) -> 0 | N66: Boleto | O66: Recebido
A67: 66 | B67: 45901 | C67: 1 | D67: 23 | E67: 1 | F67: 313 | G67: 45931 | H67: 45960 | I67: =IF(E67="","",_xlfn.XLOOKUP(E67,'🏢 CLIENTES'!A:A,'🏢 CLIENTES'!B:B,"")) -> Celebre Obras e Servicos LTDA | J67: 21550 | K67: 45960 | L67: 21550 | M67: =IF(OR(L67=0,L67=""),0,L67-J67) -> 0 | N67: Pix | O67: Recebido
A68: 67 | B68: 45901 | C68: 1 | D68: 22 | E68: 1 | F68: 314 | G68: 45945 | H68: 45962 | I68: =IF(E68="","",_xlfn.XLOOKUP(E68,'🏢 CLIENTES'!A:A,'🏢 CLIENTES'!B:B,"")) -> Celebre Obras e Servicos LTDA | J68: 13316.67 | K68: 45964 | L68: 13316.67 | M68: =IF(OR(L68=0,L68=""),0,L68-J68) -> 0 | N68: Pix | O68: Recebido
A69: 69 | B69: 45931 | C69: 3 | D69: 29 | E69: 9 | F69: 108 | G69: 45965 | H69: 45966 | I69: =IF(E69="","",_xlfn.XLOOKUP(E69,'🏢 CLIENTES'!A:A,'🏢 CLIENTES'!B:B,"")) -> Polemica Servicos Basicos LTDA | J69: 33330 | K69: 45966 | L69: 33330 | M69: =IF(OR(L69=0,L69=""),0,L69-J69) -> 0 | N69: Boleto | O69: Recebido
A70: 68 | B70: 45931 | C70: 3 | D70: 28 | E70: 12 | F70: 110 | G70: 45962 | H70: 45969 | I70: =IF(E70="","",_xlfn.XLOOKUP(E70,'🏢 CLIENTES'!A:A,'🏢 CLIENTES'!B:B,"")) -> Consorcio Global Franca II | J70: 12500 | K70: 45978 | L70: 12500 | M70: =IF(OR(L70=0,L70=""),0,L70-J70) -> 0 | N70: Boleto | O70: Recebido
A71: 70 | B71: 45931 | C71: 3 | D71: 27 | E71: 7 | F71: 111 | G71: 45965 | H71: 45971 | I71: =IF(E71="","",_xlfn.XLOOKUP(E71,'🏢 CLIENTES'!A:A,'🏢 CLIENTES'!B:B,"")) -> Fibertec Engenharia LTDA | J71: 18500 | K71: 45980 | L71: 18550 | M71: =IF(OR(L71=0,L71=""),0,L71-J71) -> 50 | N71: Boleto | O71: Recebido
A72: 71 | B72: 45931 | C72: 3 | D72: 26 | E72: 11 | F72: 109 | G72: 45965 | H72: 45974 | I72: =IF(E72="","",_xlfn.XLOOKUP(E72,'🏢 CLIENTES'!A:A,'🏢 CLIENTES'!B:B,"")) -> Zigurate Construcao LTDA | J72: 25900 | K72: 45982 | L72: 27000 | M72: =IF(OR(L72=0,L72=""),0,L72-J72) -> 1100 | N72: Boleto | O72: Recebido
... A87: 86 | B87: 45992 | C87: 1 | D87: 23 | E87: 1 | F87: 321 | G87: 46024 | H87: 46052 | I87: =IF(E87="","",_xlfn.XLOOKUP(E87,'🏢 CLIENTES'!A:A,'🏢 CLIENTES'!B:B,"")) -> Celebre Obras e Servicos LTDA | J87: 21550 | K87: 46052 | L87: 21550 | M87: =IF(OR(L87=0,L87=""),0,L87-J87) -> 0 | N87: Pix | O87: Recebido
A88: 87 | B88: 46023 | C88: 1 | D88: 26 | E88: 11 | F88: 322 | G88: 46036 | H88: 46052 | I88: =IF(E88="","",_xlfn.XLOOKUP(E88,'🏢 CLIENTES'!A:A,'🏢 CLIENTES'!B:B,"")) -> Zigurate Construcao LTDA | J88: 0 | K88: =TODAY() -> 46152 | L88: 0 | M88: =IF(OR(L88=0,L88=""),0,L88-J88) -> 0 | N88: Boleto | O88: Cancelado
A89: 89 | B89: 46023 | C89: 3 | D89: 29 | E89: 9 | F89: 120 | G89: 46055 | H89: 46058 | I89: =IF(E89="","",_xlfn.XLOOKUP(E89,'🏢 CLIENTES'!A:A,'🏢 CLIENTES'!B:B,"")) -> Polemica Servicos Basicos LTDA | J89: 33330 | K89: 46058 | L89: 33330 | M89: =IF(OR(L89=0,L89=""),0,L89-J89) -> 0 | N89: Boleto | O89: Recebido
A90: 91 | B90: 46023 | C90: 3 | D90: 28 | E90: 12 | F90: 122 | G90: 46055 | H90: 46061 | I90: =IF(E90="","",_xlfn.XLOOKUP(E90,'🏢 CLIENTES'!A:A,'🏢 CLIENTES'!B:B,"")) -> Consorcio Global Franca II | J90: 12550 | K90: 46061 | L90: 12550 | M90: =IF(OR(L90=0,L90=""),0,L90-J90) -> 0 | N90: Boleto | O90: Recebido
A91: 92 | B91: 46023 | C91: 3 | D91: 27 | E91: 7 | F91: 123 | G91: 46055 | H91: 46063 | I91: =IF(E91="","",_xlfn.XLOOKUP(E91,'🏢 CLIENTES'!A:A,'🏢 CLIENTES'!B:B,"")) -> Fibertec Engenharia LTDA | J91: 18500 | K91: 46064 | L91: 20362.33 | M91: =IF(OR(L91=0,L91=""),0,L91-J91) -> 1862.33 | N91: Boleto | O91: Recebido
A92: 88 | B92: 46023 | C92: 1 | D92: 31 | E92: 1 | F92: 323 | G92: 46037 | H92: 46068 | I92: =IF(E92="","",_xlfn.XLOOKUP(E92,'🏢 CLIENTES'!A:A,'🏢 CLIENTES'!B:B,"")) -> Celebre Obras e Servicos LTDA | J92: 10050 | K92: 46073 | L92: 10565.89 | M92: =IF(OR(L92=0,L92=""),0,L92-J92) -> 515.89 | N92: Boleto | O92: Recebido
A93: 90 | B93: 46023 | C93: 3 | D93: 26 | E93: 11 | F93: 121 | G93: 46055 | H93: 46068 | I93: =IF(E93="","",_xlfn.XLOOKUP(E93,'🏢 CLIENTES'!A:A,'🏢 CLIENTES'!B:B,"")) -> Zigurate Construcao LTDA | J93: 27500 | K93: 46072 | L93: 28550 | M93: =IF(OR(L93=0,L93=""),0,L93-J93) -> 1050 | N93: Boleto | O93: Recebido
A94: 93 | B94: 46023 | C94: 1 | D94: 23 | E94: 1 | F94: 324 | G94: 46063 | H94: 46081 | I94: =IF(E94="","",_xlfn.XLOOKUP(E94,'🏢 CLIENTES'!A:A,'🏢 CLIENTES'!B:B,"")) -> Celebre Obras e Servicos LTDA | J94: 18026.72 | K94: 46081 | L94: 18026.72 | M94: =IF(OR(L94=0,L94=""),0,L94-J94) -> 0 | N94: Pix | O94: Recebido
A95: 96 | B95: 46054 | C95: 3 | D95: 29 | E95: 9 | F95: 124 | G95: 46083 | H95: 46086 | I95: =IF(E95="","",_xlfn.XLOOKUP(E95,'🏢 CLIENTES'!A:A,'🏢 CLIENTES'!B:B,"")) -> Polemica Servicos Basicos LTDA | J95: 32918.9 | K95: 46090 | L95: =J95+3381.9 -> 36300.8 | M95: =IF(OR(L95=0,L95=""),0,L95-J95) -> 3381.9 | N95: Boleto | O95: Recebido
A96: 98 | B96: 46054 | C96: 3 | D96: 28 | E96: 12 | F96: 126 | G96: 46083 | H96: 46089 | I96: =IF(E96="","",_xlfn.XLOOKUP(E96,'🏢 CLIENTES'!A:A,'🏢 CLIENTES'!B:B,"")) -> Consorcio Global Franca II | J96: 12550 | K96: 46098 | L96: 13252.77 | M96: =IF(OR(L96=0,L96=""),0,L96-J96) -> 702.77 | N96: Boleto | O96: Recebido
A97: 99 | B97: 46054 | C97: 3 | D97: 27 | E97: 7 | F97: 127 | G97: 46083 | H97: 46091 | I97: =IF(E97="","",_xlfn.XLOOKUP(E97,'🏢 CLIENTES'!A:A,'🏢 CLIENTES'!B:B,"")) -> Fibertec Engenharia LTDA | J97: 18500 | K97: 46100 | L97: 18500 | M97: =IF(OR(L97=0,L97=""),0,L97-J97) -> 0 | N97: Boleto | O97: Recebido
A98: 97 | B98: 46054 | C98: 3 | D98: 26 | E98: 11 | F98: 125 | G98: 46083 | H98: 46094 | I98: =IF(E98="","",_xlfn.XLOOKUP(E98,'🏢 CLIENTES'!A:A,'🏢 CLIENTES'!B:B,"")) -> Zigurate Construcao LTDA | J98: 27500 | K98: =TODAY() -> 46152 | L98: 28000 | M98: =IF(OR(L98=0,L98=""),0,L98-J98) -> 500 | N98: Boleto | O98: Recebido
A99: 94 | B99: 46054 | C99: 1 | D99: 31 | E99: 1 | F99: 325 | G99: 46072 | H99: 46096 | I99: =IF(E99="","",_xlfn.XLOOKUP(E99,'🏢 CLIENTES'!A:A,'🏢 CLIENTES'!B:B,"")) -> Celebre Obras e Servicos LTDA | J99: 10050 | K99: 46097 | L99: 10562.55 | M99: =IF(OR(L99=0,L99=""),0,L99-J99) -> 512.55 | N99: Boleto | O99: Recebido
A100: 95 | B100: 46054 | C100: 1 | D100: 31 | E100: 1 | F100: 326 | G100: 46072 | H100: 46096 | I100: =IF(E100="","",_xlfn.XLOOKUP(E100,'🏢 CLIENTES'!A:A,'🏢 CLIENTES'!B:B,"")) -> Celebre Obras e Servicos LTDA | J100: 5025 | K100: 46097 | L100: 5281.27 | M100: =IF(OR(L100=0,L100=""),0,L100-J100) -> 256.27 | N100: Boleto | O100: Recebido
A101: 100 | B101: 46054 | C101: 1 | D101: 23 | E101: 1 | F101: 327 | G101: 46086 | H101: 46111 | I101: =IF(E101="","",_xlfn.XLOOKUP(E101,'🏢 CLIENTES'!A:A,'🏢 CLIENTES'!B:B,"")) -> Celebre Obras e Servicos LTDA | J101: 21550 | K101: 46111 | L101: 21550 | M101: =IF(OR(L101=0,L101=""),0,L101-J101) -> 0 | N101: Pix | O101: Recebido
A102: 101 | B102: 46054 | C102: 1 | D102: 32 | E102: 16 | F102: 328 | G102: 46086 | H102: 46111 | I102: =IF(E102="","",_xlfn.XLOOKUP(E102,'🏢 CLIENTES'!A:A,'🏢 CLIENTES'!B:B,"")) -> Angra Construcoes e Saneamento LTDA | J102: 4795 | K102: 46111 | L102: 4795 | M102: =IF(OR(L102=0,L102=""),0,L102-J102) -> 0 | N102: Boleto | O102: Recebido
A103: 103 | B103: 46082 | C103: 3 | D103: 29 | E103: 9 | F103: 128 | G103: 46083 | H103: 46117 | I103: =IF(E103="","",_xlfn.XLOOKUP(E103,'🏢 CLIENTES'!A:A,'🏢 CLIENTES'!B:B,"")) -> Polemica Servicos Basicos LTDA | J103: 32918.9 | K103: 46117 | L103: 32918.9 | M103: =IF(OR(L103=0,L103=""),0,L103-J103) -> 0 | N103: Boleto | O103: Recebido
A104: 106 | B104: 46082 | C104: 3 | D104: 28 | E104: 12 | F104: 131 | G104: 46083 | H104: 46120 | I104: =IF(E104="","",_xlfn.XLOOKUP(E104,'🏢 CLIENTES'!A:A,'🏢 CLIENTES'!B:B,"")) -> Consorcio Global Franca II | J104: 12550 | K104: 46120 | L104: 12550 | M104: =IF(OR(L104=0,L104=""),0,L104-J104) -> 0 | N104: Boleto | O104: Recebido
A105: 107 | B105: 46082 | C105: 3 | D105: 33 | E105: 7 | F105: 132 | G105: 46083 | H105: 46122 | I105: =IF(E105="","",_xlfn.XLOOKUP(E105,'🏢 CLIENTES'!A:A,'🏢 CLIENTES'!B:B,"")) -> Fibertec Engenharia LTDA | J105: 20550 | K105: 46126 | L105: 20550 | M105: =IF(OR(L105=0,L105=""),0,L105-J105) -> 0 | N105: Boleto | O105: Recebido
A106: 105 | B106: 46082 | C106: 3 | D106: 26 | E106: 11 | F106: 130 | G106: 46083 | H106: 46125 | I106: =IF(E106="","",_xlfn.XLOOKUP(E106,'🏢 CLIENTES'!A:A,'🏢 CLIENTES'!B:B,"")) -> Zigurate Construcao LTDA | J106: 27550 | K106: 46135 | L106: 28000 | M106: =IF(OR(L106=0,L106=""),0,L106-J106) -> 450 | N106: Boleto | O106: Recebido
A107: 102 | B107: 46082 | C107: 1 | D107: 31 | E107: 1 | F107: 329 | G107: 46098 | H107: 46127 | I107: =IF(E107="","",_xlfn.XLOOKUP(E107,'🏢 CLIENTES'!A:A,'🏢 CLIENTES'!B:B,"")) -> Celebre Obras e Servicos LTDA | J107: =335*9 -> 3015 | K107: 46127 | L107: 3015 | M107: =IF(OR(L107=0,L107=""),0,L107-J107) -> 0 | N107: Boleto | O107: Recebido
A108: 104 | B108: 46082 | C108: 3 | D108: 34 | E108: 9 | F108: 129 | G108: 46083 | H108: 46127 | I108: =IF(E108="","",_xlfn.XLOOKUP(E108,'🏢 CLIENTES'!A:A,'🏢 CLIENTES'!B:B,"")) -> Polemica Servicos Basicos LTDA | J108: 9550 | K108: 46127 | L108: 9550 | M108: =IF(OR(L108=0,L108=""),0,L108-J108) -> 0 | N108: Boleto | O108: Recebido
A109: 109 | B109: 46082 | C109: 1 | D109: 35 | E109: 1 | F109: 330 | G109: 46086 | H109: 46142 | I109: =IF(E109="","",_xlfn.XLOOKUP(E109,'🏢 CLIENTES'!A:A,'🏢 CLIENTES'!B:B,"")) -> Celebre Obras e Servicos LTDA | J109: 21550 | K109: 46142 | L109: 21550 | M109: =IF(OR(L109=0,L109=""),0,L109-J109) -> 0 | N109: Pix | O109: Recebido
A110: 110 | B110: 46082 | C110: 1 | D110: 32 | E110: 16 | F110: 331 | G110: 46086 | H110: 46142 | I110: =IF(E110="","",_xlfn.XLOOKUP(E110,'🏢 CLIENTES'!A:A,'🏢 CLIENTES'!B:B,"")) -> Angra Construcoes e Saneamento LTDA | J110: 6650 | L110: 0 | M110: =IF(OR(L110=0,L110=""),0,L110-J110) -> 0 | N110: Boleto | O110: Pendente

Sheet ↩️ REEMBOLSOS
A1: IDReembolso | B1: Tipo | C1: IDEmpresa | D1: IDContrato | E1: IDCliente | F1: IDVeiculo | G1: IDOrdServ | H1: IDMulta | I1: Recibo | J1: Emissão | K1: Vencimento | L1: Empresa | M1: ValorReembolso | N1: DataEntrada | O1: ValorRecebido | P1: Encargos de Faturamento | Q1: FormaRecebimento | R1: StatusRecebimento | S1: DocumentoRede
A2: 1 | B2: Transporte | C2: 1 | D2: 20 | E2: 8 | F2: 20 | I2: 12003 | J2: 45659 | K2: 45663 | L2: Consorcio Global Franca | M2: 2333.33 | N2: 45663 | O2: 2333.33 | P2: =IF(OR(O2=0,O2=""),0,O2-M2) -> 0 | Q2: Boleto | R2: Recebido
A3: 2 | B3: Multa de Trânsito | C3: 1 | D3: 9 | E3: 4 | F3: 6 | I3: 12004 | J3: 45674 | K3: 45687 | L3: Consorcio Gb Osasco Tiete | M3: 2010.28 | O3: 0 | P3: =IF(OR(O3=0,O3=""),0,O3-M3) -> 0 | Q3: Pix | R3: Vencido
A4: 3 | B4: Manutenção | C4: 1 | D4: 15 | E4: 1 | I4: 12005 | J4: 45659 | K4: 45691 | L4: Celebre Obras e Servicos LTDA | M4: 1669.389 | O4: 0 | P4: =IF(OR(O4=0,O4=""),0,O4-M4) -> 0 | Q4: Pix | R4: Cancelado
A5: 4 | B5: Franquia de Seguro | C5: 1 | D5: 13 | E5: 9 | F5: 46 | I5: 12006 | J5: 45691 | K5: 45693 | L5: Polemica Servicos Basicos LTDA | M5: 547 | N5: 45693 | O5: 547 | P5: =IF(OR(O5=0,O5=""),0,O5-M5) -> 0 | Q5: Boleto | R5: Recebido
A6: 5 | B6: Manutenção | C6: 1 | D6: 17 | E6: 11 | F6: 17 | I6: 12007 | J6: 45691 | K6: 45693 | L6: Zigurate Construcao LTDA | M6: 1100 | N6: 45693 | O6: 1100 | P6: =IF(OR(O6=0,O6=""),0,O6-M6) -> 0 | Q6: Boleto | R6: Recebido
A7: 6 | B7: Multa de Trânsito | C7: 1 | D7: 16 | E7: 7 | F7: 47 | I7: 12008 | J7: 45691 | K7: 45698 | L7: Fibertec Engenharia LTDA | M7: 195.23 | N7: 45698 | O7: 195.23 | P7: =IF(OR(O7=0,O7=""),0,O7-M7) -> 0 | Q7: Boleto | R7: Recebido
A8: 7 | B8: Indenização | C8: 1 | D8: 21 | E8: 1 | F8: 33 | I8: 12009 | J8: 45698 | K8: 45716 | L8: Celebre Obras e Servicos LTDA | M8: 6011.98 | N8: 45716 | O8: 6011.98 | P8: =IF(OR(O8=0,O8=""),0,O8-M8) -> 0 | Q8: Pix | R8: Recebido
A9: 8 | B9: Manutenção | C9: 1 | D9: 16 | E9: 7 | F9: 47 | I9: 12010 | J9: 45722 | K9: 45736 | L9: Fibertec Engenharia LTDA | M9: 6500 | N9: 45736 | O9: 6500 | P9: =IF(OR(O9=0,O9=""),0,O9-M9) -> 0 | Q9: Boleto | R9: Recebido
A10: 9 | B10: Manutenção | C10: 1 | D10: 10 | E10: 9 | F10: 42 | G10: OS-2025-0023 | I10: 12011 | J10: 45726 | K10: 45713 | L10: Polemica Servicos Basicos LTDA | M10: 2962.25 | N10: 45713 | O10: 2962.25 | P10: =IF(OR(O10=0,O10=""),0,O10-M10) -> 0 | Q10: Boleto | R10: Recebido
A11: 10 | B11: Multa de Trânsito | C11: 1 | D11: 14 | E11: 11 | F11: 24 | I11: 12012 | J11: 45764 | K11: 45782 | L11: Zigurate Construcao LTDA | M11: 2064.62 | N11: 45825 | O11: 2330.34 | P11: =IF(OR(O11=0,O11=""),0,O11-M11) -> 265.72 | Q11: Pix | R11: Recebido
A12: 11 | B12: Multa de Trânsito | C12: 1 | D12: 16 | E12: 7 | F12: 6 | I12: 12013 | J12: 45764 | K12: 45777 | L12: Fibertec Engenharia LTDA | M12: 3028 | N12: 45792 | O12: 3361.08 | P12: =IF(OR(O12=0,O12=""),0,O12-M12) -> 333.08 | Q12: Pix | R12: Recebido
A13: 12 | B13: Multa de Trânsito | C13: 1 | D13: 22 | E13: 1 | F13: 39 | I13: 12014 | J13: 45764 | K13: 45782 | L13: Celebre Obras e Servicos LTDA | M13: 390.48 | N13: 45849 | O13: 390.48 | P13: =IF(OR(O13=0,O13=""),0,O13-M13) -> 0 | Q13: Pix | R13: Recebido
A14: 13 | B14: Manutenção | C14: 1 | D14: 17 | E14: 11 | F14: 17 | G14: OS-2025-0045 | I14: 12015 | J14: 45778 | K14: 45786 | L14: Zigurate Construcao LTDA | M14: 932.13 | N14: 45796 | O14: 1031.54 | P14: =IF(OR(O14=0,O14=""),0,O14-M14) -> 99.41 | Q14: Boleto | R14: Recebido
A15: 14 | B15: Franquia de Seguro | C15: 1 | D15: 10 | E15: 9 | F15: 34 | I15: 12016 | J15: 45778 | K15: 45782 | L15: Polemica Servicos Basicos LTDA | M15: 659 | N15: 45782 | O15: 659 | P15: =IF(OR(O15=0,O15=""),0,O15-M15) -> 0 | Q15: Boleto | R15: Recebido
A16: 15 | B16: Manutenção | C16: 1 | D16: 22 | E16: 1 | I16: 12017 | J16: 45793 | K16: 45870 | L16: Celebre Obras e Servicos LTDA | M16: 3933.67 | O16: 0 | P16: =IF(OR(O16=0,O16=""),0,O16-M16) -> 0 | Q16: Pix | R16: Cancelado
A17: 16 | B17: Manutenção | C17: 1 | D17: 24 | E17: 9 | F17: 42 | G17: OS-2025-0004 | I17: 12018 | J17: 45809 | K17: 45813 | L17: Polemica Servicos Basicos LTDA | M17: 1318 | N17: 45813 | O17: 1318 | P17: =IF(OR(O17=0,O17=""),0,O17-M17) -> 0 | Q17: Boleto | R17: Recebido
A18: 17 | B18: Multa de Trânsito | C18: 1 | D18: 13 | E18: 9 | I18: 12019 | J18: 45809 | K18: 45835 | L18: Polemica Servicos Basicos LTDA | M18: 0 | O18: 0 | P18: =IF(OR(O18=0,O18=""),0,O18-M18) -> 0 | Q18: Boleto | R18: Cancelado
A19: 18 | B19: Manutenção | C19: 1 | D19: 24 | E19: 9 | F19: 43 | I19: 12020 | J19: 45839 | K19: 45843 | L19: Polemica Servicos Basicos LTDA | M19: 235 | N19: 45843 | O19: 235 | P19: =IF(OR(O19=0,O19=""),0,O19-M19) -> 0 | Q19: Boleto | R19: Recebido
A20: 19 | B20: Manutenção | C20: 1 | D20: 16 | E20: 7 | F20: 43 | G20: OS-2025-0068 | I20: 12021 | J20: 45839 | K20: 45848 | L20: Fibertec Engenharia LTDA | M20: 1450 | N20: 45854 | O20: 1450 | P20: =IF(OR(O20=0,O20=""),0,O20-M20) -> 0 | Q20: Pix | R20: Recebido
A21: 20 | B21: Manutenção | C21: 1 | D21: 22 | E21: 1 | F21: 41 | G21: OS-2025-0064 | I21: 12022 | J21: 45856 | K21: 45870 | L21: Celebre Obras e Servicos LTDA | M21: 366.2 | N21: 45874 | O21: 366.2 | P21: =IF(OR(O21=0,O21=""),0,O21-M21) -> 0 | Q21: Pix | R21: Recebido
B22: Manutenção | C22: 1 | D22: 22 | E22: 1 | F22: 41 | G22: OS-2025-0076 | I22: 12022 | J22: 45856 | K22: 45870 | L22: Celebre Obras e Servicos LTDA | M22: 2426.91 | N22: 45874 | O22: 2426.91 | P22: =IF(OR(O22=0,O22=""),0,O22-M22) -> 0 | Q22: Pix | R22: Recebido
B23: Manutenção | C23: 1 | D23: 22 | E23: 1 | F23: 39 | G23: OS-2025-0145 | I23: 12022 | J23: 45856 | K23: 45870 | L23: Celebre Obras e Servicos LTDA | M23: 3656.62 | N23: 45874 | O23: 3656.62 | P23: =IF(OR(O23=0,O23=""),0,O23-M23) -> 0 | Q23: Pix | R23: Recebido
A24: 21 | B24: Encargos de Faturamento | C24: 1 | D24: 22 | E24: 1 | I24: 12023 | J24: 45901 | K24: 45910 | L24: Celebre Obras e Servicos LTDA | M24: 0 | O24: 0 | P24: =IF(OR(O24=0,O24=""),0,O24-M24) -> 0 | Q24: Pix | R24: Cancelado
A25: 22 | B25: Manutenção | C25: 1 | D25: 9 | E25: 4 | I25: 12024 | J25: 45901 | K25: 45905 | L25: Consorcio Gb Osasco Tiete | M25: 22859 | O25: 0 | P25: =IF(OR(O25=0,O25=""),0,O25-M25) -> 0 | Q25: Pix | R25: Vencido
A26: 23 | B26: Multa de Trânsito | C26: 1 | D26: 22 | E26: 1 | F26: 44 | I26: 12025 | J26: 45901 | K26: 45915 | L26: Celebre Obras e Servicos LTDA | M26: 6526.18 | N26: 45922 | O26: 6526.18 | P26: =IF(OR(O26=0,O26=""),0,O26-M26) -> 0 | Q26: Pix | R26: Recebido
A27: 24 | B27: Manutenção | C27: 1 | D27: 14 | E27: 11 | F27: 6 | G27: OS-2025-0108 | I27: 12026 | J27: 45901 | K27: 45908 | L27: Zigurate Construcao LTDA | M27: 15500 | N27: 45908 | O27: 15887.5 | P27: =IF(OR(O27=0,O27=""),0,O27-M27) -> 387.5 | Q27: Boleto | R27: Recebido
A28: 25 | B28: Encargos de Faturamento | C28: 3 | D28: 27 | E28: 7 | I28: 1001 | J28: 45901 | K28: 45910 | L28: Fibertec Engenharia LTDA | M28: 1550 | N28: 45910 | O28: 1550 | P28: =IF(OR(O28=0,O28=""),0,O28-M28) -> 0 | Q28: Boleto | R28: Recebido
A29: 26 | B29: Manutenção | C29: 1 | D29: 26 | E29: 11 | F29: 6 | G29: OS-2025-0108 | I29: 12027 | J29: 45931 | K29: 45938 | L29: Zigurate Construcao LTDA | M29: 7647.77 | N29: 45950 | O29: 7647.77 | P29: =IF(OR(O29=0,O29=""),0,O29-M29) -> 0 | Q29: Boleto | R29: Recebido
A30: 27 | B30: Multa de Trânsito | C30: 3 | D30: 26 | E30: 11 | F30: 24 | I30: 1002 | J30: 45931 | K30: 45944 | L30: Zigurate Construcao LTDA | M30: 2541.78 | N30: 45965 | O30: 2826.45 | P30: =IF(OR(O30=0,O30=""),0,O30-M30) -> 284.67 | Q30: Boleto | R30: Recebido
A31: 28 | B31: Multa de Trânsito | C31: 3 | D31: 29 | E31: 9 | F31: 46 | I31: 1003 | J31: 45931 | K31: 45960 | L31: Polemica Servicos Basicos LTDA | M31: 880.41 | N31: 45960 | O31: 0 | P31: =IF(OR(O31=0,O31=""),0,O31-M31) -> 0 | Q31: Boleto | R31: Recebido
A32: 29 | B32: Manutenção | C32: 1 | D32: 23 | E32: 1 | F32: 39 | G32: OS-2025-0129 | I32: 12028 | J32: 45959 | K32: 45971 | L32: Celebre Obras e Servicos LTDA | M32: 3460 | N32: 45971 | O32: 3460 | P32: =IF(OR(O32=0,O32=""),0,O32-M32) -> 0 | Q32: Pix | R32: Recebido
A33: 30 | B33: Multa de Trânsito | C33: 3 | D33: 26 | E33: 11 | F33: 6 | I33: 1004 | J33: 45965 | K33: 45978 | L33: Zigurate Construcao LTDA | M33: 590.84 | N33: 45982 | O33: 657.79 | P33: =IF(OR(O33=0,O33=""),0,O33-M33) -> 66.95 | Q33: Boleto | R33: Recebido
A34: 31 | B34: Manutenção | C34: 3 | D34: 29 | E34: 9 | F34: 34 | I34: 1005 | J34: 45978 | K34: 45989 | L34: Polemica Servicos Basicos LTDA | M34: 1529.44 | N34: 45965 | O34: 0 | P34: =IF(OR(O34=0,O34=""),0,O34-M34) -> 0 | Q34: Boleto | R34: Recebido
A35: 31 | B35: Manutenção | C35: 3 | D35: 29 | E35: 9 | F35: 42 | I35: 1005 | J35: 45978 | K35: 45989 | L35: Polemica Servicos Basicos LTDA | M35: 576 | N35: 45965 | O35: 0 | P35: =IF(OR(O35=0,O35=""),0,O35-M35) -> 0 | Q35: Boleto | R35: Recebido
A36: 32 | B36: Manutenção | C36: 1 | D36: 22 | E36: 1 | F36: 39 | G36: OS-2025-0142 | I36: 12029 | J36: 45979 | K36: 45992 | L36: Celebre Obras e Servicos LTDA | M36: 1740 | N36: 46036 | O36: 1740 | P36: =IF(OR(O36=0,O36=""),0,O36-M36) -> 0 | Q36: Pix | R36: Recebido
A37: 32 | B37: Manutenção | C37: 1 | D37: 22 | E37: 1 | F37: 41 | G37: OS-2025-0123 | I37: 12029 | J37: 45979 | K37: 45992 | L37: Celebre Obras e Servicos LTDA | M37: 280 | N37: 46036 | O37: 280 | P37: =IF(OR(O37=0,O37=""),0,O37-M37) -> 0 | Q37: Pix | R37: Recebido
A38: 33 | B38: Encargos de Faturamento | C38: 3 | D38: 27 | E38: 7 | I38: 1006 | J38: 45980 | K38: 45989 | L38: Fibertec Engenharia LTDA | M38: 0 | O38: 0 | P38: 0 | Q38: Boleto | R38: Cancelado
A39: 34 | B39: Manutenção | C39: 1 | D39: 26 | E39: 11 | F39: 6 | I39: 12030 | J39: 45962 | K39: 45989 | L39: Zigurate Construcao LTDA | M39: 0 | O39: 0 | P39: =IF(OR(O39=0,O39=""),0,O39-M39) -> 0 | Q39: Boleto | R39: Cancelado
A40: 35 | B40: Manutenção | C40: 1 | D40: 30 | E40: 13 | F40: 6 | I40: 12031 | J40: 45995 | K40: 46021 | L40: Consorcio Manutencao Guarapiranga | M40: 300 | N40: 46037 | O40: 300 | P40: =IF(OR(O40=0,O40=""),0,O40-M40) -> 0 | Q40: Boleto | R40: Recebido
A41: 36 | B41: Multa de Trânsito | C41: 1 | D41: 30 | E41: 13 | F41: 6 | I41: 12031 | J41: 45995 | K41: 46021 | L41: Consorcio Manutencao Guarapiranga | M41: 1171.44 | N41: 46037 | O41: 1171.44 | P41: =IF(OR(O41=0,O41=""),0,O41-M41) -> 0 | Q41: Boleto | R41: Recebido
A42: 37 | B42: Manutenção | C42: 1 | D42: 31 | E42: 1 | F42: 41 | G42: OS-2025-0133 | I42: 12032 | J42: 46021 | K42: 46037 | L42: Celebre Obras e Servicos LTDA | M42: 8627.68 | N42: 46059 | O42: 8627.68 | P42: =IF(OR(O42=0,O42=""),0,O42-M42) -> 0 | Q42: Pix | R42: Recebido
A43: 38 | B43: Manutenção | C43: 3 | D43: 28 | E43: 12 | F43: 20 | G43: OS-2025-0132 | I43: 1007 | J43: 45999 | K43: 46010 | L43: Consorcio Global Franca II | M43: 3394.04 | N43: 46031 | O43: 3394.04 | P43: =IF(OR(O43=0,O43=""),0,O43-M43) -> 0 | Q43: Boleto | R43: Recebido
A44: 39 | B44: Manutenção | C44: 3 | D44: 28 | E44: 12 | F44: 20 | G44: OS-2025-0132 | I44: 1008 | J44: 46024 | K44: 46037 | L44: Consorcio Global Franca II | M44: 2850 | N44: 46036 | O44: 2850 | P44: =IF(OR(O44=0,O44=""),0,O44-M44) -> 0 | Q44: Boleto | R44: Recebido
A45: 40 | B45: Manutenção | C45: 3 | D45: 28 | E45: 12 | F45: 20 | G45: OS-2025-0132 | I45: 1009 | J45: 46055 | K45: 46061 | L45: Consorcio Global Franca II | M45: 2850 | N45: 46061 | O45: 2850 | P45: =IF(OR(O45=0,O45=""),0,O45-M45) -> 0 | Q45: Boleto | R45: Recebido
A46: 41 | B46: Manutenção | C46: 3 | D46: 26 | E46: 11 | F46: 6 | G46: OS-2026-0172 | I46: 1010 | J46: 46083 | K46: 46132 | L46: Zigurate Construcao LTDA | M46: 8818.18 | O46: 0 | P46: =IF(OR(O46=0,O46=""),0,O46-M46) -> 0 | Q46: Boleto | R46: Pendente
A47: 42 | B47: Encargos de Faturamento | C47: 1 | D47: 31 | E47: 1 | I47: 12033 | J47: 46072 | K47: 46097 | L47: Celebre Obras e Servicos LTDA | M47: 544.52 | N47: 46097 | O47: 544.52 | P47: =IF(OR(O47=0,O47=""),0,O47-M47) -> 0 | Q47: Boleto | R47: Recebido
A48: 43 | B48: Manutenção | C48: 1 | D48: 31 | E48: 1 | F48: 39 | I48: 12034 | J48: 46072 | K48: 46097 | L48: Celebre Obras e Servicos LTDA | M48: 1577.24 | N48: 46097 | O48: 1577.24 | P48: =IF(OR(O48=0,O48=""),0,O48-M48) -> 0 | Q48: Boleto | R48: Recebido
A49: 44 | B49: Manutenção | C49: 1 | D49: 31 | E49: 1 | F49: 41 | I49: 12035 | J49: 46072 | K49: 46097 | L49: Celebre Obras e Servicos LTDA | M49: 1426.4 | N49: 46097 | O49: 1426.4 | P49: =IF(OR(O49=0,O49=""),0,O49-M49) -> 0 | Q49: Boleto | R49: Recebido
A50: 45 | B50: Encargos de Faturamento | C50: 3 | D50: 27 | E50: 7 | F50: 47 | I50: 1011 | J50: 46104 | K50: 46111 | L50: Fibertec Engenharia LTDA | M50: 1960.97 | O50: 0 | P50: =IF(OR(O50=0,O50=""),0,O50-M50) -> 0 | Q50: Boleto | R50: Pendente
A51: 46 | B51: Transporte | C51: 3 | D51: 29 | E51: 9 | F51: 41 | I51: 1012 | J51: 46083 | K51: 46086 | L51: Polemica Servicos Basicos LTDA | M51: 1448.06 | O51: 0 | P51: =IF(OR(O51=0,O51=""),0,O51-M51) -> 0 | Q51: Boleto | R51: Cancelado
A52: 47 | B52: Manutenção | C52: 3 | D52: 26 | E52: 11 | F52: 24 | I52: 1013 | J52: 46083 | K52: 46125 | L52: Zigurate Construcao LTDA | M52: 15550 | N52: 46129 | O52: 15550 | P52: =IF(OR(O52=0,O52=""),0,O52-M52) -> 0 | Q52: Boleto | R52: Recebido

Sheet 🛡️ SEGUROS
A1: IDSeguro | B1: IDEmpresa | C1: NumApolice | D1: Inicio | E1: Validade | F1: IDVeiculo | G1: Itens | H1: Modelo | I1: Cobertura | J1: ValorTotal | K1: ValorParcela | L1: Parcelas | M1: DiaVencimento | N1: DocumentoRede | O1: Status
A2: 1 | B2: 1 | C2: 0531 49 7942680 | D2: 45419 | E2: 45784 | F2: 42;43 | G2: BSX5H07; CSU3F94 | H2: Veículo | I2: Completo | J2: 23454.2 | K2: 2345.42 | L2: 10 | M2: 15 | N2: 052024 auto frota 2 itens BSX5H07 e CSU3F94 apl | O2: Vencido
A3: 2 | B3: 1 | C3: 171 49 24005276 | D3: 45447 | E3: 45813 | F3: 17 | G3: BQV5264 | H3: Equipamemento | I3: Completo | J3: 10847.45 | K3: 1807.91 | L3: 6 | M3: 15 | N3: Apol_BQV5264-171 49 24005276 | O3: Vencido
A4: 3 | B4: 1 | C4: 0531 49 7942680 | D4: 45450 | E4: 45518 | F4: 34 | G4: EXW7D65 | H4: Veículo | I4: Completo | J4: 18494.4 | K4: 1849.44 | L4: 10 | M4: 15 | N4: 06.24_0531 49 7942680 | O4: Cancelado
A5: 4 | B5: 1 | C5: 0531 49 8045088 | D5: 45512 | E5: 45877 | F5: 24;39;47 | G5: CUG4B86;DYG5G03;EJX0I24 | H5: Veículo | I5: Terceiros e Assistência 24h | J5: 8743.51 | K5: 874.32 | L5: 10 | M5: 10 | N5: 082024 auto frota 3 itens CUG4B86-DYG5G03-EJX0I24 apl | O5: Vencido
A6: 5 | B6: 1 | C6: 0531 49 8045088 | D6: 45512 | E6: 45877 | F6: 4;6;34;46 | G6: CCU5G26;EVF8883;EXW7D65;KJX8J96 | H6: Veículo | I6: Terceiros e Assistência 24h | J6: 12995.05 | K6: 1299.51 | L6: 10 | M6: 12 | N6: 08.24_0531 49 8045088 | O6: Vencido
A7: 6 | B7: 1 | C7: 171 49 24005792 | D7: 45540 | E7: 46270 | F7: 20 | G7: JCB 3CX | H7: Equipamemento | I7: Completo | J7: 15188.46 | K7: 2531.41 | L7: 6 | M7: 15 | N7: 092024 equip retroescavadeira 2020 apl e boletos 1362 | O7: Vencido
A8: 7 | B8: 4 | C8: 171 49 24005910 | D8: 45552 | E8: 45689 | F8: 50 | G8: XCMG XZ200 | H8: Equipamemento | I8: Completo | J8: 21437.8 | K8: 3572.97 | L8: 6 | M8: 4 | N8: 092024 equip perfuratriz apl 3951 | O8: Cancelado
A9: 8 | B9: 1 | C9: 0531 49 8359988 | D9: 45783 | E9: 46148 | F9: 42;43 | G9: BSX5H07;CSU3F94 | H9: Veículo | I9: Terceiros e Assistência 24h | J9: 8737.7 | K9: 873.76 | L9: 10 | M9: 20 | N9: 052025_AutoFrota | O9: Ativo
A10: 9 | B10: 1 | C10: 171 49 24007849 | D10: 45812 | E10: 46177 | F10: 17 | G10: BQV5264 | H10: Veículo | I10: Completo | J10: 7136.94 | K10: 1189.49 | L10: 6 | M10: 19 | N10: 06.25_BQV5264 | O10: Ativo
A11: 10 | B11: 1 | C11: 0531 49 8551463 | D11: 45877 | E11: 46242 | F11: 6;24;34;39;46;47 | G11: CUG4B86;DYG5G03;EJX0I24;CCU5G26;EVF8883;EXW7D65 | H11: Veículo | I11: Terceiros e Assistência 24h | J11: 21525.14 | K11: 2152.56 | L11: 10 | M11: 15 | N11: 082025_AutoFrota | O11: Ativo
A12: 11 | B12: 1 | C12: 171 49 24008647 | D12: 45905 | E12: 46270 | F12: 20 | G12: JCB 3CX | H12: Equipamemento | I12: Completo | J12: 16284.68 | K12: 2714.12 | L12: 6 | M12: 22 | N12: 09.25_Jcb3CX | O12: Ativo

Sheet 📋 SEGURO_MENSAL
A1: IDFinancaSeguro | B1: IDSeguro | C1: IDEmpresa | D1: IDVeiculo | E1: Placa | F1: ApoliceSeguro | G1: Vencimento | H1: Valor | I1: ParcelaAtual | J1: ParcelaTotal | K1: Status
A2: 1 | B2: 1 | C2: 1 | D2: 42 | E2: =_xlfn.XLOOKUP(D2,'🚛 FROTA'!A:A,'🚛 FROTA'!B:B,"") -> BSX5H07 | F2: =_xlfn.XLOOKUP(B2,'🛡️ SEGUROS'!A:A,'🛡️ SEGUROS'!C:C,"") -> 0531 49 7942680 | G2: 45450 | H2: =2345.42/2 -> 1172.71 | I2: 1 | J2: 10 | K2: Pago
A3: 2 | B3: 1 | C3: 1 | D3: 43 | E3: =_xlfn.XLOOKUP(D3,'🚛 FROTA'!A:A,'🚛 FROTA'!B:B,"") -> CSU3F94 | F3: =_xlfn.XLOOKUP(B3,'🛡️ SEGUROS'!A:A,'🛡️ SEGUROS'!C:C,"") -> 0531 49 7942680 | G3: 45450 | H3: =2345.42/2 -> 1172.71 | I3: 1 | J3: 10 | K3: Pago
A4: 3 | B4: 2 | C4: 1 | D4: 17 | E4: =_xlfn.XLOOKUP(D4,'🚛 FROTA'!A:A,'🚛 FROTA'!B:B,"") -> BQV5264 | F4: =_xlfn.XLOOKUP(B4,'🛡️ SEGUROS'!A:A,'🛡️ SEGUROS'!C:C,"") -> 171 49 24005276 | G4: 45458 | H4: =10847.46/6 -> 1807.91 | I4: 1 | J4: 6 | K4: Pago
A5: 4 | B5: 3 | C5: 1 | D5: 34 | E5: =_xlfn.XLOOKUP(D5,'🚛 FROTA'!A:A,'🚛 FROTA'!B:B,"") -> EXW7D65 | F5: =_xlfn.XLOOKUP(B5,'🛡️ SEGUROS'!A:A,'🛡️ SEGUROS'!C:C,"") -> 0531 49 7942680 | G5: 45480 | H5: =1849.44+713.69 -> 2563.13 | I5: 1 | J5: 10 | K5: Pago
A6: 5 | B6: 1 | C6: 1 | D6: 42 | E6: =_xlfn.XLOOKUP(D6,'🚛 FROTA'!A:A,'🚛 FROTA'!B:B,"") -> BSX5H07 | F6: =_xlfn.XLOOKUP(B6,'🛡️ SEGUROS'!A:A,'🛡️ SEGUROS'!C:C,"") -> 0531 49 7942680 | G6: 45488 | H6: =2345.42/2 -> 1172.71 | I6: 2 | J6: 10 | K6: Pago
A7: 6 | B7: 1 | C7: 1 | D7: 43 | E7: =_xlfn.XLOOKUP(D7,'🚛 FROTA'!A:A,'🚛 FROTA'!B:B,"") -> CSU3F94 | F7: =_xlfn.XLOOKUP(B7,'🛡️ SEGUROS'!A:A,'🛡️ SEGUROS'!C:C,"") -> 0531 49 7942680 | G7: 45488 | H7: =2345.42/2 -> 1172.71 | I7: 2 | J7: 10 | K7: Pago
A8: 7 | B8: 2 | C8: 1 | D8: 17 | E8: =_xlfn.XLOOKUP(D8,'🚛 FROTA'!A:A,'🚛 FROTA'!B:B,"") -> BQV5264 | F8: =_xlfn.XLOOKUP(B8,'🛡️ SEGUROS'!A:A,'🛡️ SEGUROS'!C:C,"") -> 171 49 24005276 | G8: 45488 | H8: =10847.46/6 -> 1807.91 | I8: 2 | J8: 6 | K8: Pago
A9: 8 | B9: 1 | C9: 1 | D9: 42 | E9: =_xlfn.XLOOKUP(D9,'🚛 FROTA'!A:A,'🚛 FROTA'!B:B,"") -> BSX5H07 | F9: =_xlfn.XLOOKUP(B9,'🛡️ SEGUROS'!A:A,'🛡️ SEGUROS'!C:C,"") -> 0531 49 7942680 | G9: 45519 | H9: =2345.42/2 -> 1172.71 | I9: 3 | J9: 10 | K9: Pago
A10: 9 | B10: 1 | C10: 1 | D10: 43 | E10: =_xlfn.XLOOKUP(D10,'🚛 FROTA'!A:A,'🚛 FROTA'!B:B,"") -> CSU3F94 | F10: =_xlfn.XLOOKUP(B10,'🛡️ SEGUROS'!A:A,'🛡️ SEGUROS'!C:C,"") -> 0531 49 7942680 | G10: 45519 | H10: =2345.42/2 -> 1172.71 | I10: 3 | J10: 10 | K10: Pago
A11: 10 | B11: 2 | C11: 1 | D11: 17 | E11: =_xlfn.XLOOKUP(D11,'🚛 FROTA'!A:A,'🚛 FROTA'!B:B,"") -> BQV5264 | F11: =_xlfn.XLOOKUP(B11,'🛡️ SEGUROS'!A:A,'🛡️ SEGUROS'!C:C,"") -> 171 49 24005276 | G11: 45519 | H11: =10847.46/6 -> 1807.91 | I11: 3 | J11: 6 | K11: Pago
A12: 11 | B12: 3 | C12: 1 | D12: 34 | E12: =_xlfn.XLOOKUP(D12,'🚛 FROTA'!A:A,'🚛 FROTA'!B:B,"") -> EXW7D65 | F12: =_xlfn.XLOOKUP(B12,'🛡️ SEGUROS'!A:A,'🛡️ SEGUROS'!C:C,"") -> 0531 49 7942680 | G12: 45519 | H12: =1849.44+713.69 -> 2563.13 | I12: 2 | J12: 10 | K12: Pago
A13: 12 | B13: 5 | C13: 1 | D13: 4 | E13: =_xlfn.XLOOKUP(D13,'🚛 FROTA'!A:A,'🚛 FROTA'!B:B,"") -> KJX8J96 | F13: =_xlfn.XLOOKUP(B13,'🛡️ SEGUROS'!A:A,'🛡️ SEGUROS'!C:C,"") -> 0531 49 8045088 | G13: 45549 | H13: =3160.37/10 -> 316.037 | I13: 1 | J13: 10 | K13: Pago
A14: 13 | B14: 5 | C14: 1 | D14: 6 | E14: =_xlfn.XLOOKUP(D14,'🚛 FROTA'!A:A,'🚛 FROTA'!B:B,"") -> EVF8I83 | F14: =_xlfn.XLOOKUP(B14,'🛡️ SEGUROS'!A:A,'🛡️ SEGUROS'!C:C,"") -> 0531 49 8045088 | G14: 45549 | H14: =3362.47/10+0.01 -> 336.257 | I14: 1 | J14: 10 | K14: Pago
A15: 14 | B15: 5 | C15: 1 | D15: 34 | E15: =_xlfn.XLOOKUP(D15,'🚛 FROTA'!A:A,'🚛 FROTA'!B:B,"") -> EXW7D65 | F15: =_xlfn.XLOOKUP(B15,'🛡️ SEGUROS'!A:A,'🛡️ SEGUROS'!C:C,"") -> 0531 49 8045088 | G15: 45549 | H15: =3236.1/10 -> 323.61 | I15: 1 | J15: 10 | K15: Pago
A16: 15 | B16: 5 | C16: 1 | D16: 46 | E16: =_xlfn.XLOOKUP(D16,'🚛 FROTA'!A:A,'🚛 FROTA'!B:B,"") -> CCU5G26 | F16: =_xlfn.XLOOKUP(B16,'🛡️ SEGUROS'!A:A,'🛡️ SEGUROS'!C:C,"") -> 0531 49 8045088 | G16: 45549 | H16: =3236.1/10 -> 323.61 | I16: 1 | J16: 10 | K16: Pago
A17: 16 | B17: 1 | C17: 1 | D17: 42 | E17: =_xlfn.XLOOKUP(D17,'🚛 FROTA'!A:A,'🚛 FROTA'!B:B,"") -> BSX5H07 | F17: =_xlfn.XLOOKUP(B17,'🛡️ SEGUROS'!A:A,'🛡️ SEGUROS'!C:C,"") -> 0531 49 7942680 | G17: 45550 | H17: =2345.42/2 -> 1172.71 | I17: 4 | J17: 10 | K17: Pago
A18: 17 | B18: 1 | C18: 1 | D18: 43 | E18: =_xlfn.XLOOKUP(D18,'🚛 FROTA'!A:A,'🚛 FROTA'!B:B,"") -> CSU3F94 | F18: =_xlfn.XLOOKUP(B18,'🛡️ SEGUROS'!A:A,'🛡️ SEGUROS'!C:C,"") -> 0531 49 7942680 | G18: 45550 | H18: =2345.42/2 -> 1172.71 | I18: 4 | J18: 10 | K18: Pago
A19: 18 | B19: 2 | C19: 1 | D19: 17 | E19: =_xlfn.XLOOKUP(D19,'🚛 FROTA'!A:A,'🚛 FROTA'!B:B,"") -> BQV5264 | F19: =_xlfn.XLOOKUP(B19,'🛡️ SEGUROS'!A:A,'🛡️ SEGUROS'!C:C,"") -> 171 49 24005276 | G19: 45550 | H19: =10847.46/6 -> 1807.91 | I19: 4 | J19: 6 | K19: Pago
A20: 19 | B20: 6 | C20: 1 | D20: 20 | E20: =_xlfn.XLOOKUP(D20,'🚛 FROTA'!A:A,'🚛 FROTA'!B:B,"") -> MAX4116 | F20: =_xlfn.XLOOKUP(B20,'🛡️ SEGUROS'!A:A,'🛡️ SEGUROS'!C:C,"") -> 171 49 24005792 | G20: 45550 | H20: 2531.41 | I20: 1 | J20: 6 | K20: Pago
A21: 20 | B21: 4 | C21: 1 | D21: 24 | E21: =_xlfn.XLOOKUP(D21,'🚛 FROTA'!A:A,'🚛 FROTA'!B:B,"") -> DYG5G03 | F21: =_xlfn.XLOOKUP(B21,'🛡️ SEGUROS'!A:A,'🛡️ SEGUROS'!C:C,"") -> 0531 49 8045088 | G21: 45574 | H21: =2910.47/10-0.01 -> 291.037 | I21: 1 | J21: 10 | K21: Pago
A22: 21 | B22: 4 | C22: 1 | D22: 39 | E22: =_xlfn.XLOOKUP(D22,'🚛 FROTA'!A:A,'🚛 FROTA'!B:B,"") -> EJX0I24 | F22: =_xlfn.XLOOKUP(B22,'🛡️ SEGUROS'!A:A,'🛡️ SEGUROS'!C:C,"") -> 0531 49 8045088 | G22: 45574 | H22: =2791.96/10-0.01 -> 279.186 | I22: 1 | J22: 10 | K22: Pago
A23: 22 | B23: 4 | C23: 1 | D23: 47 | E23: =_xlfn.XLOOKUP(D23,'🚛 FROTA'!A:A,'🚛 FROTA'!B:B,"") -> CUG4B86 | F23: =_xlfn.XLOOKUP(B23,'🛡️ SEGUROS'!A:A,'🛡️ SEGUROS'!C:C,"") -> 0531 49 8045088 | G23: 45574 | H23: =3041.09/10-0.01 -> 304.099 | I23: 1 | J23: 10 | K23: Pago
A24: 23 | B24: 5 | C24: 1 | D24: 4 | E24: =_xlfn.XLOOKUP(D24,'🚛 FROTA'!A:A,'🚛 FROTA'!B:B,"") -> KJX8J96 | F24: =_xlfn.XLOOKUP(B24,'🛡️ SEGUROS'!A:A,'🛡️ SEGUROS'!C:C,"") -> 0531 49 8045088 | G24: 45577 | H24: =3160.37/10 -> 316.037 | I24: 2 | J24: 10 | K24: Pago
A25: 24 | B25: 5 | C25: 1 | D25: 6 | E25: =_xlfn.XLOOKUP(D25,'🚛 FROTA'!A:A,'🚛 FROTA'!B:B,"") -> EVF8I83 | F25: =_xlfn.XLOOKUP(B25,'🛡️ SEGUROS'!A:A,'🛡️ SEGUROS'!C:C,"") -> 0531 49 8045088 | G25: 45577 | H25: =3362.47/10+0.01 -> 336.257 | I25: 2 | J25: 10 | K25: Pago
A26: 25 | B26: 5 | C26: 1 | D26: 34 | E26: =_xlfn.XLOOKUP(D26,'🚛 FROTA'!A:A,'🚛 FROTA'!B:B,"") -> EXW7D65 | F26: =_xlfn.XLOOKUP(B26,'🛡️ SEGUROS'!A:A,'🛡️ SEGUROS'!C:C,"") -> 0531 49 8045088 | G26: 45577 | H26: =3236.1/10 -> 323.61 | I26: 2 | J26: 10 | K26: Pago
A27: 26 | B27: 5 | C27: 1 | D27: 46 | E27: =_xlfn.XLOOKUP(D27,'🚛 FROTA'!A:A,'🚛 FROTA'!B:B,"") -> CCU5G26 | F27: =_xlfn.XLOOKUP(B27,'🛡️ SEGUROS'!A:A,'🛡️ SEGUROS'!C:C,"") -> 0531 49 8045088 | G27: 45577 | H27: =3236.1/10 -> 323.61 | I27: 2 | J27: 10 | K27: Pago
A28: 27 | B28: 1 | C28: 1 | D28: 42 | E28: =_xlfn.XLOOKUP(D28,'🚛 FROTA'!A:A,'🚛 FROTA'!B:B,"") -> BSX5H07 | F28: =_xlfn.XLOOKUP(B28,'🛡️ SEGUROS'!A:A,'🛡️ SEGUROS'!C:C,"") -> 0531 49 7942680 | G28: 45580 | H28: =2345.42/2 -> 1172.71 | I28: 5 | J28: 10 | K28: Pago
A29: 28 | B29: 1 | C29: 1 | D29: 43 | E29: =_xlfn.XLOOKUP(D29,'🚛 FROTA'!A:A,'🚛 FROTA'!B:B,"") -> CSU3F94 | F29: =_xlfn.XLOOKUP(B29,'🛡️ SEGUROS'!A:A,'🛡️ SEGUROS'!C:C,"") -> 0531 49 7942680 | G29: 45580 | H29: =2345.42/2 -> 1172.71 | I29: 5 | J29: 10 | K29: Pago
A30: 29 | B30: 2 | C30: 1 | D30: 17 | E30: =_xlfn.XLOOKUP(D30,'🚛 FROTA'!A:A,'🚛 FROTA'!B:B,"") -> BQV5264 | F30: =_xlfn.XLOOKUP(B30,'🛡️ SEGUROS'!A:A,'🛡️ SEGUROS'!C:C,"") -> 171 49 24005276 | G30: 45580 | H30: =10847.46/6 -> 1807.91 | I30: 5 | J30: 6 | K30: Pago
A31: 30 | B31: 6 | C31: 1 | D31: 20 | E31: =_xlfn.XLOOKUP(D31,'🚛 FROTA'!A:A,'🚛 FROTA'!B:B,"") -> MAX4116 | F31: =_xlfn.XLOOKUP(B31,'🛡️ SEGUROS'!A:A,'🛡️ SEGUROS'!C:C,"") -> 171 49 24005792 | G31: 45580 | H31: 2531.41 | I31: 2 | J31: 6 | K31: Pago
A32: 31 | B32: 4 | C32: 1 | D32: 24 | E32: =_xlfn.XLOOKUP(D32,'🚛 FROTA'!A:A,'🚛 FROTA'!B:B,"") -> DYG5G03 | F32: =_xlfn.XLOOKUP(B32,'🛡️ SEGUROS'!A:A,'🛡️ SEGUROS'!C:C,"") -> 0531 49 8045088 | G32: 45606 | H32: =2910.47/10-0.01 -> 291.037 | I32: 2 | J32: 10 | K32: Pago
A33: 32 | B33: 4 | C33: 1 | D33: 39 | E33: =_xlfn.XLOOKUP(D33,'🚛 FROTA'!A:A,'🚛 FROTA'!B:B,"") -> EJX0I24 | F33: =_xlfn.XLOOKUP(B33,'🛡️ SEGUROS'!A:A,'🛡️ SEGUROS'!C:C,"") -> 0531 49 8045088 | G33: 45606 | H33: =2791.96/10-0.01 -> 279.186 | I33: 2 | J33: 10 | K33: Pago
A34: 33 | B34: 4 | C34: 1 | D34: 47 | E34: =_xlfn.XLOOKUP(D34,'🚛 FROTA'!A:A,'🚛 FROTA'!B:B,"") -> CUG4B86 | F34: =_xlfn.XLOOKUP(B34,'🛡️ SEGUROS'!A:A,'🛡️ SEGUROS'!C:C,"") -> 0531 49 8045088 | G34: 45606 | H34: =3041.09/10-0.01 -> 304.099 | I34: 2 | J34: 10 | K34: Pago
A35: 34 | B35: 5 | C35: 1 | D35: 4 | E35: =_xlfn.XLOOKUP(D35,'🚛 FROTA'!A:A,'🚛 FROTA'!B:B,"") -> KJX8J96 | F35: =_xlfn.XLOOKUP(B35,'🛡️ SEGUROS'!A:A,'🛡️ SEGUROS'!C:C,"") -> 0531 49 8045088 | G35: 45608 | H35: =3160.37/10 -> 316.037 | I35: 3 | J35: 10 | K35: Pago
A36: 35 | B36: 5 | C36: 1 | D36: 6 | E36: =_xlfn.XLOOKUP(D36,'🚛 FROTA'!A:A,'🚛 FROTA'!B:B,"") -> EVF8I83 | F36: =_xlfn.XLOOKUP(B36,'🛡️ SEGUROS'!A:A,'🛡️ SEGUROS'!C:C,"") -> 0531 49 8045088 | G36: 45608 | H36: =3362.47/10+0.01 -> 336.257 | I36: 3 | J36: 10 | K36: Pago
A37: 36 | B37: 5 | C37: 1 | D37: 34 | E37: =_xlfn.XLOOKUP(D37,'🚛 FROTA'!A:A,'🚛 FROTA'!B:B,"") -> EXW7D65 | F37: =_xlfn.XLOOKUP(B37,'🛡️ SEGUROS'!A:A,'🛡️ SEGUROS'!C:C,"") -> 0531 49 8045088 | G37: 45608 | H37: =3236.1/10 -> 323.61 | I37: 3 | J37: 10 | K37: Pago
A38: 37 | B38: 5 | C38: 1 | D38: 46 | E38: =_xlfn.XLOOKUP(D38,'🚛 FROTA'!A:A,'🚛 FROTA'!B:B,"") -> CCU5G26 | F38: =_xlfn.XLOOKUP(B38,'🛡️ SEGUROS'!A:A,'🛡️ SEGUROS'!C:C,"") -> 0531 49 8045088 | G38: 45608 | H38: =3236.1/10 -> 323.61 | I38: 3 | J38: 10 | K38: Pago
A39: 38 | B39: 1 | C39: 1 | D39: 42 | E39: =_xlfn.XLOOKUP(D39,'🚛 FROTA'!A:A,'🚛 FROTA'!B:B,"") -> BSX5H07 | F39: =_xlfn.XLOOKUP(B39,'🛡️ SEGUROS'!A:A,'🛡️ SEGUROS'!C:C,"") -> 0531 49 7942680 | G39: 45611 | H39: =2345.42/2 -> 1172.71 | I39: 6 | J39: 10 | K39: Pago
A40: 39 | B40: 1 | C40: 1 | D40: 43 | E40: =_xlfn.XLOOKUP(D40,'🚛 FROTA'!A:A,'🚛 FROTA'!B:B,"") -> CSU3F94 | F40: =_xlfn.XLOOKUP(B40,'🛡️ SEGUROS'!A:A,'🛡️ SEGUROS'!C:C,"") -> 0531 49 7942680 | G40: 45611 | H40: =2345.42/2 -> 1172.71 | I40: 6 | J40: 10 | K40: Pago
A41: 40 | B41: 2 | C41: 1 | D41: 17 | E41: =_xlfn.XLOOKUP(D41,'🚛 FROTA'!A:A,'🚛 FROTA'!B:B,"") -> BQV5264 | F41: =_xlfn.XLOOKUP(B41,'🛡️ SEGUROS'!A:A,'🛡️ SEGUROS'!C:C,"") -> 171 49 24005276 | G41: 45611 | H41: =10847.46/6 -> 1807.91 | I41: 6 | J41: 6 | K41: Pago
A42: 41 | B42: 6 | C42: 1 | D42: 20 | E42: =_xlfn.XLOOKUP(D42,'🚛 FROTA'!A:A,'🚛 FROTA'!B:B,"") -> MAX4116 | F42: =_xlfn.XLOOKUP(B42,'🛡️ SEGUROS'!A:A,'🛡️ SEGUROS'!C:C,"") -> 171 49 24005792 | G42: 45611 | H42: 2531.41 | I42: 3 | J42: 6 | K42: Pago
A43: 42 | B43: 4 | C43: 1 | D43: 24 | E43: =_xlfn.XLOOKUP(D43,'🚛 FROTA'!A:A,'🚛 FROTA'!B:B,"") -> DYG5G03 | F43: =_xlfn.XLOOKUP(B43,'🛡️ SEGUROS'!A:A,'🛡️ SEGUROS'!C:C,"") -> 0531 49 8045088 | G43: 45636 | H43: =2910.47/10-0.01 -> 291.037 | I43: 3 | J43: 10 | K43: Pago
A44: 43 | B44: 4 | C44: 1 | D44: 39 | E44: =_xlfn.XLOOKUP(D44,'🚛 FROTA'!A:A,'🚛 FROTA'!B:B,"") -> EJX0I24 | F44: =_xlfn.XLOOKUP(B44,'🛡️ SEGUROS'!A:A,'🛡️ SEGUROS'!C:C,"") -> 0531 49 8045088 | G44: 45636 | H44: =2791.96/10-0.01 -> 279.186 | I44: 3 | J44: 10 | K44: Pago
A45: 44 | B45: 4 | C45: 1 | D45: 47 | E45: =_xlfn.XLOOKUP(D45,'🚛 FROTA'!A:A,'🚛 FROTA'!B:B,"") -> CUG4B86 | F45: =_xlfn.XLOOKUP(B45,'🛡️ SEGUROS'!A:A,'🛡️ SEGUROS'!C:C,"") -> 0531 49 8045088 | G45: 45636 | H45: =3041.09/10-0.01 -> 304.099 | I45: 3 | J45: 10 | K45: Pago
A46: 45 | B46: 5 | C46: 1 | D46: 4 | E46: =_xlfn.XLOOKUP(D46,'🚛 FROTA'!A:A,'🚛 FROTA'!B:B,"") -> KJX8J96 | F46: =_xlfn.XLOOKUP(B46,'🛡️ SEGUROS'!A:A,'🛡️ SEGUROS'!C:C,"") -> 0531 49 8045088 | G46: 45638 | H46: =3160.37/10 -> 316.037 | I46: 4 | J46: 10 | K46: Pago
A47: 46 | B47: 5 | C47: 1 | D47: 6 | E47: =_xlfn.XLOOKUP(D47,'🚛 FROTA'!A:A,'🚛 FROTA'!B:B,"") -> EVF8I83 | F47: =_xlfn.XLOOKUP(B47,'🛡️ SEGUROS'!A:A,'🛡️ SEGUROS'!C:C,"") -> 0531 49 8045088 | G47: 45638 | H47: =3362.47/10+0.01 -> 336.257 | I47: 4 | J47: 10 | K47: Pago
A48: 47 | B48: 5 | C48: 1 | D48: 34 | E48: =_xlfn.XLOOKUP(D48,'🚛 FROTA'!A:A,'🚛 FROTA'!B:B,"") -> EXW7D65 | F48: =_xlfn.XLOOKUP(B48,'🛡️ SEGUROS'!A:A,'🛡️ SEGUROS'!C:C,"") -> 0531 49 8045088 | G48: 45638 | H48: =3236.1/10 -> 323.61 | I48: 4 | J48: 10 | K48: Pago
A49: 48 | B49: 5 | C49: 1 | D49: 46 | E49: =_xlfn.XLOOKUP(D49,'🚛 FROTA'!A:A,'🚛 FROTA'!B:B,"") -> CCU5G26 | F49: =_xlfn.XLOOKUP(B49,'🛡️ SEGUROS'!A:A,'🛡️ SEGUROS'!C:C,"") -> 0531 49 8045088 | G49: 45638 | H49: =3236.1/10 -> 323.61 | I49: 4 | J49: 10 | K49: Pago
A50: 49 | B50: 1 | C50: 1 | D50: 42 | E50: =_xlfn.XLOOKUP(D50,'🚛 FROTA'!A:A,'🚛 FROTA'!B:B,"") -> BSX5H07 | F50: =_xlfn.XLOOKUP(B50,'🛡️ SEGUROS'!A:A,'🛡️ SEGUROS'!C:C,"") -> 0531 49 7942680 | G50: 45641 | H50: =2345.42/2 -> 1172.71 | I50: 7 | J50: 10 | K50: Pago
A51: 50 | B51: 1 | C51: 1 | D51: 43 | E51: =_xlfn.XLOOKUP(D51,'🚛 FROTA'!A:A,'🚛 FROTA'!B:B,"") -> CSU3F94 | F51: =_xlfn.XLOOKUP(B51,'🛡️ SEGUROS'!A:A,'🛡️ SEGUROS'!C:C,"") -> 0531 49 7942680 | G51: 45641 | H51: =2345.42/2 -> 1172.71 | I51: 7 | J51: 10 | K51: Pago
A52: 51 | B52: 6 | C52: 1 | D52: 20 | E52: =_xlfn.XLOOKUP(D52,'🚛 FROTA'!A:A,'🚛 FROTA'!B:B,"") -> MAX4116 | F52: =_xlfn.XLOOKUP(B52,'🛡️ SEGUROS'!A:A,'🛡️ SEGUROS'!C:C,"") -> 171 49 24005792 | G52: 45641 | H52: 2531.41 | I52: 4 | J52: 6 | K52: Pago
A53: 52 | B53: 4 | C53: 1 | D53: 24 | E53: =_xlfn.XLOOKUP(D53,'🚛 FROTA'!A:A,'🚛 FROTA'!B:B,"") -> DYG5G03 | F53: =_xlfn.XLOOKUP(B53,'🛡️ SEGUROS'!A:A,'🛡️ SEGUROS'!C:C,"") -> 0531 49 8045088 | G53: 45667 | H53: =2910.47/10-0.01 -> 291.037 | I53: 4 | J53: 10 | K53: Pago
A54: 53 | B54: 4 | C54: 1 | D54: 39 | E54: =_xlfn.XLOOKUP(D54,'🚛 FROTA'!A:A,'🚛 FROTA'!B:B,"") -> EJX0I24 | F54: =_xlfn.XLOOKUP(B54,'🛡️ SEGUROS'!A:A,'🛡️ SEGUROS'!C:C,"") -> 0531 49 8045088 | G54: 45667 | H54: =2791.96/10-0.01 -> 279.186 | I54: 4 | J54: 10 | K54: Pago
A55: 54 | B55: 4 | C55: 1 | D55: 47 | E55: =_xlfn.XLOOKUP(D55,'🚛 FROTA'!A:A,'🚛 FROTA'!B:B,"") -> CUG4B86 | F55: =_xlfn.XLOOKUP(B55,'🛡️ SEGUROS'!A:A,'🛡️ SEGUROS'!C:C,"") -> 0531 49 8045088 | G55: 45667 | H55: =3041.09/10-0.01 -> 304.099 | I55: 4 | J55: 10 | K55: Pago
A56: 55 | B56: 5 | C56: 1 | D56: 6 | E56: =_xlfn.XLOOKUP(D56,'🚛 FROTA'!A:A,'🚛 FROTA'!B:B,"") -> EVF8I83 | F56: =_xlfn.XLOOKUP(B56,'🛡️ SEGUROS'!A:A,'🛡️ SEGUROS'!C:C,"") -> 0531 49 8045088 | G56: 45669 | H56: =3362.47/10+0.01 -> 336.257 | I56: 5 | J56: 10 | K56: Pago
A57: 56 | B57: 5 | C57: 1 | D57: 34 | E57: =_xlfn.XLOOKUP(D57,'🚛 FROTA'!A:A,'🚛 FROTA'!B:B,"") -> EXW7D65 | F57: =_xlfn.XLOOKUP(B57,'🛡️ SEGUROS'!A:A,'🛡️ SEGUROS'!C:C,"") -> 0531 49 8045088 | G57: 45669 | H57: =3236.1/10 -> 323.61 | I57: 5 | J57: 10 | K57: Pago
A58: 57 | B58: 5 | C58: 1 | D58: 46 | E58: =_xlfn.XLOOKUP(D58,'🚛 FROTA'!A:A,'🚛 FROTA'!B:B,"") -> CCU5G26 | F58: =_xlfn.XLOOKUP(B58,'🛡️ SEGUROS'!A:A,'🛡️ SEGUROS'!C:C,"") -> 0531 49 8045088 | G58: 45669 | H58: =3236.1/10 -> 323.61 | I58: 5 | J58: 10 | K58: Pago
A59: 58 | B59: 1 | C59: 1 | D59: 42 | E59: =_xlfn.XLOOKUP(D59,'🚛 FROTA'!A:A,'🚛 FROTA'!B:B,"") -> BSX5H07 | F59: =_xlfn.XLOOKUP(B59,'🛡️ SEGUROS'!A:A,'🛡️ SEGUROS'!C:C,"") -> 0531 49 7942680 | G59: 45672 | H59: =2345.42/2 -> 1172.71 | I59: 8 | J59: 10 | K59: Pago
A60: 59 | B60: 1 | C60: 1 | D60: 43 | E60: =_xlfn.XLOOKUP(D60,'🚛 FROTA'!A:A,'🚛 FROTA'!B:B,"") -> CSU3F94 | F60: =_xlfn.XLOOKUP(B60,'🛡️ SEGUROS'!A:A,'🛡️ SEGUROS'!C:C,"") -> 0531 49 7942680 | G60: 45672 | H60: =2345.42/2 -> 1172.71 | I60: 8 | J60: 10 | K60: Pago
A61: 60 | B61: 6 | C61: 1 | D61: 20 | E61: =_xlfn.XLOOKUP(D61,'🚛 FROTA'!A:A,'🚛 FROTA'!B:B,"") -> MAX4116 | F61: =_xlfn.XLOOKUP(B61,'🛡️ SEGUROS'!A:A,'🛡️ SEGUROS'!C:C,"") -> 171 49 24005792 | G61: 45672 | H61: 2531.41 | I61: 5 | J61: 6 | K61: Pago
A62: 61 | B62: 4 | C62: 1 | D62: 24 | E62: =_xlfn.XLOOKUP(D62,'🚛 FROTA'!A:A,'🚛 FROTA'!B:B,"") -> DYG5G03 | F62: =_xlfn.XLOOKUP(B62,'🛡️ SEGUROS'!A:A,'🛡️ SEGUROS'!C:C,"") -> 0531 49 8045088 | G62: 45698 | H62: =2910.47/10-0.01 -> 291.037 | I62: 5 | J62: 10 | K62: Pago
A63: 62 | B63: 4 | C63: 1 | D63: 39 | E63: =_xlfn.XLOOKUP(D63,'🚛 FROTA'!A:A,'🚛 FROTA'!B:B,"") -> EJX0I24 | F63: =_xlfn.XLOOKUP(B63,'🛡️ SEGUROS'!A:A,'🛡️ SEGUROS'!C:C,"") -> 0531 49 8045088 | G63: 45698 | H63: =2791.96/10-0.01 -> 279.186 | I63: 5 | J63: 10 | K63: Pago
A64: 63 | B64: 4 | C64: 1 | D64: 47 | E64: =_xlfn.XLOOKUP(D64,'🚛 FROTA'!A:A,'🚛 FROTA'!B:B,"") -> CUG4B86 | F64: =_xlfn.XLOOKUP(B64,'🛡️ SEGUROS'!A:A,'🛡️ SEGUROS'!C:C,"") -> 0531 49 8045088 | G64: 45698 | H64: =3041.09/10-0.01 -> 304.099 | I64: 5 | J64: 10 | K64: Pago
A65: 64 | B65: 5 | C65: 1 | D65: 6 | E65: =_xlfn.XLOOKUP(D65,'🚛 FROTA'!A:A,'🚛 FROTA'!B:B,"") -> EVF8I83 | F65: =_xlfn.XLOOKUP(B65,'🛡️ SEGUROS'!A:A,'🛡️ SEGUROS'!C:C,"") -> 0531 49 8045088 | G65: 45700 | H65: =3362.47/10+0.01 -> 336.257 | I65: 6 | J65: 10 | K65: Pago
A66: 65 | B66: 5 | C66: 1 | D66: 34 | E66: =_xlfn.XLOOKUP(D66,'🚛 FROTA'!A:A,'🚛 FROTA'!B:B,"") -> EXW7D65 | F66: =_xlfn.XLOOKUP(B66,'🛡️ SEGUROS'!A:A,'🛡️ SEGUROS'!C:C,"") -> 0531 49 8045088 | G66: 45700 | H66: =3236.1/10 -> 323.61 | I66: 6 | J66: 10 | K66: Pago
A67: 66 | B67: 5 | C67: 1 | D67: 46 | E67: =_xlfn.XLOOKUP(D67,'🚛 FROTA'!A:A,'🚛 FROTA'!B:B,"") -> CCU5G26 | F67: =_xlfn.XLOOKUP(B67,'🛡️ SEGUROS'!A:A,'🛡️ SEGUROS'!C:C,"") -> 0531 49 8045088 | G67: 45700 | H67: =3236.1/10 -> 323.61 | I67: 6 | J67: 10 | K67: Pago
A68: 67 | B68: 1 | C68: 1 | D68: 42 | E68: =_xlfn.XLOOKUP(D68,'🚛 FROTA'!A:A,'🚛 FROTA'!B:B,"") -> BSX5H07 | F68: =_xlfn.XLOOKUP(B68,'🛡️ SEGUROS'!A:A,'🛡️ SEGUROS'!C:C,"") -> 0531 49 7942680 | G68: 45703 | H68: =2345.42/2 -> 1172.71 | I68: 9 | J68: 10 | K68: Pago
A69: 68 | B69: 1 | C69: 1 | D69: 43 | E69: =_xlfn.XLOOKUP(D69,'🚛 FROTA'!A:A,'🚛 FROTA'!B:B,"") -> CSU3F94 | F69: =_xlfn.XLOOKUP(B69,'🛡️ SEGUROS'!A:A,'🛡️ SEGUROS'!C:C,"") -> 0531 49 7942680 | G69: 45703 | H69: =2345.42/2 -> 1172.71 | I69: 9 | J69: 10 | K69: Pago
A70: 69 | B70: 6 | C70: 1 | D70: 20 | E70: =_xlfn.XLOOKUP(D70,'🚛 FROTA'!A:A,'🚛 FROTA'!B:B,"") -> MAX4116 | F70: =_xlfn.XLOOKUP(B70,'🛡️ SEGUROS'!A:A,'🛡️ SEGUROS'!C:C,"") -> 171 49 24005792 | G70: 45703 | H70: 2531.41 | I70: 6 | J70: 6 | K70: Pago
A71: 70 | B71: 4 | C71: 1 | D71: 24 | E71: =_xlfn.XLOOKUP(D71,'🚛 FROTA'!A:A,'🚛 FROTA'!B:B,"") -> DYG5G03 | F71: =_xlfn.XLOOKUP(B71,'🛡️ SEGUROS'!A:A,'🛡️ SEGUROS'!C:C,"") -> 0531 49 8045088 | G71: 45726 | H71: =2910.47/10-0.01 -> 291.037 | I71: 6 | J71: 10 | K71: Pago
A72: 71 | B72: 4 | C72: 1 | D72: 39 | E72: =_xlfn.XLOOKUP(D72,'🚛 FROTA'!A:A,'🚛 FROTA'!B:B,"") -> EJX0I24 | F72: =_xlfn.XLOOKUP(B72,'🛡️ SEGUROS'!A:A,'🛡️ SEGUROS'!C:C,"") -> 0531 49 8045088 | G72: 45726 | H72: =2791.96/10-0.01 -> 279.186 | I72: 6 | J72: 10 | K72: Pago
A73: 72 | B73: 4 | C73: 1 | D73: 47 | E73: =_xlfn.XLOOKUP(D73,'🚛 FROTA'!A:A,'🚛 FROTA'!B:B,"") -> CUG4B86 | F73: =_xlfn.XLOOKUP(B73,'🛡️ SEGUROS'!A:A,'🛡️ SEGUROS'!C:C,"") -> 0531 49 8045088 | G73: 45726 | H73: =3041.09/10-0.01 -> 304.099 | I73: 6 | J73: 10 | K73: Pago
A74: 73 | B74: 5 | C74: 1 | D74: 6 | E74: =_xlfn.XLOOKUP(D74,'🚛 FROTA'!A:A,'🚛 FROTA'!B:B,"") -> EVF8I83 | F74: =_xlfn.XLOOKUP(B74,'🛡️ SEGUROS'!A:A,'🛡️ SEGUROS'!C:C,"") -> 0531 49 8045088 | G74: 45728 | H74: =3362.47/10+0.01 -> 336.257 | I74: 7 | J74: 10 | K74: Pago
A75: 74 | B75: 5 | C75: 1 | D75: 34 | E75: =_xlfn.XLOOKUP(D75,'🚛 FROTA'!A:A,'🚛 FROTA'!B:B,"") -> EXW7D65 | F75: =_xlfn.XLOOKUP(B75,'🛡️ SEGUROS'!A:A,'🛡️ SEGUROS'!C:C,"") -> 0531 49 8045088 | G75: 45728 | H75: =3236.1/10 -> 323.61 | I75: 7 | J75: 10 | K75: Pago
A76: 75 | B76: 5 | C76: 1 | D76: 46 | E76: =_xlfn.XLOOKUP(D76,'🚛 FROTA'!A:A,'🚛 FROTA'!B:B,"") -> CCU5G26 | F76: =_xlfn.XLOOKUP(B76,'🛡️ SEGUROS'!A:A,'🛡️ SEGUROS'!C:C,"") -> 0531 49 8045088 | G76: 45728 | H76: =3236.1/10 -> 323.61 | I76: 7 | J76: 10 | K76: Pago
A77: 76 | B77: 1 | C77: 1 | D77: 42 | E77: =_xlfn.XLOOKUP(D77,'🚛 FROTA'!A:A,'🚛 FROTA'!B:B,"") -> BSX5H07 | F77: =_xlfn.XLOOKUP(B77,'🛡️ SEGUROS'!A:A,'🛡️ SEGUROS'!C:C,"") -> 0531 49 7942680 | G77: 45731 | H77: =2345.42/2+0.1 -> 1172.81 | I77: 10 | J77: 10 | K77: Pago
A78: 77 | B78: 1 | C78: 1 | D78: 43 | E78: =_xlfn.XLOOKUP(D78,'🚛 FROTA'!A:A,'🚛 FROTA'!B:B,"") -> CSU3F94 | F78: =_xlfn.XLOOKUP(B78,'🛡️ SEGUROS'!A:A,'🛡️ SEGUROS'!C:C,"") -> 0531 49 7942680 | G78: 45731 | H78: =2345.42/2+0.1 -> 1172.81 | I78: 10 | J78: 10 | K78: Pago
A79: 78 | B79: 4 | C79: 1 | D79: 24 | E79: =_xlfn.XLOOKUP(D79,'🚛 FROTA'!A:A,'🚛 FROTA'!B:B,"") -> DYG5G03 | F79: =_xlfn.XLOOKUP(B79,'🛡️ SEGUROS'!A:A,'🛡️ SEGUROS'!C:C,"") -> 0531 49 8045088 | G79: 45757 | H79: =2910.47/10-0.01 -> 291.037 | I79: 7 | J79: 10 | K79: Pago
A80: 79 | B80: 4 | C80: 1 | D80: 39 | E80: =_xlfn.XLOOKUP(D80,'🚛 FROTA'!A:A,'🚛 FROTA'!B:B,"") -> EJX0I24 | F80: =_xlfn.XLOOKUP(B80,'🛡️ SEGUROS'!A:A,'🛡️ SEGUROS'!C:C,"") -> 0531 49 8045088 | G80: 45757 | H80: =2791.96/10-0.01 -> 279.186 | I80: 7 | J80: 10 | K80: Pago
A81: 80 | B81: 4 | C81: 1 | D81: 47 | E81: =_xlfn.XLOOKUP(D81,'🚛 FROTA'!A:A,'🚛 FROTA'!B:B,"") -> CUG4B86 | F81: =_xlfn.XLOOKUP(B81,'🛡️ SEGUROS'!A:A,'🛡️ SEGUROS'!C:C,"") -> 0531 49 8045088 | G81: 45757 | H81: =3041.09/10-0.01 -> 304.099 | I81: 7 | J81: 10 | K81: Pago
A82: 81 | B82: 5 | C82: 1 | D82: 6 | E82: =_xlfn.XLOOKUP(D82,'🚛 FROTA'!A:A,'🚛 FROTA'!B:B,"") -> EVF8I83 | F82: =_xlfn.XLOOKUP(B82,'🛡️ SEGUROS'!A:A,'🛡️ SEGUROS'!C:C,"") -> 0531 49 8045088 | G82: 45759 | H82: =3362.47/10+0.01 -> 336.257 | I82: 8 | J82: 10 | K82: Pago
A83: 82 | B83: 5 | C83: 1 | D83: 34 | E83: =_xlfn.XLOOKUP(D83,'🚛 FROTA'!A:A,'🚛 FROTA'!B:B,"") -> EXW7D65 | F83: =_xlfn.XLOOKUP(B83,'🛡️ SEGUROS'!A:A,'🛡️ SEGUROS'!C:C,"") -> 0531 49 8045088 | G83: 45759 | H83: =3236.1/10 -> 323.61 | I83: 8 | J83: 10 | K83: Pago
A84: 83 | B84: 5 | C84: 1 | D84: 46 | E84: =_xlfn.XLOOKUP(D84,'🚛 FROTA'!A:A,'🚛 FROTA'!B:B,"") -> CCU5G26 | F84: =_xlfn.XLOOKUP(B84,'🛡️ SEGUROS'!A:A,'🛡️ SEGUROS'!C:C,"") -> 0531 49 8045088 | G84: 45759 | H84: =3236.1/10 -> 323.61 | I84: 8 | J84: 10 | K84: Pago
A85: 84 | B85: 4 | C85: 1 | D85: 24 | E85: =_xlfn.XLOOKUP(D85,'🚛 FROTA'!A:A,'🚛 FROTA'!B:B,"") -> DYG5G03 | F85: =_xlfn.XLOOKUP(B85,'🛡️ SEGUROS'!A:A,'🛡️ SEGUROS'!C:C,"") -> 0531 49 8045088 | G85: 45787 | H85: =2910.47/10-0.01 -> 291.037 | I85: 8 | J85: 10 | K85: Pago
A86: 85 | B86: 4 | C86: 1 | D86: 39 | E86: =_xlfn.XLOOKUP(D86,'🚛 FROTA'!A:A,'🚛 FROTA'!B:B,"") -> EJX0I24 | F86: =_xlfn.XLOOKUP(B86,'🛡️ SEGUROS'!A:A,'🛡️ SEGUROS'!C:C,"") -> 0531 49 8045088 | G86: 45787 | H86: =2791.96/10-0.01 -> 279.186 | I86: 8 | J86: 10 | K86: Pago
A87: 86 | B87: 4 | C87: 1 | D87: 47 | E87: =_xlfn.XLOOKUP(D87,'🚛 FROTA'!A:A,'🚛 FROTA'!B:B,"") -> CUG4B86 | F87: =_xlfn.XLOOKUP(B87,'🛡️ SEGUROS'!A:A,'🛡️ SEGUROS'!C:C,"") -> 0531 49 8045088 | G87: 45787 | H87: =3041.09/10-0.01 -> 304.099 | I87: 8 | J87: 10 | K87: Pago
A88: 87 | B88: 5 | C88: 1 | D88: 6 | E88: =_xlfn.XLOOKUP(D88,'🚛 FROTA'!A:A,'🚛 FROTA'!B:B,"") -> EVF8I83 | F88: =_xlfn.XLOOKUP(B88,'🛡️ SEGUROS'!A:A,'🛡️ SEGUROS'!C:C,"") -> 0531 49 8045088 | G88: 45789 | H88: =3362.47/10+0.01 -> 336.257 | I88: 9 | J88: 10 | K88: Pago
A89: 88 | B89: 5 | C89: 1 | D89: 34 | E89: =_xlfn.XLOOKUP(D89,'🚛 FROTA'!A:A,'🚛 FROTA'!B:B,"") -> EXW7D65 | F89: =_xlfn.XLOOKUP(B89,'🛡️ SEGUROS'!A:A,'🛡️ SEGUROS'!C:C,"") -> 0531 49 8045088 | G89: 45789 | H89: =3236.1/10 -> 323.61 | I89: 9 | J89: 10 | K89: Pago
A90: 89 | B90: 5 | C90: 1 | D90: 46 | E90: =_xlfn.XLOOKUP(D90,'🚛 FROTA'!A:A,'🚛 FROTA'!B:B,"") -> CCU5G26 | F90: =_xlfn.XLOOKUP(B90,'🛡️ SEGUROS'!A:A,'🛡️ SEGUROS'!C:C,"") -> 0531 49 8045088 | G90: 45789 | H90: =3236.1/10 -> 323.61 | I90: 9 | J90: 10 | K90: Pago
A91: 90 | B91: 8 | C91: 1 | D91: 42 | E91: =_xlfn.XLOOKUP(D91,'🚛 FROTA'!A:A,'🚛 FROTA'!B:B,"") -> BSX5H07 | F91: =_xlfn.XLOOKUP(B91,'🛡️ SEGUROS'!A:A,'🛡️ SEGUROS'!C:C,"") -> 0531 49 8359988 | G91: 45814 | H91: =873.76/2 -> 436.88 | I91: 1 | J91: 10 | K91: Pago
A92: 91 | B92: 8 | C92: 1 | D92: 43 | E92: =_xlfn.XLOOKUP(D92,'🚛 FROTA'!A:A,'🚛 FROTA'!B:B,"") -> CSU3F94 | F92: =_xlfn.XLOOKUP(B92,'🛡️ SEGUROS'!A:A,'🛡️ SEGUROS'!C:C,"") -> 0531 49 8359988 | G92: 45814 | H92: =873.76/2 -> 436.88 | I92: 1 | J92: 10 | K92: Pago
A93: 92 | B93: 4 | C93: 1 | D93: 24 | E93: =_xlfn.XLOOKUP(D93,'🚛 FROTA'!A:A,'🚛 FROTA'!B:B,"") -> DYG5G03 | F93: =_xlfn.XLOOKUP(B93,'🛡️ SEGUROS'!A:A,'🛡️ SEGUROS'!C:C,"") -> 0531 49 8045088 | G93: 45818 | H93: =2910.47/10-0.01 -> 291.037 | I93: 9 | J93: 10 | K93: Pago
A94: 93 | B94: 4 | C94: 1 | D94: 39 | E94: =_xlfn.XLOOKUP(D94,'🚛 FROTA'!A:A,'🚛 FROTA'!B:B,"") -> EJX0I24 | F94: =_xlfn.XLOOKUP(B94,'🛡️ SEGUROS'!A:A,'🛡️ SEGUROS'!C:C,"") -> 0531 49 8045088 | G94: 45818 | H94: =2791.96/10-0.01 -> 279.186 | I94: 9 | J94: 10 | K94: Pago
A95: 94 | B95: 4 | C95: 1 | D95: 47 | E95: =_xlfn.XLOOKUP(D95,'🚛 FROTA'!A:A,'🚛 FROTA'!B:B,"") -> CUG4B86 | F95: =_xlfn.XLOOKUP(B95,'🛡️ SEGUROS'!A:A,'🛡️ SEGUROS'!C:C,"") -> 0531 49 8045088 | G95: 45818 | H95: =3041.09/10-0.01 -> 304.099 | I95: 9 | J95: 10 | K95: Pago
A96: 95 | B96: 5 | C96: 1 | D96: 6 | E96: =_xlfn.XLOOKUP(D96,'🚛 FROTA'!A:A,'🚛 FROTA'!B:B,"") -> EVF8I83 | F96: =_xlfn.XLOOKUP(B96,'🛡️ SEGUROS'!A:A,'🛡️ SEGUROS'!C:C,"") -> 0531 49 8045088 | G96: 45820 | H96: =3362.47/10-6.32 -> 329.927 | I96: 10 | J96: 10 | K96: Pago
A97: 96 | B97: 5 | C97: 1 | D97: 34 | E97: =_xlfn.XLOOKUP(D97,'🚛 FROTA'!A:A,'🚛 FROTA'!B:B,"") -> EXW7D65 | F97: =_xlfn.XLOOKUP(B97,'🛡️ SEGUROS'!A:A,'🛡️ SEGUROS'!C:C,"") -> 0531 49 8045088 | G97: 45820 | H97: =3236.1/10-6.32 -> 317.29 | I97: 10 | J97: 10 | K97: Pago
A98: 97 | B98: 5 | C98: 1 | D98: 46 | E98: =_xlfn.XLOOKUP(D98,'🚛 FROTA'!A:A,'🚛 FROTA'!B:B,"") -> CCU5G26 | F98: =_xlfn.XLOOKUP(B98,'🛡️ SEGUROS'!A:A,'🛡️ SEGUROS'!C:C,"") -> 0531 49 8045088 | G98: 45820 | H98: =3236.1/10-6.32 -> 317.29 | I98: 10 | J98: 10 | K98: Pago
A99: 98 | B99: 9 | C99: 1 | D99: 17 | E99: =_xlfn.XLOOKUP(D99,'🚛 FROTA'!A:A,'🚛 FROTA'!B:B,"") -> BQV5264 | F99: =_xlfn.XLOOKUP(B99,'🛡️ SEGUROS'!A:A,'🛡️ SEGUROS'!C:C,"") -> 171 49 24007849 | G99: 46192 | H99: =7136.94/6 -> 1189.49 | I99: 1 | J99: 6 | K99: Pago
A100: 99 | B100: 4 | C100: 1 | D100: 24 | E100: =_xlfn.XLOOKUP(D100,'🚛 FROTA'!A:A,'🚛 FROTA'!B:B,"") -> DYG5G03 | F100: =_xlfn.XLOOKUP(B100,'🛡️ SEGUROS'!A:A,'🛡️ SEGUROS'!C:C,"") -> 0531 49 8045088 | G100: 45848 | H100: =2910.47/10+0.1 -> 291.147 | I100: 10 | J100: 10 | K100: Pago
...

Sheet 🔧 MANUTENCOES
A1: IDManutencao | B1: ValidaNovaOS | C1: IDOrdServ | D1: NFOrdem | E1: TotalOS | F1: Empresa | G1: Placa | H1: IDVeiculo | I1: IDContrato | J1: Modelo | K1: Implemento | L1: Fornecedor | M1: Nota | N1: Data Venc. | O1: ParcelaAtual | P1: ParcelaTotal | Q1: ValorParcela | R1: FormaPgto | S1: Categoria | T1: Status | U1: TipoManutencao | V1: Sistema | W1: Serviço | X1: Descricao | Y1: QtdItens | Z1: KM | AA1: PosiçãoPneu | AB1: QtdPneu | AC1: EspecificaçãoPneu | AD1: MarcaPneu | AE1: ModeloPneu | AF1: CondicaoPneu | AG1: ManejoPneu | AH1: DataExecução | AI1: ResponsavelTec | AJ1: Indisponível | AK1: ProxKM | AL1: ProxData | AM1: Obsercacoes
A2: 1 | C2: OS-2024-0001 | D2: {=SUM(--(_xlfn.UNIQUE(_xlfn._xlws.FILTER($M$2:$M$1011 & "", ($C$2:$C$1011 = C2) * ($M$2:$M$1011 <> ""))) <> ""))} -> 1 | E2: =SUMIF(C:C, C2, Q:Q) -> 2169.99 | F2: 1 | G2: CSU3F94 | H2: =_xlfn.XLOOKUP(G2,'🚛 FROTA'!B:B,'🚛 FROTA'!A:A,"") -> 43 | J2: =IF(G2="","",_xlfn.XLOOKUP(G2,'🚛 FROTA'!B:B,'🚛 FROTA'!E:E,"")) -> Express Delivery | K2: =IF(G2="","",_xlfn.XLOOKUP(G2,'🚛 FROTA'!B:B,'🚛 FROTA'!K:K,"")) -> Carroceria | L2: FLORENZA TRUCK | M2: 2036/2754 | N2: 45487 | O2: 1 | P2: 3 | Q2: 723.33 | R2: Faturado | S2: Serviço | T2: Pago | U2: Corretiva | V2: Freio | W2: SUBST. PASTILHAS E DISCOS | X2: SUBSTITUIÇÃO DE PASTILHAS (DIANT.+TRAS.) E DISCOS DIANTEIROS | Z2: 31751 | AH2: =IF(OR(R2="A VISTA", R2="C. CRÉDITO", R2="ADIANTAMENTO"), N2, IF(R2="Faturado", _xlfn.MINIFS(N:N, C:C, C2)-30, "")) -> 45457 | AI2: AROUDO
A3: 2 | C3: OS-2024-0001 | D3: {=SUM(--(_xlfn.UNIQUE(_xlfn._xlws.FILTER($M$2:$M$1011 & "", ($C$2:$C$1011 = C3) * ($M$2:$M$1011 <> ""))) <> ""))} -> 1 | E3: =SUMIF(C:C, C3, Q:Q) -> 2169.99 | F3: 1 | G3: CSU3F94 | H3: =_xlfn.XLOOKUP(G3,'🚛 FROTA'!B:B,'🚛 FROTA'!A:A,"") -> 43 | J3: =IF(G3="","",_xlfn.XLOOKUP(G3,'🚛 FROTA'!B:B,'🚛 FROTA'!E:E,"")) -> Express Delivery | K3: =IF(G3="","",_xlfn.XLOOKUP(G3,'🚛 FROTA'!B:B,'🚛 FROTA'!K:K,"")) -> Carroceria | L3: FLORENZA TRUCK | M3: 2036/2754 | N3: 45517 | O3: 2 | P3: 3 | Q3: 723.33 | R3: Faturado | S3: Compra | T3: Pago | U3: Corretiva | V3: Freio | W3: SUBST. PASTILHAS E DISCOS | X3: SUBSTITUIÇÃO DE PASTILHAS (DIANT.+TRAS.) E DISCOS DIANTEIROS | Z3: 31751 | AH3: =IF(OR(R3="A VISTA", R3="C. CRÉDITO", R3="ADIANTAMENTO"), N3, IF(R3="Faturado", _xlfn.MINIFS(N:N, C:C, C3)-30, "")) -> 45457 | AI3: AROUDO
A4: 3 | C4: OS-2024-0001 | D4: {=SUM(--(_xlfn.UNIQUE(_xlfn._xlws.FILTER($M$2:$M$1011 & "", ($C$2:$C$1011 = C4) * ($M$2:$M$1011 <> ""))) <> ""))} -> 1 | E4: =SUMIF(C:C, C4, Q:Q) -> 2169.99 | F4: 1 | G4: CSU3F94 | H4: =_xlfn.XLOOKUP(G4,'🚛 FROTA'!B:B,'🚛 FROTA'!A:A,"") -> 43 | J4: =IF(G4="","",_xlfn.XLOOKUP(G4,'🚛 FROTA'!B:B,'🚛 FROTA'!E:E,"")) -> Express Delivery | K4: =IF(G4="","",_xlfn.XLOOKUP(G4,'🚛 FROTA'!B:B,'🚛 FROTA'!K:K,"")) -> Carroceria | L4: FLORENZA TRUCK | M4: 2036/2754 | N4: 45547 | O4: 3 | P4: 3 | Q4: 723.33 | R4: Faturado | S4: Serviço | T4: Pago | U4: Corretiva | V4: Freio | W4: SUBST. PASTILHAS E DISCOS | X4: SUBSTITUIÇÃO DE PASTILHAS (DIANT.+TRAS.) E DISCOS DIANTEIROS | Z4: 31751 | AH4: =IF(OR(R4="A VISTA", R4="C. CRÉDITO", R4="ADIANTAMENTO"), N4, IF(R4="Faturado", _xlfn.MINIFS(N:N, C:C, C4)-30, "")) -> 45457 | AI4: AROUDO
A5: 4 | C5: OS-2024-0002 | D5: {=SUM(--(_xlfn.UNIQUE(_xlfn._xlws.FILTER($M$2:$M$1011 & "", ($C$2:$C$1011 = C5) * ($M$2:$M$1011 <> ""))) <> ""))} -> 1 | E5: =SUMIF(C:C, C5, Q:Q) -> 3424.84 | F5: 1 | G5: EXW7D65 | H5: =_xlfn.XLOOKUP(G5,'🚛 FROTA'!B:B,'🚛 FROTA'!A:A,"") -> 34 | J5: =IF(G5="","",_xlfn.XLOOKUP(G5,'🚛 FROTA'!B:B,'🚛 FROTA'!E:E,"")) -> 9.170 Delivery | K5: =IF(G5="","",_xlfn.XLOOKUP(G5,'🚛 FROTA'!B:B,'🚛 FROTA'!K:K,"")) -> Basculante | L5: FLORENZA TRUCK | M5: 3078/2335 | N5: 45630 | O5: 1 | P5: 4 | Q5: 856.21 | R5: Faturado | S5: Serviço | T5: Pago | U5: Corretiva | V5: Freio | W5: SUBST. LONAS E TAMBOR | X5: SUBST. LONAS (DIANT.+TRAS.), TAMBOR TRASEIRO E RETÍFICA DE CAMPANAS DIANTEIRAS | Z5: 58017 | AH5: =IF(OR(R5="A VISTA", R5="C. CRÉDITO", R5="ADIANTAMENTO"), N5, IF(R5="Faturado", _xlfn.MINIFS(N:N, C:C, C5)-30, "")) -> 45600 | AI5: AROUDO
A6: 5 | C6: OS-2025-0003 | D6: {=SUM(--(_xlfn.UNIQUE(_xlfn._xlws.FILTER($M$2:$M$1011 & "", ($C$2:$C$1011 = C6) * ($M$2:$M$1011 <> ""))) <> ""))} -> 1 | E6: =SUMIF(C:C, C6, Q:Q) -> 0 | F6: 1 | G6: CCF9F13 | H6: =_xlfn.XLOOKUP(G6,'🚛 FROTA'!B:B,'🚛 FROTA'!A:A,"") -> 33 | J6: =IF(G6="","",_xlfn.XLOOKUP(G6,'🚛 FROTA'!B:B,'🚛 FROTA'!E:E,"")) -> Fiorino Working | L6: TKJ GERENCIAMENTO | M6: 0 | N6: 45658 | O6: 1 | P6: 1 | Q6: 0 | R6: Faturado | S6: Serviço | T6: Pago | U6: Corretiva | V6: Diversos | W6: LANÇAMENTO INTERNO | X6: LANÇAMENTO INTERNO / AUTORIZAÇÃO (SEM DESCRIÇÃO) | AH6: =IF(OR(R6="A VISTA", R6="C. CRÉDITO", R6="ADIANTAMENTO"), N6, IF(R6="Faturado", _xlfn.MINIFS(N:N, C:C, C6)-30, "")) -> 45628
A7: 6 | C7: OS-2025-0004 | D7: {=SUM(--(_xlfn.UNIQUE(_xlfn._xlws.FILTER($M$2:$M$1011 & "", ($C$2:$C$1011 = C7) * ($M$2:$M$1011 <> ""))) <> ""))} -> 2 | E7: =SUMIF(C:C, C7, Q:Q) -> 1871.58 | F7: 1 | G7: BSX5H07 | H7: =_xlfn.XLOOKUP(G7,'🚛 FROTA'!B:B,'🚛 FROTA'!A:A,"") -> 42 | J7: =IF(G7="","",_xlfn.XLOOKUP(G7,'🚛 FROTA'!B:B,'🚛 FROTA'!E:E,"")) -> Express Delivery | K7: =IF(G7="","",_xlfn.XLOOKUP(G7,'🚛 FROTA'!B:B,'🚛 FROTA'!K:K,"")) -> Carroceria | L7: CAIADO PNEUS | M7: 67005 | N7: 45660 | O7: 1 | P7: 2 | Q7: 788 | R7: Faturado | S7: Compra | T7: Pago | U7: Corretiva | V7: Pneu | W7: FORNEC. PNEUS | X7: FORNECIMENTO: 02 PNEUS 225/75R16C XBRI FORZA DIANTEIROS | Y7: 02 PNEUS | Z7: 50456 | AA7: DIANTEIRO | AB7: 2 | AC7: 225/75R16C | AD7: XBRI | AE7: FORZA | AF7: NOVO | AG7: Loja | AH7: =IF(OR(R7="A VISTA", R7="C. CRÉDITO", R7="ADIANTAMENTO"), N7, IF(R7="Faturado", _xlfn.MINIFS(N:N, C:C, C7)-30, "")) -> 45630 | AI7: THIAGO
A8: 7 | C8: OS-2024-0002 | D8: {=SUM(--(_xlfn.UNIQUE(_xlfn._xlws.FILTER($M$2:$M$1011 & "", ($C$2:$C$1011 = C8) * ($M$2:$M$1011 <> ""))) <> ""))} -> 1 | E8: =SUMIF(C:C, C8, Q:Q) -> 3424.84 | F8: 1 | G8: EXW7D65 | H8: =_xlfn.XLOOKUP(G8,'🚛 FROTA'!B:B,'🚛 FROTA'!A:A,"") -> 34 | J8: =IF(G8="","",_xlfn.XLOOKUP(G8,'🚛 FROTA'!B:B,'🚛 FROTA'!E:E,"")) -> 9.170 Delivery | K8: =IF(G8="","",_xlfn.XLOOKUP(G8,'🚛 FROTA'!B:B,'🚛 FROTA'!K:K,"")) -> Basculante | L8: FLORENZA TRUCK | M8: 3078/2335 | N8: 45660 | O8: 2 | P8: 4 | Q8: 856.21 | R8: Faturado | S8: Serviço | T8: Pago | U8: Corretiva | V8: Freio | W8: SUBST. LONAS E TAMBOR | X8: SUBST. LONAS (DIANT.+TRAS.), TAMBOR TRASEIRO E RETÍFICA DE CAMPANAS DIANTEIRAS | Z8: 58017 | AH8: =IF(OR(R8="A VISTA", R8="C. CRÉDITO", R8="ADIANTAMENTO"), N8, IF(R8="Faturado", _xlfn.MINIFS(N:N, C:C, C8)-30, "")) -> 45600 | AI8: AROUDO
A9: 8 | C9: OS-2025-0004 | D9: {=SUM(--(_xlfn.UNIQUE(_xlfn._xlws.FILTER($M$2:$M$1011 & "", ($C$2:$C$1011 = C9) * ($M$2:$M$1011 <> ""))) <> ""))} -> 2 | E9: =SUMIF(C:C, C9, Q:Q) -> 1871.58 | F9: 1 | G9: BSX5H07 | H9: =_xlfn.XLOOKUP(G9,'🚛 FROTA'!B:B,'🚛 FROTA'!A:A,"") -> 42 | J9: =IF(G9="","",_xlfn.XLOOKUP(G9,'🚛 FROTA'!B:B,'🚛 FROTA'!E:E,"")) -> Express Delivery | K9: =IF(G9="","",_xlfn.XLOOKUP(G9,'🚛 FROTA'!B:B,'🚛 FROTA'!K:K,"")) -> Carroceria | L9: CAIADO PNEUS | M9: 15502 | N9: 45665 | O9: 1 | P9: 1 | Q9: 295.58 | R9: Faturado | S9: Serviço | T9: Pago | U9: Corretiva | V9: Pneu | W9: MONTAGEM E ALINHAMENTO PNEUS | X9: Serviço: MONTAGEM, ALINHAMENTO E BALANCEAMENTO DE PNEUS DIANTEIROS (REF. NF 67005) | Z9: 50456 | AA9: DIANTEIRO | AB9: 2 | AC9: 225/75R16C | AE9: XBRI | AG9: Borracharia | AH9: =IF(OR(R9="A VISTA", R9="C. CRÉDITO", R9="ADIANTAMENTO"), N9, IF(R9="Faturado", _xlfn.MINIFS(N:N, C:C, C9)-30, "")) -> 45630 | AI9: THIAGO
A10: 9 | C10: OS-2025-0004 | D10: {=SUM(--(_xlfn.UNIQUE(_xlfn._xlws.FILTER($M$2:$M$1011 & "", ($C$2:$C$1011 = C10) * ($M$2:$M$1011 <> ""))) <> ""))} -> 2 | E10: =SUMIF(C:C, C10, Q:Q) -> 1871.58 | F10: 1 | G10: BSX5H07 | H10: =_xlfn.XLOOKUP(G10,'🚛 FROTA'!B:B,'🚛 FROTA'!A:A,"") -> 42 | J10: =IF(G10="","",_xlfn.XLOOKUP(G10,'🚛 FROTA'!B:B,'🚛 FROTA'!E:E,"")) -> Express Delivery | K10: =IF(G10="","",_xlfn.XLOOKUP(G10,'🚛 FROTA'!B:B,'🚛 FROTA'!K:K,"")) -> Carroceria | L10: CAIADO PNEUS | M10: 67005 | N10: 45691 | O10: 2 | P10: 2 | Q10: 788 | R10: Faturado | S10: Compra | T10: Pago | U10: Corretiva | V10: Pneu | W10: FORNEC. PNEUS | X10: FORNECIMENTO: 02 PNEUS 225/75R16C XBRI FORZA DIANTEIROS | Y10: 02 PNEUS | Z10: 50456 | AA10: DIANTEIRO | AB10: 2 | AC10: 225/75R16C | AD10: XBRI | AE10: FORZA | AF10: NOVO | AG10: Loja | AH10: =IF(OR(R10="A VISTA", R10="C. CRÉDITO", R10="ADIANTAMENTO"), N10, IF(R10="Faturado", _xlfn.MINIFS(N:N, C:C, C10)-30, "")) -> 45630 | AI10: THIAGO
A11: 10 | C11: OS-2025-0005 | D11: {=SUM(--(_xlfn.UNIQUE(_xlfn._xlws.FILTER($M$2:$M$1011 & "", ($C$2:$C$1011 = C11) * ($M$2:$M$1011 <> ""))) <> ""))} -> 1 | E11: =SUMIF(C:C, C11, Q:Q) -> 2340 | F11: 1 | G11: CSU3F94 | H11: =_xlfn.XLOOKUP(G11,'🚛 FROTA'!B:B,'🚛 FROTA'!A:A,"") -> 43 | J11: =IF(G11="","",_xlfn.XLOOKUP(G11,'🚛 FROTA'!B:B,'🚛 FROTA'!E:E,"")) -> Express Delivery | K11: =IF(G11="","",_xlfn.XLOOKUP(G11,'🚛 FROTA'!B:B,'🚛 FROTA'!K:K,"")) -> Carroceria | L11: FLORENZA TRUCK | M11: 2436/3192 | N11: 45665 | O11: 1 | P11: 3 | Q11: 780 | R11: Faturado | S11: Serviço | T11: Pago | U11: Corretiva | V11: Freio | W11: SUBST. PASTILHAS E DISCOS | X11: SUBSTITUIÇÃO DE PASTILHAS (DIANT.+TRAS.) E DISCOS DIANTEIROS | Z11: 37842 | AH11: =IF(OR(R11="A VISTA", R11="C. CRÉDITO", R11="ADIANTAMENTO"), N11, IF(R11="Faturado", _xlfn.MINIFS(N:N, C:C, C11)-30, "")) -> 45635 | AI11: AROUDO
A12: 11 | C12: OS-2025-0005 | D12: {=SUM(--(_xlfn.UNIQUE(_xlfn._xlws.FILTER($M$2:$M$1011 & "", ($C$2:$C$1011 = C12) * ($M$2:$M$1011 <> ""))) <> ""))} -> 1 | E12: =SUMIF(C:C, C12, Q:Q) -> 2340 | F12: 1 | G12: CSU3F94 | H12: =_xlfn.XLOOKUP(G12,'🚛 FROTA'!B:B,'🚛 FROTA'!A:A,"") -> 43 | J12: =IF(G12="","",_xlfn.XLOOKUP(G12,'🚛 FROTA'!B:B,'🚛 FROTA'!E:E,"")) -> Express Delivery | K12: =IF(G12="","",_xlfn.XLOOKUP(G12,'🚛 FROTA'!B:B,'🚛 FROTA'!K:K,"")) -> Carroceria | L12: FLORENZA TRUCK | M12: 2436/3192 | N12: 45695 | O12: 2 | P12: 3 | Q12: 780 | R12: Faturado | S12: Serviço | T12: Pago | U12: Corretiva | V12: Freio | W12: SUBST. PASTILHAS E DISCOS | X12: SUBSTITUIÇÃO DE PASTILHAS (DIANT.+TRAS.) E DISCOS DIANTEIROS | Z12: 37842 | AH12: =IF(OR(R12="A VISTA", R12="C. CRÉDITO", R12="ADIANTAMENTO"), N12, IF(R12="Faturado", _xlfn.MINIFS(N:N, C:C, C12)-30, "")) -> 45635 | AI12: AROUDO
A13: 12 | C13: OS-2025-0005 | D13: {=SUM(--(_xlfn.UNIQUE(_xlfn._xlws.FILTER($M$2:$M$1011 & "", ($C$2:$C$1011 = C13) * ($M$2:$M$1011 <> ""))) <> ""))} -> 1 | E13: =SUMIF(C:C, C13, Q:Q) -> 2340 | F13: 1 | G13: CSU3F94 | H13: =_xlfn.XLOOKUP(G13,'🚛 FROTA'!B:B,'🚛 FROTA'!A:A,"") -> 43 | J13: =IF(G13="","",_xlfn.XLOOKUP(G13,'🚛 FROTA'!B:B,'🚛 FROTA'!E:E,"")) -> Express Delivery | K13: =IF(G13="","",_xlfn.XLOOKUP(G13,'🚛 FROTA'!B:B,'🚛 FROTA'!K:K,"")) -> Carroceria | L13: FLORENZA TRUCK | M13: 2436/3192 | N13: 45725 | O13: 3 | P13: 3 | Q13: 780 | R13: Faturado | S13: Serviço | T13: Pago | U13: Corretiva | V13: Freio | W13: SUBST. PASTILHAS E DISCOS | X13: SUBSTITUIÇÃO DE PASTILHAS (DIANT.+TRAS.) E DISCOS DIANTEIROS | Z13: 37842 | AH13: =IF(OR(R13="A VISTA", R13="C. CRÉDITO", R13="ADIANTAMENTO"), N13, IF(R13="Faturado", _xlfn.MINIFS(N:N, C:C, C13)-30, "")) -> 45635 | AI13: AROUDO
A14: 13 | C14: OS-2025-0006 | D14: {=SUM(--(_xlfn.UNIQUE(_xlfn._xlws.FILTER($M$2:$M$1011 & "", ($C$2:$C$1011 = C14) * ($M$2:$M$1011 <> ""))) <> ""))} -> 2 | E14: =SUMIF(C:C, C14, Q:Q) -> 1877.12 | F14: 1 | G14: CSU3F94 | H14: =_xlfn.XLOOKUP(G14,'🚛 FROTA'!B:B,'🚛 FROTA'!A:A,"") -> 43 | J14: =IF(G14="","",_xlfn.XLOOKUP(G14,'🚛 FROTA'!B:B,'🚛 FROTA'!E:E,"")) -> Express Delivery | K14: =IF(G14="","",_xlfn.XLOOKUP(G14,'🚛 FROTA'!B:B,'🚛 FROTA'!K:K,"")) -> Carroceria | L14: CAIADO PNEUS | M14: 67052 | N14: 45667 | O14: 1 | P14: 3 | Q14: 523.33 | R14: Faturado | S14: Compra | T14: Pago | U14: Corretiva | V14: Pneu | W14: FORNEC. PNEUS | X14: FORNECIMENTO: 02 PNEUS 225/75R16C XBRI FORZA DIANTEIROS | Y14: 02 PNEUS | Z14: 38060 | AA14: DIANTEIRO | AB14: 2 | AC14: 225/75R16C | AD14: XBRI | AE14: FORZA | AF14: NOVO | AG14: Loja | AH14: =IF(OR(R14="A VISTA", R14="C. CRÉDITO", R14="ADIANTAMENTO"), N14, IF(R14="Faturado", _xlfn.MINIFS(N:N, C:C, C14)-30, "")) -> 45637 | AI14: THIAGO
A15: 14 | C15: OS-2025-0006 | D15: {=SUM(--(_xlfn.UNIQUE(_xlfn._xlws.FILTER($M$2:$M$1011 & "", ($C$2:$C$1011 = C15) * ($M$2:$M$1011 <> ""))) <> ""))} -> 2 | E15: =SUMIF(C:C, C15, Q:Q) -> 1877.12 | F15: 1 | G15: CSU3F94 | H15: =_xlfn.XLOOKUP(G15,'🚛 FROTA'!B:B,'🚛 FROTA'!A:A,"") -> 43 | J15: =IF(G15="","",_xlfn.XLOOKUP(G15,'🚛 FROTA'!B:B,'🚛 FROTA'!E:E,"")) -> Express Delivery | K15: =IF(G15="","",_xlfn.XLOOKUP(G15,'🚛 FROTA'!B:B,'🚛 FROTA'!K:K,"")) -> Carroceria | L15: CAIADO PNEUS | M15: 15506 | N15: 45670 | O15: 1 | P15: 1 | Q15: 305.12 | R15: Faturado | S15: Serviço | T15: Pago | U15: Corretiva | V15: Pneu | W15: MONTAGEM E ALINHAMENTO PNEUS | X15: Serviço: MONTAGEM, ALINHAMENTO E BALANCEAMENTO DE PNEUS DIANTEIROS (REF. NF 67052) | Z15: 38060 | AA15: DIANTEIRO | AB15: 2 | AC15: 225/75R16C | AE15: XBRI | AG15: Borracharia | AH15: =IF(OR(R15="A VISTA", R15="C. CRÉDITO", R15="ADIANTAMENTO"), N15, IF(R15="Faturado", _xlfn.MINIFS(N:N, C:C, C15)-30, "")) -> 45637 | AI15: THIAGO
A16: 15 | C16: OS-2025-0006 | D16: {=SUM(--(_xlfn.UNIQUE(_xlfn._xlws.FILTER($M$2:$M$1011 & "", ($C$2:$C$1011 = C16) * ($M$2:$M$1011 <> ""))) <> ""))} -> 2 | E16: =SUMIF(C:C, C16, Q:Q) -> 1877.12 | F16: 1 | G16: CSU3F94 | H16: =_xlfn.XLOOKUP(G16,'🚛 FROTA'!B:B,'🚛 FROTA'!A:A,"") -> 43 | J16: =IF(G16="","",_xlfn.XLOOKUP(G16,'🚛 FROTA'!B:B,'🚛 FROTA'!E:E,"")) -> Express Delivery | K16: =IF(G16="","",_xlfn.XLOOKUP(G16,'🚛 FROTA'!B:B,'🚛 FROTA'!K:K,"")) -> Carroceria | L16: CAIADO PNEUS | M16: 67052 | N16: 45698 | O16: 2 | P16: 3 | Q16: 523.33 | R16: Faturado | S16: Compra | T16: Pago | U16: Corretiva | V16: Pneu | W16: FORNEC. PNEUS | X16: FORNECIMENTO: 02 PNEUS 225/75R16C XBRI FORZA DIANTEIROS | Y16: 02 PNEUS | Z16: 38060 | AA16: DIANTEIRO | AB16: 2 | AC16: 225/75R16C | AD16: XBRI | AE16: FORZA | AF16: NOVO | AG16: Loja | AH16: =IF(OR(R16="A VISTA", R16="C. CRÉDITO", R16="ADIANTAMENTO"), N16, IF(R16="Faturado", _xlfn.MINIFS(N:N, C:C, C16)-30, "")) -> 45637 | AI16: THIAGO
A17: 16 | C17: OS-2025-0006 | D17: {=SUM(--(_xlfn.UNIQUE(_xlfn._xlws.FILTER($M$2:$M$1011 & "", ($C$2:$C$1011 = C17) * ($M$2:$M$1011 <> ""))) <> ""))} -> 2 | E17: =SUMIF(C:C, C17, Q:Q) -> 1877.12 | F17: 1 | G17: CSU3F94 | H17: =_xlfn.XLOOKUP(G17,'🚛 FROTA'!B:B,'🚛 FROTA'!A:A,"") -> 43 | J17: =IF(G17="","",_xlfn.XLOOKUP(G17,'🚛 FROTA'!B:B,'🚛 FROTA'!E:E,"")) -> Express Delivery | K17: =IF(G17="","",_xlfn.XLOOKUP(G17,'🚛 FROTA'!B:B,'🚛 FROTA'!K:K,"")) -> Carroceria | L17: CAIADO PNEUS | M17: 67052 | N17: 45727 | O17: 3 | P17: 3 | Q17: 525.34 | R17: Faturado | S17: Compra | T17: Pago | U17: Corretiva | V17: Pneu | W17: FORNEC. PNEUS | X17: FORNECIMENTO: 02 PNEUS 225/75R16C XBRI FORZA DIANTEIROS | Y17: 02 PNEUS | Z17: 38060 | AA17: DIANTEIRO | AB17: 2 | AC17: 225/75R16C | AD17: XBRI | AE17: FORZA | AF17: NOVO | AG17: Loja | AH17: =IF(OR(R17="A VISTA", R17="C. CRÉDITO", R17="ADIANTAMENTO"), N17, IF(R17="Faturado", _xlfn.MINIFS(N:N, C:C, C17)-30, "")) -> 45637 | AI17: THIAGO
A18: 17 | C18: OS-2025-0007 | D18: {=SUM(--(_xlfn.UNIQUE(_xlfn._xlws.FILTER($M$2:$M$1011 & "", ($C$2:$C$1011 = C18) * ($M$2:$M$1011 <> ""))) <> ""))} -> 1 | E18: =SUMIF(C:C, C18, Q:Q) -> 668.29 | F18: 1 | G18: DYG5G03 | H18: =_xlfn.XLOOKUP(G18,'🚛 FROTA'!B:B,'🚛 FROTA'!A:A,"") -> 24 | J18: =IF(G18="","",_xlfn.XLOOKUP(G18,'🚛 FROTA'!B:B,'🚛 FROTA'!E:E,"")) -> 14.190 Constellation | K18: =IF(G18="","",_xlfn.XLOOKUP(G18,'🚛 FROTA'!B:B,'🚛 FROTA'!K:K,"")) -> Munck | L18: TIETE VEÍCULOS | M18: 572703 | N18: 45668 | O18: 2 | P18: 3 | Q18: 334.09 | R18: Faturado | S18: Compra | T18: Pago | U18: Preventiva | V18: Revisão | W18: FORNEC. KIT FILTROS + ÓLEO | X18: FORNECIMENTO: KIT FILTROS + BALDE ÓLEO 10W20 20L ALMAX | Y18: 01 KIT + 01 BALDE 20L | Z18: 105005 | AH18: =IF(OR(R18="A VISTA", R18="C. CRÉDITO", R18="ADIANTAMENTO"), N18, IF(R18="Faturado", _xlfn.MINIFS(N:N, C:C, C18)-30, "")) -> 45638 | AI18: GREGORY | AK18: =IF(Z18="",0,Z18+10000) -> 115005
A19: 18 | C19: OS-2025-0007 | D19: {=SUM(--(_xlfn.UNIQUE(_xlfn._xlws.FILTER($M$2:$M$1011 & "", ($C$2:$C$1011 = C19) * ($M$2:$M$1011 <> ""))) <> ""))} -> 1 | E19: =SUMIF(C:C, C19, Q:Q) -> 668.29 | F19: 1 | G19: DYG5G03 | H19: =_xlfn.XLOOKUP(G19,'🚛 FROTA'!B:B,'🚛 FROTA'!A:A,"") -> 24 | J19: =IF(G19="","",_xlfn.XLOOKUP(G19,'🚛 FROTA'!B:B,'🚛 FROTA'!E:E,"")) -> 14.190 Constellation | K19: =IF(G19="","",_xlfn.XLOOKUP(G19,'🚛 FROTA'!B:B,'🚛 FROTA'!K:K,"")) -> Munck | L19: TIETE VEÍCULOS | M19: 572703 | N19: 45698 | O19: 3 | P19: 3 | Q19: 334.2 | R19: Faturado | S19: Compra | T19: Pago | U19: Preventiva | V19: Revisão | W19: FORNEC. KIT FILTROS + ÓLEO | X19: FORNECIMENTO: KIT FILTROS + BALDE ÓLEO 10W20 20L ALMAX | Y19: 01 KIT + 01 BALDE 20L | Z19: 105005 | AH19: =IF(OR(R19="A VISTA", R19="C. CRÉDITO", R19="ADIANTAMENTO"), N19, IF(R19="Faturado", _xlfn.MINIFS(N:N, C:C, C19)-30, "")) -> 45638 | AI19: GREGORY | AK19: =IF(Z19="",0,Z19+10000) -> 115005
A20: 19 | C20: OS-2025-0008 | D20: {=SUM(--(_xlfn.UNIQUE(_xlfn._xlws.FILTER($M$2:$M$1011 & "", ($C$2:$C$1011 = C20) * ($M$2:$M$1011 <> ""))) <> ""))} -> 1 | E20: =SUMIF(C:C, C20, Q:Q) -> 1065.32 | F20: 1 | G20: EMN8B51 | H20: =_xlfn.XLOOKUP(G20,'🚛 FROTA'!B:B,'🚛 FROTA'!A:A,"") -> 45 | J20: =IF(G20="","",_xlfn.XLOOKUP(G20,'🚛 FROTA'!B:B,'🚛 FROTA'!E:E,"")) -> Express Delivery | K20: =IF(G20="","",_xlfn.XLOOKUP(G20,'🚛 FROTA'!B:B,'🚛 FROTA'!K:K,"")) -> Carroceria | L20: BONI PNEUS | M20: 46236 | N20: 45668 | O20: 2 | P20: 3 | Q20: 532.66 | R20: Faturado | S20: Compra | T20: Pago | U20: Corretiva | V20: Pneu | W20: FORNEC. PNEUS | X20: FORNECIMENTO: 02 PNEUS 225/75R16C APOLLO DIANTEIROS | Y20: 02 PNEUS | AA20: DIANTEIRO | AB20: 2 | AC20: 225/75R16C | AD20: APOLLO | AE20: ALTRUST | AF20: NOVO | AG20: Loja | AH20: =IF(OR(R20="A VISTA", R20="C. CRÉDITO", R20="ADIANTAMENTO"), N20, IF(R20="Faturado", _xlfn.MINIFS(N:N, C:C, C20)-30, "")) -> 45638 | AI20: RAFAEL
A21: 20 | C21: OS-2025-0008 | D21: {=SUM(--(_xlfn.UNIQUE(_xlfn._xlws.FILTER($M$2:$M$1011 & "", ($C$2:$C$1011 = C21) * ($M$2:$M$1011 <> ""))) <> ""))} -> 1 | E21: =SUMIF(C:C, C21, Q:Q) -> 1065.32 | F21: 1 | G21: EMN8B51 | H21: =_xlfn.XLOOKUP(G21,'🚛 FROTA'!B:B,'🚛 FROTA'!A:A,"") -> 45 | J21: =IF(G21="","",_xlfn.XLOOKUP(G21,'🚛 FROTA'!B:B,'🚛 FROTA'!E:E,"")) -> Express Delivery | K21: =IF(G21="","",_xlfn.XLOOKUP(G21,'🚛 FROTA'!B:B,'🚛 FROTA'!K:K,"")) -> Carroceria | L21: BONI PNEUS | M21: 46236 | N21: 45698 | O21: 3 | P21: 3 | Q21: 532.66 | R21: Faturado | S21: Compra | T21: Pago | U21: Corretiva | V21: Pneu | W21: FORNEC. PNEUS | X21: FORNECIMENTO: 02 PNEUS 225/75R16C APOLLO DIANTEIROS | Y21: 02 PNEUS | AA21: DIANTEIRO | AB21: 2 | AC21: 225/75R16C | AD21: APOLLO | AE21: ALTRUST | AF21: NOVO | AG21: Loja | AH21: =IF(OR(R21="A VISTA", R21="C. CRÉDITO", R21="ADIANTAMENTO"), N21, IF(R21="Faturado", _xlfn.MINIFS(N:N, C:C, C21)-30, "")) -> 45638 | AI21: RAFAEL
A22: 21 | C22: OS-2025-0009 | D22: {=SUM(--(_xlfn.UNIQUE(_xlfn._xlws.FILTER($M$2:$M$1011 & "", ($C$2:$C$1011 = C22) * ($M$2:$M$1011 <> ""))) <> ""))} -> 1 | E22: =SUMIF(C:C, C22, Q:Q) -> 1326.66 | F22: 1 | G22: MAX4116 | H22: =_xlfn.XLOOKUP(G22,'🚛 FROTA'!B:B,'🚛 FROTA'!A:A,"") -> 20 | J22: =IF(G22="","",_xlfn.XLOOKUP(G22,'🚛 FROTA'!B:B,'🚛 FROTA'!E:E,"")) -> 3CX | L22: CAIADO PNEUS | M22: 66471 | N22: 45670 | O22: 3 | P22: 3 | Q22: 1326.66 | R22: Faturado | S22: Compra | T22: Pago | U22: Corretiva | V22: Pneu | W22: FORNEC. PNEUS | X22: FORNECIMENTO: 02 PNEUS 12.5/80-18 FORERUNNER DIANTEIROS | Y22: 02 PNEUS | AA22: DIANTEIRO | AB22: 2 | AC22: 12.5/80-18 | AD22: FORERUNNER | AE22: QH603 | AF22: NOVO | AG22: Loja | AH22: =IF(OR(R22="A VISTA", R22="C. CRÉDITO", R22="ADIANTAMENTO"), N22, IF(R22="Faturado", _xlfn.MINIFS(N:N, C:C, C22)-30, "")) -> 45640 | AI22: THIAGO
A23: 22 | C23: OS-2024-0002 | D23: {=SUM(--(_xlfn.UNIQUE(_xlfn._xlws.FILTER($M$2:$M$1011 & "", ($C$2:$C$1011 = C23) * ($M$2:$M$1011 <> ""))) <> ""))} -> 1 | E23: =SUMIF(C:C, C23, Q:Q) -> 3424.84 | F23: 1 | G23: EXW7D65 | H23: =_xlfn.XLOOKUP(G23,'🚛 FROTA'!B:B,'🚛 FROTA'!A:A,"") -> 34 | J23: =IF(G23="","",_xlfn.XLOOKUP(G23,'🚛 FROTA'!B:B,'🚛 FROTA'!E:E,"")) -> 9.170 Delivery | K23: =IF(G23="","",_xlfn.XLOOKUP(G23,'🚛 FROTA'!B:B,'🚛 FROTA'!K:K,"")) -> Basculante | L23: FLORENZA TRUCK | M23: 3078/2335 | N23: 45690 | O23: 3 | P23: 4 | Q23: 856.21 | R23: Faturado | S23: Serviço | T23: Pago | U23: Corretiva | V23: Freio | W23: SUBST. LONAS E TAMBOR | X23: SUBST. LONAS (DIANT.+TRAS.), TAMBOR TRASEIRO E RETÍFICA DE CAMPANAS DIANTEIRAS | Z23: 58017 | AH23: =IF(OR(R23="A VISTA", R23="C. CRÉDITO", R23="ADIANTAMENTO"), N23, IF(R23="Faturado", _xlfn.MINIFS(N:N, C:C, C23)-30, "")) -> 45600 | AI23: AROUDO
A24: 23 | C24: OS-2025-0010 | D24: {=SUM(--(_xlfn.UNIQUE(_xlfn._xlws.FILTER($M$2:$M$1011 & "", ($C$2:$C$1011 = C24) * ($M$2:$M$1011 <> ""))) <> ""))} -> 3 | E24: =SUMIF(C:C, C24, Q:Q) -> 5943.73 | F24: 1 | G24: EVF8I83 | H24: =_xlfn.XLOOKUP(G24,'🚛 FROTA'!B:B,'🚛 FROTA'!A:A,"") -> 6 | J24: =IF(G24="","",_xlfn.XLOOKUP(G24,'🚛 FROTA'!B:B,'🚛 FROTA'!E:E,"")) -> 13.180 Constellation | K24: =IF(G24="","",_xlfn.XLOOKUP(G24,'🚛 FROTA'!B:B,'🚛 FROTA'!K:K,"")) -> Munck | L24: RS DIESEL | M24: 51 | N24: 45672 | O24: 1 | P24: 1 | Q24: 565 | R24: Faturado | S24: Compra | T24: Pago | U24: Corretiva | V24: Motor | W24: FORNEC. SENSOR E ADITIVO | X24: FORNECIMENTO: SENSOR DE PRESSÃO DE AR + ADITIVO + PARAFUSOS DO COLETOR | AH24: =IF(OR(R24="A VISTA", R24="C. CRÉDITO", R24="ADIANTAMENTO"), N24, IF(R24="Faturado", _xlfn.MINIFS(N:N, C:C, C24)-30, "")) -> 45642 | AI24: SANDOVAL
A25: 24 | C25: OS-2025-0010 | D25: {=SUM(--(_xlfn.UNIQUE(_xlfn._xlws.FILTER($M$2:$M$1011 & "", ($C$2:$C$1011 = C25) * ($M$2:$M$1011 <> ""))) <> ""))} -> 3 | E25: =SUMIF(C:C, C25, Q:Q) -> 5943.73 | F25: 1 | G25: EVF8I83 | H25: =_xlfn.XLOOKUP(G25,'🚛 FROTA'!B:B,'🚛 FROTA'!A:A,"") -> 6 | J25: =IF(G25="","",_xlfn.XLOOKUP(G25,'🚛 FROTA'!B:B,'🚛 FROTA'!E:E,"")) -> 13.180 Constellation | K25: =IF(G25="","",_xlfn.XLOOKUP(G25,'🚛 FROTA'!B:B,'🚛 FROTA'!K:K,"")) -> Munck | L25: PJ DIESEL | M25: 2073 | N25: 45673 | O25: 1 | P25: 1 | Q25: 1800 | R25: Faturado | S25: Serviço | T25: Pago | U25: Corretiva | V25: Motor | W25: RETÍFICA CABEÇOTE E BLOCO | X25: Serviço: RETÍFICA DE CABEÇOTE E BLOCO DO MOTOR | AH25: =IF(OR(R25="A VISTA", R25="C. CRÉDITO", R25="ADIANTAMENTO"), N25, IF(R25="Faturado", _xlfn.MINIFS(N:N, C:C, C25)-30, "")) -> 45642
A26: 25 | C26: OS-2025-0010 | D26: {=SUM(--(_xlfn.UNIQUE(_xlfn._xlws.FILTER($M$2:$M$1011 & "", ($C$2:$C$1011 = C26) * ($M$2:$M$1011 <> ""))) <> ""))} -> 3 | E26: =SUMIF(C:C, C26, Q:Q) -> 5943.73 | F26: 1 | G26: EVF8I83 | H26: =_xlfn.XLOOKUP(G26,'🚛 FROTA'!B:B,'🚛 FROTA'!A:A,"") -> 6 | J26: =IF(G26="","",_xlfn.XLOOKUP(G26,'🚛 FROTA'!B:B,'🚛 FROTA'!E:E,"")) -> 13.180 Constellation | K26: =IF(G26="","",_xlfn.XLOOKUP(G26,'🚛 FROTA'!B:B,'🚛 FROTA'!K:K,"")) -> Munck | L26: MSAM PEÇAS | M26: 651012 | N26: 45684 | O26: 2 | P26: 3 | Q26: 1789.37 | R26: Faturado | S26: Compra | T26: Pago | U26: Corretiva | V26: Motor | W26: FORNEC. KIT REPARO MOTOR | X26: FORNECIMENTO: KIT DE PEÇAS PARA REPARO DE MOTOR | AH26: =IF(OR(R26="A VISTA", R26="C. CRÉDITO", R26="ADIANTAMENTO"), N26, IF(R26="Faturado", _xlfn.MINIFS(N:N, C:C, C26)-30, "")) -> 45642 | AI26: KAROLINE
A27: 26 | C27: OS-2025-0010 | D27: {=SUM(--(_xlfn.UNIQUE(_xlfn._xlws.FILTER($M$2:$M$1011 & "", ($C$2:$C$1011 = C27) * ($M$2:$M$1011 <> ""))) <> ""))} -> 3 | E27: =SUMIF(C:C, C27, Q:Q) -> 5943.73 | F27: 1 | G27: EVF8I83 | H27: =_xlfn.XLOOKUP(G27,'🚛 FROTA'!B:B,'🚛 FROTA'!A:A,"") -> 6 | J27: =IF(G27="","",_xlfn.XLOOKUP(G27,'🚛 FROTA'!B:B,'🚛 FROTA'!E:E,"")) -> 13.180 Constellation | K27: =IF(G27="","",_xlfn.XLOOKUP(G27,'🚛 FROTA'!B:B,'🚛 FROTA'!K:K,"")) -> Munck | L27: MSAM PEÇAS | M27: 651012 | N27: 45713 | O27: 3 | P27: 3 | Q27: 1789.36 | R27: Faturado | S27: Compra | T27: Pago | U27: Corretiva | V27: Motor | W27: FORNEC. KIT REPARO MOTOR | X27: FORNECIMENTO: KIT DE PEÇAS PARA REPARO DE MOTOR | AH27: =IF(OR(R27="A VISTA", R27="C. CRÉDITO", R27="ADIANTAMENTO"), N27, IF(R27="Faturado", _xlfn.MINIFS(N:N, C:C, C27)-30, "")) -> 45642 | AI27: KAROLINE
A28: 27 | C28: OS-2025-0011 | D28: {=SUM(--(_xlfn.UNIQUE(_xlfn._xlws.FILTER($M$2:$M$1011 & "", ($C$2:$C$1011 = C28) * ($M$2:$M$1011 <> ""))) <> ""))} -> 1 | E28: =SUMIF(C:C, C28, Q:Q) -> 1100 | F28: 1 | G28: EJX0I24 | H28: =_xlfn.XLOOKUP(G28,'🚛 FROTA'!B:B,'🚛 FROTA'!A:A,"") -> 39 | J28: =IF(G28="","",_xlfn.XLOOKUP(G28,'🚛 FROTA'!B:B,'🚛 FROTA'!E:E,"")) -> Express Delivery | K28: =IF(G28="","",_xlfn.XLOOKUP(G28,'🚛 FROTA'!B:B,'🚛 FROTA'!K:K,"")) -> Carroceria Cabinado | L28: RS DIESEL | M28: 911/55 | N28: 45674 | O28: 1 | P28: 1 | Q28: 1100 | R28: Faturado | S28: Serviço | T28: Pago | U28: Corretiva | V28: Direção | W28: SUBST. TERMINAIS DIREÇÃO | X28: SUBSTITUIÇÃO: TERMINAIS DE DIREÇÃO + MÁQUINA DE VIDRO | AH28: =IF(OR(R28="A VISTA", R28="C. CRÉDITO", R28="ADIANTAMENTO"), N28, IF(R28="Faturado", _xlfn.MINIFS(N:N, C:C, C28)-30, "")) -> 45644 | AI28: SANDOVAL
A29: 28 | C29: OS-2025-0012 | D29: {=SUM(--(_xlfn.UNIQUE(_xlfn._xlws.FILTER($M$2:$M$1011 & "", ($C$2:$C$1011 = C29) * ($M$2:$M$1011 <> ""))) <> ""))} -> 1 | E29: =SUMIF(C:C, C29, Q:Q) -> 4620 | F29: 1 | G29: EVF8I83 | H29: =_xlfn.XLOOKUP(G29,'🚛 FROTA'!B:B,'🚛 FROTA'!A:A,"") -> 6 | J29: =IF(G29="","",_xlfn.XLOOKUP(G29,'🚛 FROTA'!B:B,'🚛 FROTA'!E:E,"")) -> 13.180 Constellation | K29: =IF(G29="","",_xlfn.XLOOKUP(G29,'🚛 FROTA'!B:B,'🚛 FROTA'!K:K,"")) -> Munck | L29: MONKEY MUNCK | M29: 9 | N29: 45678 | O29: 1 | P29: 3 | Q29: 1540 | R29: Faturado | S29: Serviço | T29: Pago | U29: Corretiva | V29: Hidráulico | W29: SUBST. BOMBA HID. E TDF | X29: SUBSTITUIÇÃO: BOMBA HIDRÁULICA + TOMADA DE FORÇA + ÓLEO DE CÂMBIO | AH29: =IF(OR(R29="A VISTA", R29="C. CRÉDITO", R29="ADIANTAMENTO"), N29, IF(R29="Faturado", _xlfn.MINIFS(N:N, C:C, C29)-30, "")) -> 45648
A30: 29 | C30: OS-2025-0012 | D30: {=SUM(--(_xlfn.UNIQUE(_xlfn._xlws.FILTER($M$2:$M$1011 & "", ($C$2:$C$1011 = C30) * ($M$2:$M$1011 <> ""))) <> ""))} -> 1 | E30: =SUMIF(C:C, C30, Q:Q) -> 4620 | F30: 1 | G30: EVF8I83 | H30: =_xlfn.XLOOKUP(G30,'🚛 FROTA'!B:B,'🚛 FROTA'!A:A,"") -> 6 | J30: =IF(G30="","",_xlfn.XLOOKUP(G30,'🚛 FROTA'!B:B,'🚛 FROTA'!E:E,"")) -> 13.180 Constellation | K30: =IF(G30="","",_xlfn.XLOOKUP(G30,'🚛 FROTA'!B:B,'🚛 FROTA'!K:K,"")) -> Munck | L30: MONKEY MUNCK | M30: 9 | N30: 45728 | O30: 2 | P30: 2 | Q30: 1540 | R30: Faturado | S30: Serviço | T30: Pago | U30: Corretiva | V30: Hidráulico | W30: SUBST. BOMBA HID. E TDF | X30: SUBSTITUIÇÃO: BOMBA HIDRÁULICA + TOMADA DE FORÇA + ÓLEO DE CÂMBIO | AH30: =IF(OR(R30="A VISTA", R30="C. CRÉDITO", R30="ADIANTAMENTO"), N30, IF(R30="Faturado", _xlfn.MINIFS(N:N, C:C, C30)-30, "")) -> 45648
A31: 30 | C31: OS-2025-0012 | D31: {=SUM(--(_xlfn.UNIQUE(_xlfn._xlws.FILTER($M$2:$M$1011 & "", ($C$2:$C$1011 = C31) * ($M$2:$M$1011 <> ""))) <> ""))} -> 1 | E31: =SUMIF(C:C, C31, Q:Q) -> 4620 | F31: 1 | G31: EVF8I83 | H31: =_xlfn.XLOOKUP(G31,'🚛 FROTA'!B:B,'🚛 FROTA'!A:A,"") -> 6 | J31: =IF(G31="","",_xlfn.XLOOKUP(G31,'🚛 FROTA'!B:B,'🚛 FROTA'!E:E,"")) -> 13.180 Constellation | K31: =IF(G31="","",_xlfn.XLOOKUP(G31,'🚛 FROTA'!B:B,'🚛 FROTA'!K:K,"")) -> Munck | L31: MONKEY MUNCK | M31: 9 | N31: 45758 | O31: 3 | P31: 3 | Q31: 1540 | R31: Faturado | S31: Serviço | T31: Pago | U31: Corretiva | V31: Hidráulico | W31: SUBST. BOMBA HID. E TDF | X31: SUBSTITUIÇÃO: BOMBA HIDRÁULICA + TOMADA DE FORÇA + ÓLEO DE CÂMBIO | AH31: =IF(OR(R31="A VISTA", R31="C. CRÉDITO", R31="ADIANTAMENTO"), N31, IF(R31="Faturado", _xlfn.MINIFS(N:N, C:C, C31)-30, "")) -> 45648
A32: 31 | C32: OS-2025-0013 | D32: {=SUM(--(_xlfn.UNIQUE(_xlfn._xlws.FILTER($M$2:$M$1011 & "", ($C$2:$C$1011 = C32) * ($M$2:$M$1011 <> ""))) <> ""))} -> 1 | E32: =SUMIF(C:C, C32, Q:Q) -> 10400 | F32: 1 | G32: KJX8J96 | H32: =_xlfn.XLOOKUP(G32,'🚛 FROTA'!B:B,'🚛 FROTA'!A:A,"") -> 4 | J32: =IF(G32="","",_xlfn.XLOOKUP(G32,'🚛 FROTA'!B:B,'🚛 FROTA'!E:E,"")) -> 8.150E Delivery | K32: =IF(G32="","",_xlfn.XLOOKUP(G32,'🚛 FROTA'!B:B,'🚛 FROTA'!K:K,"")) -> Baú | L32: RS DIESEL | M32: 863 | N32: 45682 | O32: 2 | P32: 5 | Q32: 2600 | R32: Faturado | S32: Serviço | T32: Pago | U32: Corretiva | V32: Injeção | W32: RECONDICIONAMENTO INJEÇÃO ELETRÔNICA | X32: Serviço: RECONDICIONAMENTO DO SISTEMA DE INJEÇÃO ELETRÔNICA | AH32: =IF(OR(R32="A VISTA", R32="C. CRÉDITO", R32="ADIANTAMENTO"), N32, IF(R32="Faturado", _xlfn.MINIFS(N:N, C:C, C32)-30, "")) -> 45652 | AI32: SANDOVAL
A33: 32 | C33: OS-2025-0013 | D33: {=SUM(--(_xlfn.UNIQUE(_xlfn._xlws.FILTER($M$2:$M$1011 & "", ($C$2:$C$1011 = C33) * ($M$2:$M$1011 <> ""))) <> ""))} -> 1 | E33: =SUMIF(C:C, C33, Q:Q) -> 10400 | F33: 1 | G33: KJX8J96 | H33: =_xlfn.XLOOKUP(G33,'🚛 FROTA'!B:B,'🚛 FROTA'!A:A,"") -> 4 | J33: =IF(G33="","",_xlfn.XLOOKUP(G33,'🚛 FROTA'!B:B,'🚛 FROTA'!E:E,"")) -> 8.150E Delivery | K33: =IF(G33="","",_xlfn.XLOOKUP(G33,'🚛 FROTA'!B:B,'🚛 FROTA'!K:K,"")) -> Baú | L33: RS DIESEL | M33: 863 | N33: 45713 | O33: 2 | P33: 5 | Q33: 2600 | R33: Faturado | S33: Serviço | T33: Pago | U33: Corretiva | V33: Injeção | W33: RECONDICIONAMENTO INJEÇÃO ELETRÔNICA | X33: Serviço: RECONDICIONAMENTO DO SISTEMA DE INJEÇÃO ELETRÔNICA | AH33: =IF(OR(R33="A VISTA", R33="C. CRÉDITO", R33="ADIANTAMENTO"), N33, IF(R33="Faturado", _xlfn.MINIFS(N:N, C:C, C33)-30, "")) -> 45652 | AI33: SANDOVAL
A34: 33 | C34: OS-2025-0013 | D34: {=SUM(--(_xlfn.UNIQUE(_xlfn._xlws.FILTER($M$2:$M$1011 & "", ($C$2:$C$1011 = C34) * ($M$2:$M$1011 <> ""))) <> ""))} -> 1 | E34: =SUMIF(C:C, C34, Q:Q) -> 10400 | F34: 1 | G34: KJX8J96 | H34: =_xlfn.XLOOKUP(G34,'🚛 FROTA'!B:B,'🚛 FROTA'!A:A,"") -> 4 | J34: =IF(G34="","",_xlfn.XLOOKUP(G34,'🚛 FROTA'!B:B,'🚛 FROTA'!E:E,"")) -> 8.150E Delivery | K34: =IF(G34="","",_xlfn.XLOOKUP(G34,'🚛 FROTA'!B:B,'🚛 FROTA'!K:K,"")) -> Baú | L34: RS DIESEL | M34: 863 | N34: 45741 | O34: 4 | P34: 5 | Q34: 2600 | R34: Faturado | S34: Serviço | T34: Pago | U34: Corretiva | V34: Injeção | W34: RECONDICIONAMENTO INJEÇÃO ELETRÔNICA | X34: Serviço: RECONDICIONAMENTO DO SISTEMA DE INJEÇÃO ELETRÔNICA | AH34: =IF(OR(R34="A VISTA", R34="C. CRÉDITO", R34="ADIANTAMENTO"), N34, IF(R34="Faturado", _xlfn.MINIFS(N:N, C:C, C34)-30, "")) -> 45652 | AI34: SANDOVAL
A35: 34 | C35: OS-2025-0013 | D35: {=SUM(--(_xlfn.UNIQUE(_xlfn._xlws.FILTER($M$2:$M$1011 & "", ($C$2:$C$1011 = C35) * ($M$2:$M$1011 <> ""))) <> ""))} -> 1 | E35: =SUMIF(C:C, C35, Q:Q) -> 10400 | F35: 1 | G35: KJX8J96 | H35: =_xlfn.XLOOKUP(G35,'🚛 FROTA'!B:B,'🚛 FROTA'!A:A,"") -> 4 | J35: =IF(G35="","",_xlfn.XLOOKUP(G35,'🚛 FROTA'!B:B,'🚛 FROTA'!E:E,"")) -> 8.150E Delivery | K35: =IF(G35="","",_xlfn.XLOOKUP(G35,'🚛 FROTA'!B:B,'🚛 FROTA'!K:K,"")) -> Baú | L35: RS DIESEL | M35: 863 | N35: 45792 | O35: 5 | P35: 5 | Q35: 2600 | R35: Faturado | S35: Serviço | T35: Pago | U35: Corretiva | V35: Injeção | W35: RECONDICIONAMENTO INJEÇÃO ELETRÔNICA | X35: Serviço: RECONDICIONAMENTO DO SISTEMA DE INJEÇÃO ELETRÔNICA | AH35: =IF(OR(R35="A VISTA", R35="C. CRÉDITO", R35="ADIANTAMENTO"), N35, IF(R35="Faturado", _xlfn.MINIFS(N:N, C:C, C35)-30, "")) -> 45652 | AI35: SANDOVAL
A36: 35 | C36: OS-2025-0014 | D36: {=SUM(--(_xlfn.UNIQUE(_xlfn._xlws.FILTER($M$2:$M$1011 & "", ($C$2:$C$1011 = C36) * ($M$2:$M$1011 <> ""))) <> ""))} -> 1 | E36: =SUMIF(C:C, C36, Q:Q) -> 450 | F36: 1 | G36: MAX4116 | H36: =_xlfn.XLOOKUP(G36,'🚛 FROTA'!B:B,'🚛 FROTA'!A:A,"") -> 20 | J36: =IF(G36="","",_xlfn.XLOOKUP(G36,'🚛 FROTA'!B:B,'🚛 FROTA'!E:E,"")) -> 3CX | L36: MM LUIBRIFICANTES | M36: 20060 | N36: 45687 | O36: 1 | P36: 1 | Q36: 450 | R36: A Vista | S36: Compra | T36: Pago | U36: Preventiva | V36: Diversos | W36: FORNEC. GRAXA | X36: FORNECIMENTO: GRAXA AZUL 18KG | Y36: 18 KG | AH36: =IF(OR(R36="A Vista", R36="Crédito", R36="Adiantamento"), N36, IF(R36="Faturado", _xlfn.MINIFS(N:N, C:C, C36)-30, "")) -> 45687
A37: 36 | C37: OS-2025-0015 | D37: {=SUM(--(_xlfn.UNIQUE(_xlfn._xlws.FILTER($M$2:$M$1011 & "", ($C$2:$C$1011 = C37) * ($M$2:$M$1011 <> ""))) <> ""))} -> 2 | E37: =SUMIF(C:C, C37, Q:Q) -> 1588.01 | F37: 1 | G37: BSX5H07 | H37: =_xlfn.XLOOKUP(G37,'🚛 FROTA'!B:B,'🚛 FROTA'!A:A,"") -> 42 | J37: =IF(G37="","",_xlfn.XLOOKUP(G37,'🚛 FROTA'!B:B,'🚛 FROTA'!E:E,"")) -> Express Delivery | K37: =IF(G37="","",_xlfn.XLOOKUP(G37,'🚛 FROTA'!B:B,'🚛 FROTA'!K:K,"")) -> Carroceria | L37: CAIADO PNEUS | M37: 15556 | N37: 45695 | O37: 1 | P37: 1 | Q37: 50 | R37: Faturado | S37: Serviço | T37: Pago | U37: Corretiva | V37: Pneu | W37: INSTALAÇÃO PNEUS | X37: Serviço: INSTALAÇÃO DE PNEUS (REF. NF 67279) | Z37: 52531 | AA37: TRASEIRO | AB37: 2 | AC37: 225/75R16C | AD37: XBRI | AE37: FORZA | AG37: Loja | AH37: =IF(OR(R37="A VISTA", R37="C. CRÉDITO", R37="ADIANTAMENTO"), N37, IF(R37="Faturado", _xlfn.MINIFS(N:N, C:C, C37)-30, "")) -> 45665 | AI37: THIAGO
A38: 37 | C38: OS-2024-0002 | D38: {=SUM(--(_xlfn.UNIQUE(_xlfn._xlws.FILTER($M$2:$M$1011 & "", ($C$2:$C$1011 = C38) * ($M$2:$M$1011 <> ""))) <> ""))} -> 1 | E38: =SUMIF(C:C, C38, Q:Q) -> 3424.84 | F38: 1 | G38: EXW7D65 | H38: =_xlfn.XLOOKUP(G38,'🚛 FROTA'!B:B,'🚛 FROTA'!A:A,"") -> 34 | J38: =IF(G38="","",_xlfn.XLOOKUP(G38,'🚛 FROTA'!B:B,'🚛 FROTA'!E:E,"")) -> 9.170 Delivery | K38: =IF(G38="","",_xlfn.XLOOKUP(G38,'🚛 FROTA'!B:B,'🚛 FROTA'!K:K,"")) -> Basculante | L38: FLORENZA TRUCK | M38: 3078/2335 | N38: 45720 | O38: 4 | P38: 4 | Q38: 856.21 | R38: Faturado | S38: Serviço | T38: Pago | U38: Corretiva | V38: Freio | W38: SUBST. LONAS E TAMBOR | X38: SUBST. LONAS (DIANT.+TRAS.), TAMBOR TRASEIRO E RETÍFICA DE CAMPANAS DIANTEIRAS | Z38: 58017 | AH38: =IF(OR(R38="A VISTA", R38="C. CRÉDITO", R38="ADIANTAMENTO"), N38, IF(R38="Faturado", _xlfn.MINIFS(N:N, C:C, C38)-30, "")) -> 45600 | AI38: AROUDO
A39: 38 | C39: OS-2025-0015 | D39: {=SUM(--(_xlfn.UNIQUE(_xlfn._xlws.FILTER($M$2:$M$1011 & "", ($C$2:$C$1011 = C39) * ($M$2:$M$1011 <> ""))) <> ""))} -> 2 | E39: =SUMIF(C:C, C39, Q:Q) -> 1588.01 | F39: 1 | G39: BSX5H07 | H39: =_xlfn.XLOOKUP(G39,'🚛 FROTA'!B:B,'🚛 FROTA'!A:A,"") -> 42 | J39: =IF(G39="","",_xlfn.XLOOKUP(G39,'🚛 FROTA'!B:B,'🚛 FROTA'!E:E,"")) -> Express Delivery | K39: =IF(G39="","",_xlfn.XLOOKUP(G39,'🚛 FROTA'!B:B,'🚛 FROTA'!K:K,"")) -> Carroceria | L39: CAIADO PNEUS | M39: 67279 | N39: 45695 | O39: 1 | P39: 3 | Q39: 512.67 | R39: Faturado | S39: Compra | T39: Pago | U39: Corretiva | V39: Pneu | W39: FORNEC. PNEUS | X39: FORNECIMENTO: 02 PNEUS 225/75R16C XBRI FORZA TRASEIROS | Y39: 02 PNEUS | Z39: 52531 | AA39: TRASEIRO | AB39: 2 | AC39: 225/75R16C | AD39: XBRI | AE39: FORZA | AF39: NOVO | AG39: Loja | AH39: =IF(OR(R39="A VISTA", R39="C. CRÉDITO", R39="ADIANTAMENTO"), N39, IF(R39="Faturado", _xlfn.MINIFS(N:N, C:C, C39)-30, "")) -> 45665 | AI39: THIAGO
A40: 39 | C40: OS-2025-0015 | D40: {=SUM(--(_xlfn.UNIQUE(_xlfn._xlws.FILTER($M$2:$M$1011 & "", ($C$2:$C$1011 = C40) * ($M$2:$M$1011 <> ""))) <> ""))} -> 2 | E40: =SUMIF(C:C, C40, Q:Q) -> 1588.01 | F40: 1 | G40: BSX5H07 | H40: =_xlfn.XLOOKUP(G40,'🚛 FROTA'!B:B,'🚛 FROTA'!A:A,"") -> 42 | J40: =IF(G40="","",_xlfn.XLOOKUP(G40,'🚛 FROTA'!B:B,'🚛 FROTA'!E:E,"")) -> Express Delivery | K40: =IF(G40="","",_xlfn.XLOOKUP(G40,'🚛 FROTA'!B:B,'🚛 FROTA'!K:K,"")) -> Carroceria | L40: CAIADO PNEUS | M40: 67279 | N40: 45726 | O40: 2 | P40: 3 | Q40: 512.67 | R40: Faturado | S40: Compra | T40: Pago | U40: Corretiva | V40: Pneu | W40: FORNEC. PNEUS | X40: FORNECIMENTO: 02 PNEUS 225/75R16C XBRI FORZA TRASEIROS | Y40: 02 PNEUS | Z40: 52531 | AA40: TRASEIRO | AB40: 2 | AC40: 225/75R16C | AD40: XBRI | AE40: FORZA | AF40: NOVO | AG40: Loja | AH40: =IF(OR(R40="A VISTA", R40="C. CRÉDITO", R40="ADIANTAMENTO"), N40, IF(R40="Faturado", _xlfn.MINIFS(N:N, C:C, C40)-30, "")) -> 45665 | AI40: THIAGO
A41: 40 | C41: OS-2025-0015 | D41: {=SUM(--(_xlfn.UNIQUE(_xlfn._xlws.FILTER($M$2:$M$1011 & "", ($C$2:$C$1011 = C41) * ($M$2:$M$1011 <> ""))) <> ""))} -> 2 | E41: =SUMIF(C:C, C41, Q:Q) -> 1588.01 | F41: 1 | G41: BSX5H07 | H41: =_xlfn.XLOOKUP(G41,'🚛 FROTA'!B:B,'🚛 FROTA'!A:A,"") -> 42 | J41: =IF(G41="","",_xlfn.XLOOKUP(G41,'🚛 FROTA'!B:B,'🚛 FROTA'!E:E,"")) -> Express Delivery | K41: =IF(G41="","",_xlfn.XLOOKUP(G41,'🚛 FROTA'!B:B,'🚛 FROTA'!K:K,"")) -> Carroceria | L41: CAIADO PNEUS | M41: 67279 | N41: 45755 | O41: 3 | P41: 3 | Q41: 512.67 | R41: Faturado | S41: Compra | T41: Pago | U41: Corretiva | V41: Pneu | W41: FORNEC. PNEUS | X41: FORNECIMENTO: 02 PNEUS 225/75R16C XBRI FORZA TRASEIROS | Y41: 02 PNEUS | Z41: 52531 | AA41: TRASEIRO | AB41: 2 | AC41: 225/75R16C | AD41: XBRI | AE41: FORZA | AF41: NOVO | AG41: Loja | AH41: =IF(OR(R41="A VISTA", R41="C. CRÉDITO", R41="ADIANTAMENTO"), N41, IF(R41="Faturado", _xlfn.MINIFS(N:N, C:C, C41)-30, "")) -> 45665 | AI41: THIAGO
A42: 41 | C42: OS-2025-0016 | D42: {=SUM(--(_xlfn.UNIQUE(_xlfn._xlws.FILTER($M$2:$M$1011 & "", ($C$2:$C$1011 = C42) * ($M$2:$M$1011 <> ""))) <> ""))} -> 2 | E42: =SUMIF(C:C, C42, Q:Q) -> 3178.68 | F42: 1 | G42: DLG0D92 | H42: =_xlfn.XLOOKUP(G42,'🚛 FROTA'!B:B,'🚛 FROTA'!A:A,"") -> 41 | J42: =IF(G42="","",_xlfn.XLOOKUP(G42,'🚛 FROTA'!B:B,'🚛 FROTA'!E:E,"")) -> Express Delivery | K42: =IF(G42="","",_xlfn.XLOOKUP(G42,'🚛 FROTA'!B:B,'🚛 FROTA'!K:K,"")) -> Carroceria Cabinado | L42: TIETE VEÍCULOS | M42: 2770 | N42: 45697 | O42: 1 | P42: 3 | Q42: 726.16 | R42: Faturado | S42: Compra | T42: Pago | U42: Corretiva | V42: Freio | W42: FORNEC. PINÇA, DISCO E PASTILHAS | X42: FORNECIMENTO: 01 PINÇA DIANTEIRA + 01 DISCO + KIT PASTILHAS DIANTEIRAS | Y42: 01 PINÇA + 01 DISCO + 01 KIT | AH42: =IF(OR(R42="A VISTA", R42="C. CRÉDITO", R42="ADIANTAMENTO"), N42, IF(R42="Faturado", _xlfn.MINIFS(N:N, C:C, C42)-30, "")) -> 45667 | AI42: GREGORY
A43: 42 | C43: OS-2025-0018 | D43: {=SUM(--(_xlfn.UNIQUE(_xlfn._xlws.FILTER($M$2:$M$1011 & "", ($C$2:$C$1011 = C43) * ($M$2:$M$1011 <> ""))) <> ""))} -> 1 | E43: =SUMIF(C:C, C43, Q:Q) -> 570 | F43: 1 | G43: DLG0D92 | H43: =_xlfn.XLOOKUP(G43,'🚛 FROTA'!B:B,'🚛 FROTA'!A:A,"") -> 41 | J43: =IF(G43="","",_xlfn.XLOOKUP(G43,'🚛 FROTA'!B:B,'🚛 FROTA'!E:E,"")) -> Express Delivery | K43: =IF(G43="","",_xlfn.XLOOKUP(G43,'🚛 FROTA'!B:B,'🚛 FROTA'!K:K,"")) -> Carroceria Cabinado | L43: BATERIAS MOGI | M43: 3400 | N43: 45700 | O43: 1 | P43: 1 | Q43: 570 | R43: A Vista | S43: Compra | T43: Pago | U43: Corretiva | V43: Elétrico | W43: FORNEC. BATERIA | X43: FORNECIMENTO: 01 BATERIA 100A CRAL | Y43: 01 BATERIA | Z43: 29323 | AH43: =IF(OR(R43="A Vista", R43="Crédito", R43="Adiantamento"), N43, IF(R43="Faturado", _xlfn.MINIFS(N:N, C:C, C43)-30, "")) -> 45700
A44: 43 | C44: OS-2025-0016 | D44: {=SUM(--(_xlfn.UNIQUE(_xlfn._xlws.FILTER($M$2:$M$1011 & "", ($C$2:$C$1011 = C44) * ($M$2:$M$1011 <> ""))) <> ""))} -> 2 | E44: =SUMIF(C:C, C44, Q:Q) -> 3178.68 | F44: 1 | G44: DLG0D92 | H44: =_xlfn.XLOOKUP(G44,'🚛 FROTA'!B:B,'🚛 FROTA'!A:A,"") -> 41 | J44: =IF(G44="","",_xlfn.XLOOKUP(G44,'🚛 FROTA'!B:B,'🚛 FROTA'!E:E,"")) -> Express Delivery | K44: =IF(G44="","",_xlfn.XLOOKUP(G44,'🚛 FROTA'!B:B,'🚛 FROTA'!K:K,"")) -> Carroceria Cabinado | L44: RS DIESEL | M44: 940/64 | N44: 45700 | O44: 1 | P44: 2 | Q44: 500 | R44: Faturado | S44: Serviço | T44: Pago | U44: Corretiva | V44: Freio | W44: SUBST. PINÇA, DISCOS E PASTILHAS | X44: SUBSTITUIÇÃO DE PINÇA, DISCOS E PASTILHAS DE FREIO | AH44: =IF(OR(R44="A VISTA", R44="C. CRÉDITO", R44="ADIANTAMENTO"), N44, IF(R44="Faturado", _xlfn.MINIFS(N:N, C:C, C44)-30, "")) -> 45667 | AI44: SANDOVAL
A45: 44 | C45: OS-2025-0020 | D45: {=SUM(--(_xlfn.UNIQUE(_xlfn._xlws.FILTER($M$2:$M$1011 & "", ($C$2:$C$1011 = C45) * ($M$2:$M$1011 <> ""))) <> ""))} -> 2 | E45: =SUMIF(C:C, C45, Q:Q) -> 2177.47 | F45: 1 | G45: DLG0D92 | H45: =_xlfn.XLOOKUP(G45,'🚛 FROTA'!B:B,'🚛 FROTA'!A:A,"") -> 41 | J45: =IF(G45="","",_xlfn.XLOOKUP(G45,'🚛 FROTA'!B:B,'🚛 FROTA'!E:E,"")) -> Express Delivery | K45: =IF(G45="","",_xlfn.XLOOKUP(G45,'🚛 FROTA'!B:B,'🚛 FROTA'!K:K,"")) -> Carroceria Cabinado | L45: TIETE VEÍCULOS | M45: 5363 | N45: 45725 | O45: 1 | P45: 3 | Q45: 359.13 | R45: Faturado | S45: Compra | T45: Pago | U45: Preventiva | V45: Revisão | W45: KIT REVISAO — VW EXPRESS | X45: KIT REVISAO VW EXPRESS (OLEO + FILTROS) | AH45: =IF(OR(R45="A VISTA", R45="C. CRÉDITO", R45="ADIANTAMENTO"), N45, IF(R45="Faturado", _xlfn.MINIFS(N:N, C:C, C45)-30, "")) -> 45695 | AI45: GREGORY | AK45: =IF(Z45="",0,Z45+10000) -> 0
A46: 45 | C46: OS-2025-0016 | D46: {=SUM(--(_xlfn.UNIQUE(_xlfn._xlws.FILTER($M$2:$M$1011 & "", ($C$2:$C$1011 = C46) * ($M$2:$M$1011 <> ""))) <> ""))} -> 2 | E46: =SUMIF(C:C, C46, Q:Q) -> 3178.68 | F46: 1 | G46: DLG0D92 | H46: =_xlfn.XLOOKUP(G46,'🚛 FROTA'!B:B,'🚛 FROTA'!A:A,"") -> 41 | J46: =IF(G46="","",_xlfn.XLOOKUP(G46,'🚛 FROTA'!B:B,'🚛 FROTA'!E:E,"")) -> Express Delivery | K46: =IF(G46="","",_xlfn.XLOOKUP(G46,'🚛 FROTA'!B:B,'🚛 FROTA'!K:K,"")) -> Carroceria Cabinado | L46: TIETE VEÍCULOS | M46: 2770 | N46: 45727 | O46: 2 | P46: 3 | Q46: 726.15 | R46: Faturado | S46: Compra | T46: Pago | U46: Corretiva | V46: Freio | W46: FORNEC. PINÇA, DISCO E PASTILHAS | X46: FORNECIMENTO: 01 PINÇA DIANTEIRA + 01 DISCO + KIT PASTILHAS DIANTEIRAS | Y46: 01 PINÇA + 01 DISCO + 01 KIT | Z46: 53195 | AH46: =IF(OR(R46="A VISTA", R46="C. CRÉDITO", R46="ADIANTAMENTO"), N46, IF(R46="Faturado", _xlfn.MINIFS(N:N, C:C, C46)-30, "")) -> 45667 | AI46: GREGORY
A47: 46 | C47: OS-2025-0017 | D47: {=SUM(--(_xlfn.UNIQUE(_xlfn._xlws.FILTER($M$2:$M$1011 & "", ($C$2:$C$1011 = C47) * ($M$2:$M$1011 <> ""))) <> ""))} -> 1 | E47: =SUMIF(C:C, C47, Q:Q) -> 1521.34 | F47: 1 | G47: EJX0I24 | H47: =_xlfn.XLOOKUP(G47,'🚛 FROTA'!B:B,'🚛 FROTA'!A:A,"") -> 39 | J47: =IF(G47="","",_xlfn.XLOOKUP(G47,'🚛 FROTA'!B:B,'🚛 FROTA'!E:E,"")) -> Express Delivery | K47: =IF(G47="","",_xlfn.XLOOKUP(G47,'🚛 FROTA'!B:B,'🚛 FROTA'!K:K,"")) -> Carroceria Cabinado | L47: DIBRACAM | M47: 812277 | N47: 45698 | O47: 1 | P47: 3 | Q47: 507.12 | R47: Faturado | S47: Compra | T47: Pago | U47: Corretiva | V47: Direção | W47: FORNEC. BRAÇO AXIAL DIREÇÃO | X47: FORNECIMENTO: BRAÇO AXIAL DE DIREÇÃO L.M. (MOTORISTA) | AH47: =IF(OR(R47="A VISTA", R47="C. CRÉDITO", R47="ADIANTAMENTO"), N47, IF(R47="Faturado", _xlfn.MINIFS(N:N, C:C, C47)-30, "")) -> 45668 | AI47: HENRIQUE
A48: 47 | C48: OS-2025-0017 | D48: {=SUM(--(_xlfn.UNIQUE(_xlfn._xlws.FILTER($M$2:$M$1011 & "", ($C$2:$C$1011 = C48) * ($M$2:$M$1011 <> ""))) <> ""))} -> 1 | E48: =SUMIF(C:C, C48, Q:Q) -> 1521.34 | F48: 1 | G48: EJX0I24 | H48: =_xlfn.XLOOKUP(G48,'🚛 FROTA'!B:B,'🚛 FROTA'!A:A,"") -> 39 | J48: =IF(G48="","",_xlfn.XLOOKUP(G48,'🚛 FROTA'!B:B,'🚛 FROTA'!E:E,"")) -> Express Delivery | K48: =IF(G48="","",_xlfn.XLOOKUP(G48,'🚛 FROTA'!B:B,'🚛 FROTA'!K:K,"")) -> Carroceria Cabinado | L48: DIBRACAM | M48: 812277 | N48: 45726 | O48: 2 | P48: 3 | Q48: 507.11 | R48: Faturado | S48: Compra | T48: Pago | U48: Corretiva | V48: Direção | W48: FORNEC. BRAÇO AXIAL DIREÇÃO | X48: FORNECIMENTO: BRAÇO AXIAL DE DIREÇÃO L.M. (MOTORISTA) | Z48: 53195 | AH48: =IF(OR(R48="A VISTA", R48="C. CRÉDITO", R48="ADIANTAMENTO"), N48, IF(R48="Faturado", _xlfn.MINIFS(N:N, C:C, C48)-30, "")) -> 45668 | AI48: HENRIQUE
A49: 48 | C49: OS-2025-0017 | D49: {=SUM(--(_xlfn.UNIQUE(_xlfn._xlws.FILTER($M$2:$M$1011 & "", ($C$2:$C$1011 = C49) * ($M$2:$M$1011 <> ""))) <> ""))} -> 1 | E49: =SUMIF(C:C, C49, Q:Q) -> 1521.34 | F49: 1 | G49: EJX0I24 | H49: =_xlfn.XLOOKUP(G49,'🚛 FROTA'!B:B,'🚛 FROTA'!A:A,"") -> 39 | J49: =IF(G49="","",_xlfn.XLOOKUP(G49,'🚛 FROTA'!B:B,'🚛 FROTA'!E:E,"")) -> Express Delivery | K49: =IF(G49="","",_xlfn.XLOOKUP(G49,'🚛 FROTA'!B:B,'🚛 FROTA'!K:K,"")) -> Carroceria Cabinado | L49: DIBRACAM | M49: 812277 | N49: 45754 | O49: 3 | P49: 3 | Q49: 507.11 | R49: Faturado | S49: Compra | T49: Pago | U49: Corretiva | V49: Direção | W49: FORNEC. BRAÇO AXIAL DIREÇÃO | X49: FORNECIMENTO: BRAÇO AXIAL DE DIREÇÃO L.M. (MOTORISTA) | AH49: =IF(OR(R49="A VISTA", R49="C. CRÉDITO", R49="ADIANTAMENTO"), N49, IF(R49="Faturado", _xlfn.MINIFS(N:N, C:C, C49)-30, "")) -> 45668 | AI49: HENRIQUE
A50: 49 | C50: OS-2025-0016 | D50: {=SUM(--(_xlfn.UNIQUE(_xlfn._xlws.FILTER($M$2:$M$1011 & "", ($C$2:$C$1011 = C50) * ($M$2:$M$1011 <> ""))) <> ""))} -> 2 | E50: =SUMIF(C:C, C50, Q:Q) -> 3178.68 | F50: 1 | G50: DLG0D92 | H50: =_xlfn.XLOOKUP(G50,'🚛 FROTA'!B:B,'🚛 FROTA'!A:A,"") -> 41 | J50: =IF(G50="","",_xlfn.XLOOKUP(G50,'🚛 FROTA'!B:B,'🚛 FROTA'!E:E,"")) -> Express Delivery | K50: =IF(G50="","",_xlfn.XLOOKUP(G50,'🚛 FROTA'!B:B,'🚛 FROTA'!K:K,"")) -> Carroceria Cabinado | L50: RS DIESEL | M50: 940/64 | N50: 45728 | O50: 2 | P50: 2 | Q50: 500 | R50: Faturado | S50: Serviço | T50: Pago | U50: Corretiva | V50: Freio | W50: SUBST. PINÇA, DISCOS E PASTILHAS | X50: SUBSTITUIÇÃO DE PINÇA, DISCOS E PASTILHAS DE FREIO | Z50: 29323 | AH50: =IF(OR(R50="A VISTA", R50="C. CRÉDITO", R50="ADIANTAMENTO"), N50, IF(R50="Faturado", _xlfn.MINIFS(N:N, C:C, C50)-30, "")) -> 45667 | AI50: SANDOVAL
A51: 50 | C51: OS-2025-0019 | D51: {=SUM(--(_xlfn.UNIQUE(_xlfn._xlws.FILTER($M$2:$M$1011 & "", ($C$2:$C$1011 = C51) * ($M$2:$M$1011 <> ""))) <> ""))} -> 1 | E51: =SUMIF(C:C, C51, Q:Q) -> 4568 | F51: 1 | G51: CCU5G26 | H51: =_xlfn.XLOOKUP(G51,'🚛 FROTA'!B:B,'🚛 FROTA'!A:A,"") -> 46 | J51: =IF(G51="","",_xlfn.XLOOKUP(G51,'🚛 FROTA'!B:B,'🚛 FROTA'!E:E,"")) -> Express Delivery | K51: =IF(G51="","",_xlfn.XLOOKUP(G51,'🚛 FROTA'!B:B,'🚛 FROTA'!K:K,"")) -> Carroceria | L51: FLORENZA TRUCK | M51: 2489/3248 | N51: 45703 | O51: 1 | P51: 4 | Q51: 1142 | R51: Faturado | S51: Serviço | T51: Pago | U51: Corretiva | V51: Câmbio | W51: SUBST. KIT EMBREAGEM | X51: SUBSTITUIÇÃO: KIT DE EMBREAGEM | AH51: =IF(OR(R51="A VISTA", R51="C. CRÉDITO", R51="ADIANTAMENTO"), N51, IF(R51="Faturado", _xlfn.MINIFS(N:N, C:C, C51)-30, "")) -> 45673 | AI51: AROUDO
A52: 51 | C52: OS-2025-0019 | D52: {=SUM(--(_xlfn.UNIQUE(_xlfn._xlws.FILTER($M$2:$M$1011 & "", ($C$2:$C$1011 = C52) * ($M$2:$M$1011 <> ""))) <> ""))} -> 1 | E52: =SUMIF(C:C, C52, Q:Q) -> 4568 | F52: 1 | G52: CCU5G26 | H52: =_xlfn.XLOOKUP(G52,'🚛 FROTA'!B:B,'🚛 FROTA'!A:A,"") -> 46 | J52: =IF(G52="","",_xlfn.XLOOKUP(G52,'🚛 FROTA'!B:B,'🚛 FROTA'!E:E,"")) -> Express Delivery | K52: =IF(G52="","",_xlfn.XLOOKUP(G52,'🚛 FROTA'!B:B,'🚛 FROTA'!K:K,"")) -> Carroceria | L52: FLORENZA TRUCK | M52: 2489/3248 | N52: 45731 | O52: 2 | P52: 4 | Q52: 1142 | R52: Faturado | S52: Serviço | T52: Pago | U52: Corretiva | V52: Câmbio | W52: SUBST. KIT EMBREAGEM | X52: SUBSTITUIÇÃO: KIT DE EMBREAGEM | AH52: =IF(OR(R52="A VISTA", R52="C. CRÉDITO", R52="ADIANTAMENTO"), N52, IF(R52="Faturado", _xlfn.MINIFS(N:N, C:C, C52)-30, "")) -> 45673 | AI52: AROUDO
A53: 52 | C53: OS-2025-0019 | D53: {=SUM(--(_xlfn.UNIQUE(_xlfn._xlws.FILTER($M$2:$M$1011 & "", ($C$2:$C$1011 = C53) * ($M$2:$M$1011 <> ""))) <> ""))} -> 1 | E53: =SUMIF(C:C, C53, Q:Q) -> 4568 | F53: 1 | G53: CCU5G26 | H53: =_xlfn.XLOOKUP(G53,'🚛 FROTA'!B:B,'🚛 FROTA'!A:A,"") -> 46 | J53: =IF(G53="","",_xlfn.XLOOKUP(G53,'🚛 FROTA'!B:B,'🚛 FROTA'!E:E,"")) -> Express Delivery | K53: =IF(G53="","",_xlfn.XLOOKUP(G53,'🚛 FROTA'!B:B,'🚛 FROTA'!K:K,"")) -> Carroceria | L53: FLORENZA TRUCK | M53: 2489/3248 | N53: 45762 | O53: 3 | P53: 4 | Q53: 1142 | R53: Faturado | S53: Serviço | T53: Pago | U53: Corretiva | V53: Câmbio | W53: SUBST. KIT EMBREAGEM | X53: SUBSTITUIÇÃO: KIT DE EMBREAGEM | Z53: 52531 | AH53: =IF(OR(R53="A VISTA", R53="C. CRÉDITO", R53="ADIANTAMENTO"), N53, IF(R53="Faturado", _xlfn.MINIFS(N:N, C:C, C53)-30, "")) -> 45673 | AI53: AROUDO
A54: 53 | C54: OS-2025-0019 | D54: {=SUM(--(_xlfn.UNIQUE(_xlfn._xlws.FILTER($M$2:$M$1011 & "", ($C$2:$C$1011 = C54) * ($M$2:$M$1011 <> ""))) <> ""))} -> 1 | E54: =SUMIF(C:C, C54, Q:Q) -> 4568 | F54: 1 | G54: CCU5G26 | H54: =_xlfn.XLOOKUP(G54,'🚛 FROTA'!B:B,'🚛 FROTA'!A:A,"") -> 46 | J54: =IF(G54="","",_xlfn.XLOOKUP(G54,'🚛 FROTA'!B:B,'🚛 FROTA'!E:E,"")) -> Express Delivery | K54: =IF(G54="","",_xlfn.XLOOKUP(G54,'🚛 FROTA'!B:B,'🚛 FROTA'!K:K,"")) -> Carroceria | L54: FLORENZA TRUCK | M54: 2489/3248 | N54: 45790 | O54: 4 | P54: 4 | Q54: 1142 | R54: Faturado | S54: Serviço | T54: Pago | U54: Corretiva | V54: Câmbio | W54: SUBST. KIT EMBREAGEM | X54: SUBSTITUIÇÃO: KIT DE EMBREAGEM | Z54: 5390 | AH54: =IF(OR(R54="A VISTA", R54="C. CRÉDITO", R54="ADIANTAMENTO"), N54, IF(R54="Faturado", _xlfn.MINIFS(N:N, C:C, C54)-30, "")) -> 45673 | AI54: AROUDO
A55: 54 | C55: OS-2025-0020 | D55: {=SUM(--(_xlfn.UNIQUE(_xlfn._xlws.FILTER($M$2:$M$1011 & "", ($C$2:$C$1011 = C55) * ($M$2:$M$1011 <> ""))) <> ""))} -> 2 | E55: =SUMIF(C:C, C55, Q:Q) -> 2177.47 | F55: 1 | G55: DLG0D92 | H55: =_xlfn.XLOOKUP(G55,'🚛 FROTA'!B:B,'🚛 FROTA'!A:A,"") -> 41 | J55: =IF(G55="","",_xlfn.XLOOKUP(G55,'🚛 FROTA'!B:B,'🚛 FROTA'!E:E,"")) -> Express Delivery | K55: =IF(G55="","",_xlfn.XLOOKUP(G55,'🚛 FROTA'!B:B,'🚛 FROTA'!K:K,"")) -> Carroceria Cabinado | L55: RS DIESEL | M55: 966 | N55: 45730 | O55: 1 | P55: 1 | Q55: 1100 | R55: Faturado | S55: Serviço | T55: Pago | U55: Preventiva | V55: Revisão | W55: TROCA ÓLEO E FILTROS | X55: Serviço: SUBSTITUIÇÃO DE FILTROS E TROCA DE ÓLEO | AH55: =IF(OR(R55="A VISTA", R55="C. CRÉDITO", R55="ADIANTAMENTO"), N55, IF(R55="Faturado", _xlfn.MINIFS(N:N, C:C, C55)-30, "")) -> 45695 | AI55: SANDOVAL | AK55: =IF(Z55="",0,Z55+10000) -> 0
A56: 55 | C56: OS-2025-0020 | D56: {=SUM(--(_xlfn.UNIQUE(_xlfn._xlws.FILTER($M$2:$M$1011 & "", ($C$2:$C$1011 = C56) * ($M$2:$M$1011 <> ""))) <> ""))} -> 2 | E56: =SUMIF(C:C, C56, Q:Q) -> 2177.47 | F56: 1 | G56: DLG0D92 | H56: =_xlfn.XLOOKUP(G56,'🚛 FROTA'!B:B,'🚛 FROTA'!A:A,"") -> 41 | J56: =IF(G56="","",_xlfn.XLOOKUP(G56,'🚛 FROTA'!B:B,'🚛 FROTA'!E:E,"")) -> Express Delivery | K56: =IF(G56="","",_xlfn.XLOOKUP(G56,'🚛 FROTA'!B:B,'🚛 FROTA'!K:K,"")) -> Carroceria Cabinado | L56: TIETE VEÍCULOS | M56: 5363 | N56: 45755 | O56: 2 | P56: 3 | Q56: 359.12 | R56: Faturado | S56: Compra | T56: Pago | U56: Preventiva | V56: Revisão | W56: KIT REVISAO — VW EXPRESS | X56: KIT REVISAO VW EXPRESS (OLEO + FILTROS) | AH56: =IF(OR(R56="A VISTA", R56="C. CRÉDITO", R56="ADIANTAMENTO"), N56, IF(R56="Faturado", _xlfn.MINIFS(N:N, C:C, C56)-30, "")) -> 45695 | AI56: GREGORY | AK56: =IF(Z56="",0,Z56+10000) -> 0
A57: 56 | C57: OS-2025-0016 | D57: {=SUM(--(_xlfn.UNIQUE(_xlfn._xlws.FILTER($M$2:$M$1011 & "", ($C$2:$C$1011 = C57) * ($M$2:$M$1011 <> ""))) <> ""))} -> 2 | E57: =SUMIF(C:C, C57, Q:Q) -> 3178.68 | F57: 1 | G57: DLG0D92 | H57: =_xlfn.XLOOKUP(G57,'🚛 FROTA'!B:B,'🚛 FROTA'!A:A,"") -> 41 | J57: =IF(G57="","",_xlfn.XLOOKUP(G57,'🚛 FROTA'!B:B,'🚛 FROTA'!E:E,"")) -> Express Delivery | K57: =IF(G57="","",_xlfn.XLOOKUP(G57,'🚛 FROTA'!B:B,'🚛 FROTA'!K:K,"")) -> Carroceria Cabinado | L57: TIETE VEÍCULOS | M57: 2770 | N57: 45757 | O57: 3 | P57: 3 | Q57: 726.37 | R57: Faturado | S57: Compra | T57: Pago | U57: Corretiva | V57: Freio | W57: FORNEC. PINÇA, DISCO E PASTILHAS | X57: FORNECIMENTO: 01 PINÇA DIANTEIRA + 01 DISCO + KIT PASTILHAS DIANTEIRAS | Y57: 01 PINÇA + 01 DISCO + 01 KIT | AH57: =IF(OR(R57="A VISTA", R57="C. CRÉDITO", R57="ADIANTAMENTO"), N57, IF(R57="Faturado", _xlfn.MINIFS(N:N, C:C, C57)-30, "")) -> 45667 | AI57: GREGORY
A58: 57 | C58: OS-2025-0020 | D58: {=SUM(--(_xlfn.UNIQUE(_xlfn._xlws.FILTER($M$2:$M$1011 & "", ($C$2:$C$1011 = C58) * ($M$2:$M$1011 <> ""))) <> ""))} -> 2 | E58: =SUMIF(C:C, C58, Q:Q) -> 2177.47 | F58: 1 | G58: DLG0D92 | H58: =_xlfn.XLOOKUP(G58,'🚛 FROTA'!B:B,'🚛 FROTA'!A:A,"") -> 41 | J58: =IF(G58="","",_xlfn.XLOOKUP(G58,'🚛 FROTA'!B:B,'🚛 FROTA'!E:E,"")) -> Express Delivery | K58: =IF(G58="","",_xlfn.XLOOKUP(G58,'🚛 FROTA'!B:B,'🚛 FROTA'!K:K,"")) -> Carroceria Cabinado | L58: TIETE VEÍCULOS | M58: 5363 | N58: 45785 | O58: 3 | P58: 3 | Q58: 359.22 | R58: Faturado | S58: Compra | T58: Pago | U58: Preventiva | V58: Revisão | W58: KIT REVISAO — VW EXPRESS | X58: KIT REVISAO VW EXPRESS (OLEO + FILTROS) | AH58: =IF(OR(R58="A VISTA", R58="C. CRÉDITO", R58="ADIANTAMENTO"), N58, IF(R58="Faturado", _xlfn.MINIFS(N:N, C:C, C58)-30, "")) -> 45695 | AI58: GREGORY | AK58: =IF(Z58="",0,Z58+10000) -> 0
A59: 58 | C59: OS-2025-0021 | D59: {=SUM(--(_xlfn.UNIQUE(_xlfn._xlws.FILTER($M$2:$M$1011 & "", ($C$2:$C$1011 = C59) * ($M$2:$M$1011 <> ""))) <> ""))} -> 1 | E59: =SUMIF(C:C, C59, Q:Q) -> 1077.46 | F59: 1 | G59: EJX0I24 | H59: =_xlfn.XLOOKUP(G59,'🚛 FROTA'!B:B,'🚛 FROTA'!A:A,"") -> 39 | J59: =IF(G59="","",_xlfn.XLOOKUP(G59,'🚛 FROTA'!B:B,'🚛 FROTA'!E:E,"")) -> Express Delivery | K59: =IF(G59="","",_xlfn.XLOOKUP(G59,'🚛 FROTA'!B:B,'🚛 FROTA'!K:K,"")) -> Carroceria Cabinado | L59: TIETE VEÍCULOS | M59: 5363 | N59: 45725 | O59: 1 | P59: 3 | Q59: 359.13 | R59: Faturado | S59: Compra | T59: Pago | U59: Preventiva | V59: Revisão | W59: KIT REVISAO — VW EXPRESS | X59: KIT REVISAO VW EXPRESS (OLEO + FILTROS) | AH59: =IF(OR(R59="A VISTA", R59="C. CRÉDITO", R59="ADIANTAMENTO"), N59, IF(R59="Faturado", _xlfn.MINIFS(N:N, C:C, C59)-30, "")) -> 45695 | AI59: GREGORY | AK59: =IF(Z59="",0,Z59+10000) -> 0
A60: 59 | C60: OS-2025-0021 | D60: {=SUM(--(_xlfn.UNIQUE(_xlfn._xlws.FILTER($M$2:$M$1011 & "", ($C$2:$C$1011 = C60) * ($M$2:$M$1011 <> ""))) <> ""))} -> 1 | E60: =SUMIF(C:C, C60, Q:Q) -> 1077.46 | F60: 1 | G60: EJX0I24 | H60: =_xlfn.XLOOKUP(G60,'🚛 FROTA'!B:B,'🚛 FROTA'!A:A,"") -> 39 | J60: =IF(G60="","",_xlfn.XLOOKUP(G60,'🚛 FROTA'!B:B,'🚛 FROTA'!E:E,"")) -> Express Delivery | K60: =IF(G60="","",_xlfn.XLOOKUP(G60,'🚛 FROTA'!B:B,'🚛 FROTA'!K:K,"")) -> Carroceria Cabinado | L60: TIETE VEÍCULOS | M60: 5363 | N60: 45755 | O60: 2 | P60: 3 | Q60: 359.12 | R60: Faturado | S60: Compra | T60: Pago | U60: Preventiva | V60: Revisão | W60: KIT REVISAO — VW EXPRESS | X60: KIT REVISAO VW EXPRESS (OLEO + FILTROS) | AH60: =IF(OR(R60="A VISTA", R60="C. CRÉDITO", R60="ADIANTAMENTO"), N60, IF(R60="Faturado", _xlfn.MINIFS(N:N, C:C, C60)-30, "")) -> 45695 | AI60: GREGORY | AK60: =IF(Z60="",0,Z60+10000) -> 0
A61: 60 | C61: OS-2025-0021 | D61: {=SUM(--(_xlfn.UNIQUE(_xlfn._xlws.FILTER($M$2:$M$1011 & "", ($C$2:$C$1011 = C61) * ($M$2:$M$1011 <> ""))) <> ""))} -> 1 | E61: =SUMIF(C:C, C61, Q:Q) -> 1077.46 | F61: 1 | G61: EJX0I24 | H61: =_xlfn.XLOOKUP(G61,'🚛 FROTA'!B:B,'🚛 FROTA'!A:A,"") -> 39 | J61: =IF(G61="","",_xlfn.XLOOKUP(G61,'🚛 FROTA'!B:B,'🚛 FROTA'!E:E,"")) -> Express Delivery | K61: =IF(G61="","",_xlfn.XLOOKUP(G61,'🚛 FROTA'!B:B,'🚛 FROTA'!K:K,"")) -> Carroceria Cabinado | L61: TIETE VEÍCULOS | M61: 5363 | N61: 45785 | O61: 3 | P61: 3 | Q61: 359.21 | R61: Faturado | S61: Compra | T61: Pago | U61: Preventiva | V61: Revisão | W61: KIT REVISAO — VW EXPRESS | X61: KIT REVISAO VW EXPRESS (OLEO + FILTROS) | AH61: =IF(OR(R61="A VISTA", R61="C. CRÉDITO", R61="ADIANTAMENTO"), N61, IF(R61="Faturado", _xlfn.MINIFS(N:N, C:C, C61)-30, "")) -> 45695 | AI61: GREGORY | AK61: =IF(Z61="",0,Z61+10000) -> 0
A62: 61 | C62: OS-2025-0022 | D62: {=SUM(--(_xlfn.UNIQUE(_xlfn._xlws.FILTER($M$2:$M$1011 & "", ($C$2:$C$1011 = C62) * ($M$2:$M$1011 <> ""))) <> ""))} -> 1 | E62: =SUMIF(C:C, C62, Q:Q) -> 1168 | F62: 1 | G62: DPB8E26 | H62: =_xlfn.XLOOKUP(G62,'🚛 FROTA'!B:B,'🚛 FROTA'!A:A,"") -> 40 | J62: =IF(G62="","",_xlfn.XLOOKUP(G62,'🚛 FROTA'!B:B,'🚛 FROTA'!E:E,"")) -> Express Delivery | K62: =IF(G62="","",_xlfn.XLOOKUP(G62,'🚛 FROTA'!B:B,'🚛 FROTA'!K:K,"")) -> Carroceria Cabinado | L62: CASALE OFICINA | M62: 1813 | N62: 45729 | O62: 1 | P62: 1 | Q62: 1168 | R62: Faturado | S62: Serviço | T62: Pago | U62: Corretiva | V62: Freio | W62: SUBST. PASTILHAS | X62: SUBSTITUIÇÃO DE PASTILHAS DE FREIO | Z62: 42300 | AH62: =IF(OR(R62="A VISTA", R62="C. CRÉDITO", R62="ADIANTAMENTO"), N62, IF(R62="Faturado", _xlfn.MINIFS(N:N, C:C, C62)-30, "")) -> 45699
A63: 62 | C63: OS-2025-0023 | D63: {=SUM(--(_xlfn.UNIQUE(_xlfn._xlws.FILTER($M$2:$M$1011 & "", ($C$2:$C$1011 = C63) * ($M$2:$M$1011 <> ""))) <> ""))} -> 1 | E63: =SUMIF(C:C, C63, Q:Q) -> 5927.12 | F63: 1 | G63: BSX5H07 | H63: =_xlfn.XLOOKUP(G63,'🚛 FROTA'!B:B,'🚛 FROTA'!A:A,"") -> 42 | J63: =IF(G63="","",_xlfn.XLOOKUP(G63,'🚛 FROTA'!B:B,'🚛 FROTA'!E:E,"")) -> Express Delivery | K63: =IF(G63="","",_xlfn.XLOOKUP(G63,'🚛 FROTA'!B:B,'🚛 FROTA'!K:K,"")) -> Carroceria | L63: FLORENZA TRUCK | M63: 2539/3307 | N63: 45730 | O63: 1 | P63: 4 | Q63: 1483.73 | R63: Faturado | S63: Serviço | T63: Pago | U63: Corretiva | V63: Câmbio | W63: SUBST. KIT EMBREAGEM | X63: SUBSTITUIÇÃO: KIT DE EMBREAGEM | Z63: 54017 | AH63: =IF(OR(R63="A VISTA", R63="C. CRÉDITO", R63="ADIANTAMENTO"), N63, IF(R63="Faturado", _xlfn.MINIFS(N:N, C:C, C63)-30, "")) -> 45700 | AI63: AROUDO
A64: 63 | C64: OS-2025-0023 | D64: {=SUM(--(_xlfn.UNIQUE(_xlfn._xlws.FILTER($M$2:$M$1011 & "", ($C$2:$C$1011 = C64) * ($M$2:$M$1011 <> ""))) <> ""))} -> 1 | E64: =SUMIF(C:C, C64, Q:Q) -> 5927.12 | F64: 1 | G64: BSX5H07 | H64: =_xlfn.XLOOKUP(G64,'🚛 FROTA'!B:B,'🚛 FROTA'!A:A,"") -> 42 | J64: =IF(G64="","",_xlfn.XLOOKUP(G64,'🚛 FROTA'!B:B,'🚛 FROTA'!E:E,"")) -> Express Delivery | K64: =IF(G64="","",_xlfn.XLOOKUP(G64,'🚛 FROTA'!B:B,'🚛 FROTA'!K:K,"")) -> Carroceria | L64: FLORENZA TRUCK | M64: 2539/3307 | N64: 45759 | O64: 2 | P64: 4 | Q64: 1481.13 | R64: Faturado | S64: Serviço | T64: Pago | U64: Corretiva | V64: Câmbio | W64: SUBST. KIT EMBREAGEM | X64: SUBSTITUIÇÃO: KIT DE EMBREAGEM | Z64: 54017 | AH64: =IF(OR(R64="A VISTA", R64="C. CRÉDITO", R64="ADIANTAMENTO"), N64, IF(R64="Faturado", _xlfn.MINIFS(N:N, C:C, C64)-30, "")) -> 45700 | AI64: AROUDO
A65: 64 | C65: OS-2025-0023 | D65: {=SUM(--(_xlfn.UNIQUE(_xlfn._xlws.FILTER($M$2:$M$1011 & "", ($C$2:$C$1011 = C65) * ($M$2:$M$1011 <> ""))) <> ""))} -> 1 | E65: =SUMIF(C:C, C65, Q:Q) -> 5927.12 | F65: 1 | G65: BSX5H07 | H65: =_xlfn.XLOOKUP(G65,'🚛 FROTA'!B:B,'🚛 FROTA'!A:A,"") -> 42 | J65: =IF(G65="","",_xlfn.XLOOKUP(G65,'🚛 FROTA'!B:B,'🚛 FROTA'!E:E,"")) -> Express Delivery | K65: =IF(G65="","",_xlfn.XLOOKUP(G65,'🚛 FROTA'!B:B,'🚛 FROTA'!K:K,"")) -> Carroceria | L65: FLORENZA TRUCK | M65: 2539/3307 | N65: 45790 | O65: 3 | P65: 4 | Q65: 1481.13 | R65: Faturado | S65: Serviço | T65: Pago | U65: Corretiva | V65: Câmbio | W65: SUBST. KIT EMBREAGEM | X65: SUBSTITUIÇÃO: KIT DE EMBREAGEM | Z65: 54017 | AH65: =IF(OR(R65="A VISTA", R65="C. CRÉDITO", R65="ADIANTAMENTO"), N65, IF(R65="Faturado", _xlfn.MINIFS(N:N, C:C, C65)-30, "")) -> 45700 | AI65: AROUDO
A66: 65 | C66: OS-2025-0023 | D66: {=SUM(--(_xlfn.UNIQUE(_xlfn._xlws.FILTER($M$2:$M$1011 & "", ($C$2:$C$1011 = C66) * ($M$2:$M$1011 <> ""))) <> ""))} -> 1 | E66: =SUMIF(C:C, C66, Q:Q) -> 5927.12 | F66: 1 | G66: BSX5H07 | H66: =_xlfn.XLOOKUP(G66,'🚛 FROTA'!B:B,'🚛 FROTA'!A:A,"") -> 42 | J66: =IF(G66="","",_xlfn.XLOOKUP(G66,'🚛 FROTA'!B:B,'🚛 FROTA'!E:E,"")) -> Express Delivery | K66: =IF(G66="","",_xlfn.XLOOKUP(G66,'🚛 FROTA'!B:B,'🚛 FROTA'!K:K,"")) -> Carroceria | L66: FLORENZA TRUCK | M66: 2539/3307 | N66: 45820 | O66: 4 | P66: 4 | Q66: 1481.13 | R66: Faturado | S66: Serviço | T66: Pago | U66: Corretiva | V66: Câmbio | W66: SUBST. KIT EMBREAGEM | X66: SUBSTITUIÇÃO: KIT DE EMBREAGEM | Z66: 54017 | AH66: =IF(OR(R66="A VISTA", R66="C. CRÉDITO", R66="ADIANTAMENTO"), N66, IF(R66="Faturado", _xlfn.MINIFS(N:N, C:C, C66)-30, "")) -> 45700 | AI66: AROUDO
A67: 66 | C67: OS-2025-0024 | D67: {=SUM(--(_xlfn.UNIQUE(_xlfn._xlws.FILTER($M$2:$M$1011 & "", ($C$2:$C$1011 = C67) * ($M$2:$M$1011 <> ""))) <> ""))} -> 1 | E67: =SUMIF(C:C, C67, Q:Q) -> 580 | F67: 1 | G67: EJX0I24 | H67: =_xlfn.XLOOKUP(G67,'🚛 FROTA'!B:B,'🚛 FROTA'!A:A,"") -> 39 | J67: =IF(G67="","",_xlfn.XLOOKUP(G67,'🚛 FROTA'!B:B,'🚛 FROTA'!E:E,"")) -> Express Delivery | K67: =IF(G67="","",_xlfn.XLOOKUP(G67,'🚛 FROTA'!B:B,'🚛 FROTA'!K:K,"")) -> Carroceria Cabinado | L67: DELLA VIA | M67: 62758 | N67: 45739 | O67: 1 | P67: 4 | Q67: 145 | R67: Faturado | S67: Compra | T67: Pago | U67: Corretiva | V67: Elétrico | W67: FORNEC. BATERIA | X67: FORNECIMENTO: 01 BATERIA 100A RYTEC | Y67: 01 BATERIA | Z67: 62639 | AH67: =IF(OR(R67="A VISTA", R67="C. CRÉDITO", R67="ADIANTAMENTO"), N67, IF(R67="Faturado", _xlfn.MINIFS(N:N, C:C, C67)-30, "")) -> 45709
A68: 67 | C68: OS-2025-0024 | D68: {=SUM(--(_xlfn.UNIQUE(_xlfn._xlws.FILTER($M$2:$M$1011 & "", ($C$2:$C$1011 = C68) * ($M$2:$M$1011 <> ""))) <> ""))} -> 1 | E68: =SUMIF(C:C, C68, Q:Q) -> 580 | F68: 1 | G68: EJX0I24 | H68: =_xlfn.XLOOKUP(G68,'🚛 FROTA'!B:B,'🚛 FROTA'!A:A,"") -> 39 | J68: =IF(G68="","",_xlfn.XLOOKUP(G68,'🚛 FROTA'!B:B,'🚛 FROTA'!E:E,"")) -> Express Delivery | K68: =IF(G68="","",_xlfn.XLOOKUP(G68,'🚛 FROTA'!B:B,'🚛 FROTA'!K:K,"")) -> Carroceria Cabinado | L68: DELLA VIA | M68: 62758 | N68: 45769 | O68: 2 | P68: 4 | Q68: 145 | R68: Faturado | S68: Compra | T68: Pago | U68: Corretiva | V68: Elétrico | W68: FORNEC. BATERIA | X68: FORNECIMENTO: 01 BATERIA 100A RYTEC | Y68: 01 BATERIA | Z68: 62639 | AH68: =IF(OR(R68="A VISTA", R68="C. CRÉDITO", R68="ADIANTAMENTO"), N68, IF(R68="Faturado", _xlfn.MINIFS(N:N, C:C, C68)-30, "")) -> 45709
A69: 68 | C69: OS-2025-0024 | D69: {=SUM(--(_xlfn.UNIQUE(_xlfn._xlws.FILTER($M$2:$M$1011 & "", ($C$2:$C$1011 = C69) * ($M$2:$M$1011 <> ""))) <> ""))} -> 1 | E69: =SUMIF(C:C, C69, Q:Q) -> 580 | F69: 1 | G69: EJX0I24 | H69: =_xlfn.XLOOKUP(G69,'🚛 FROTA'!B:B,'🚛 FROTA'!A:A,"") -> 39 | J69: =IF(G69="","",_xlfn.XLOOKUP(G69,'🚛 FROTA'!B:B,'🚛 FROTA'!E:E,"")) -> Express Delivery | K69: =IF(G69="","",_xlfn.XLOOKUP(G69,'🚛 FROTA'!B:B,'🚛 FROTA'!K:K,"")) -> Carroceria Cabinado | L69: DELLA VIA | M69: 62758 | N69: 45799 | O69: 3 | P69: 4 | Q69: 145 | R69: Faturado | S69: Compra | T69: Pago | U69: Corretiva | V69: Elétrico | W69: FORNEC. BATERIA | X69: FORNECIMENTO: 01 BATERIA 100A RYTEC | Y69: 01 BATERIA | Z69: 62639 | AH69: =IF(OR(R69="A VISTA", R69="C. CRÉDITO", R69="ADIANTAMENTO"), N69, IF(R69="Faturado", _xlfn.MINIFS(N:N, C:C, C69)-30, "")) -> 45709
A70: 69 | C70: OS-2025-0024 | D70: {=SUM(--(_xlfn.UNIQUE(_xlfn._xlws.FILTER($M$2:$M$1011 & "", ($C$2:$C$1011 = C70) * ($M$2:$M$1011 <> ""))) <> ""))} -> 1 | E70: =SUMIF(C:C, C70, Q:Q) -> 580 | F70: 1 | G70: EJX0I24 | H70: =_xlfn.XLOOKUP(G70,'🚛 FROTA'!B:B,'🚛 FROTA'!A:A,"") -> 39 | J70: =IF(G70="","",_xlfn.XLOOKUP(G70,'🚛 FROTA'!B:B,'🚛 FROTA'!E:E,"")) -> Express Delivery | K70: =IF(G70="","",_xlfn.XLOOKUP(G70,'🚛 FROTA'!B:B,'🚛 FROTA'!K:K,"")) -> Carroceria Cabinado | L70: DELLA VIA | M70: 62758 | N70: 45829 | O70: 4 | P70: 4 | Q70: 145 | R70: Faturado | S70: Compra | T70: Pago | U70: Corretiva | V70: Elétrico | W70: FORNEC. BATERIA | X70: FORNECIMENTO: 01 BATERIA 100A RYTEC | Y70: 01 BATERIA | Z70: 62639 | AH70: =IF(OR(R70="A VISTA", R70="C. CRÉDITO", R70="ADIANTAMENTO"), N70, IF(R70="Faturado", _xlfn.MINIFS(N:N, C:C, C70)-30, "")) -> 45709
A71: 70 | C71: OS-2025-0025 | D71: {=SUM(--(_xlfn.UNIQUE(_xlfn._xlws.FILTER($M$2:$M$1011 & "", ($C$2:$C$1011 = C71) * ($M$2:$M$1011 <> ""))) <> ""))} -> 2 | E71: =SUMIF(C:C, C71, Q:Q) -> 2677.99 | F71: 1 | G71: EJX0I24 | H71: =_xlfn.XLOOKUP(G71,'🚛 FROTA'!B:B,'🚛 FROTA'!A:A,"") -> 39 | J71: =IF(G71="","",_xlfn.XLOOKUP(G71,'🚛 FROTA'!B:B,'🚛 FROTA'!E:E,"")) -> Express Delivery | K71: =IF(G71="","",_xlfn.XLOOKUP(G71,'🚛 FROTA'!B:B,'🚛 FROTA'!K:K,"")) -> Carroceria Cabinado | L71: DELLA VIA | M71: 67857 | N71: 45739 | O71: 1 | P71: 4 | Q71: 69.9975 | R71: Faturado | S71: Serviço | T71: Pago | U71: Corretiva | V71: Pneu | W71: MONTAGEM E ALINHAMENTO PNEUS | X71: Serviço: MONTAGEM, ALINHAMENTO E BALANCEAMENTO DE 02 PNEUS 225/75R16C FIRESTONE | Y71: 02 PNEUS | Z71: 62639 | AA71: DIANTEIRO | AB71: 2 | AC71: 225/75R16C | AE71: FIRESTONE | AG71: Borracharia | AH71: =IF(OR(R71="A VISTA", R71="C. CRÉDITO", R71="ADIANTAMENTO"), N71, IF(R71="Faturado", _xlfn.MINIFS(N:N, C:C, C71)-30, "")) -> 45709
A72: 71 | C72: OS-2025-0025 | D72: {=SUM(--(_xlfn.UNIQUE(_xlfn._xlws.FILTER($M$2:$M$1011 & "", ($C$2:$C$1011 = C72) * ($M$2:$M$1011 <> ""))) <> ""))} -> 2 | E72: =SUMIF(C:C, C72, Q:Q) -> 2677.99 | F72: 1 | G72: EJX0I24 | H72: =_xlfn.XLOOKUP(G72,'🚛 FROTA'!B:B,'🚛 FROTA'!A:A,"") -> 39 | J72: =IF(G72="","",_xlfn.XLOOKUP(G72,'🚛 FROTA'!B:B,'🚛 FROTA'!E:E,"")) -> Express Delivery | K72: =IF(G72="","",_xlfn.XLOOKUP(G72,'🚛 FROTA'!B:B,'🚛 FROTA'!K:K,"")) -> Carroceria Cabinado | L72: DELLA VIA | M72: 62758 | N72: 45739 | O72: 1 | P72: 4 | Q72: 599.5 | R72: Faturado | S72: Compra | T72: Pago | U72: Corretiva | V72: Pneu | W72: FORNEC. PNEUS E BATERIA | X72: FORNECIMENTO: 02 PNEUS 225/75R16C FIRESTONE DIANT. + 01 BATERIA 100A | Y72: 02 PNEUS + 01 BATERIA | Z72: 62639 | AA72: DIANTEIRO | AB72: 2 | AC72: 225/75R16C | AD72: FIRESTONE | AE72: CV500 | AF72: NOVO | AG72: Loja | AH72: =IF(OR(R72="A VISTA", R72="C. CRÉDITO", R72="ADIANTAMENTO"), N72, IF(R72="Faturado", _xlfn.MINIFS(N:N, C:C, C72)-30, "")) -> 45709
A73: 72 | C73: OS-2025-0025 | D73: {=SUM(--(_xlfn.UNIQUE(_xlfn._xlws.FILTER($M$2:$M$1011 & "", ($C$2:$C$1011 = C73) * ($M$2:$M$1011 <> ""))) <> ""))} -> 2 | E73: =SUMIF(C:C, C73, Q:Q) -> 2677.99 | F73: 1 | G73: EJX0I24 | H73: =_xlfn.XLOOKUP(G73,'🚛 FROTA'!B:B,'🚛 FROTA'!A:A,"") -> 39 | J73: =IF(G73="","",_xlfn.XLOOKUP(G73,'🚛 FROTA'!B:B,'🚛 FROTA'!E:E,"")) -> Express Delivery | K73: =IF(G73="","",_xlfn.XLOOKUP(G73,'🚛 FROTA'!B:B,'🚛 FROTA'!K:K,"")) -> Carroceria Cabinado | L73: DELLA VIA | M73: 67857 | N73: 45769 | O73: 2 | P73: 4 | Q73: 69.9975 | R73: Faturado | S73: Serviço | T73: Pago | U73: Corretiva | V73: Pneu | W73: MONTAGEM E ALINHAMENTO PNEUS | X73: Serviço: MONTAGEM, ALINHAMENTO E BALANCEAMENTO DE 02 PNEUS 225/75R16C FIRESTONE | Y73: 02 PNEUS | Z73: 62639 | AA73: DIANTEIRO | AB73: 2 | AC73: 225/75R16C | AE73: FIRESTONE | AG73: Borracharia | AH73: =IF(OR(R73="A VISTA", R73="C. CRÉDITO", R73="ADIANTAMENTO"), N73, IF(R73="Faturado", _xlfn.MINIFS(N:N, C:C, C73)-30, "")) -> 45709
A74: 73 | C74: OS-2025-0025 | D74: {=SUM(--(_xlfn.UNIQUE(_xlfn._xlws.FILTER($M$2:$M$1011 & "", ($C$2:$C$1011 = C74) * ($M$2:$M$1011 <> ""))) <> ""))} -> 2 | E74: =SUMIF(C:C, C74, Q:Q) -> 2677.99 | F74: 1 | G74: EJX0I24 | H74: =_xlfn.XLOOKUP(G74,'🚛 FROTA'!B:B,'🚛 FROTA'!A:A,"") -> 39 | J74: =IF(G74="","",_xlfn.XLOOKUP(G74,'🚛 FROTA'!B:B,'🚛 FROTA'!E:E,"")) -> Express Delivery | K74: =IF(G74="","",_xlfn.XLOOKUP(G74,'🚛 FROTA'!B:B,'🚛 FROTA'!K:K,"")) -> Carroceria Cabinado | L74: DELLA VIA | M74: 62758 | N74: 45769 | O74: 2 | P74: 4 | Q74: 599.5 | R74: Faturado | S74: Compra | T74: Pago | U74: Corretiva | V74: Pneu | W74: FORNEC. PNEUS E BATERIA | X74: FORNECIMENTO: 02 PNEUS 225/75R16C FIRESTONE DIANT. + 01 BATERIA 100A | Y74: 02 PNEUS + 01 BATERIA | Z74: 62639 | AA74: DIANTEIRO | AB74: 2 | AC74: 225/75R16C | AD74: FIRESTONE | AE74: CV500 | AF74: NOVO | AG74: Loja | AH74: =IF(OR(R74="A VISTA", R74="C. CRÉDITO", R74="ADIANTAMENTO"), N74, IF(R74="Faturado", _xlfn.MINIFS(N:N, C:C, C74)-30, "")) -> 45709
A75: 74 | C75: OS-2025-0025 | D75: {=SUM(--(_xlfn.UNIQUE(_xlfn._xlws.FILTER($M$2:$M$1011 & "", ($C$2:$C$1011 = C75) * ($M$2:$M$1011 <> ""))) <> ""))} -> 2 | E75: =SUMIF(C:C, C75, Q:Q) -> 2677.99 | F75: 1 | G75: EJX0I24 | H75: =_xlfn.XLOOKUP(G75,'🚛 FROTA'!B:B,'🚛 FROTA'!A:A,"") -> 39 | J75: =IF(G75="","",_xlfn.XLOOKUP(G75,'🚛 FROTA'!B:B,'🚛 FROTA'!E:E,"")) -> Express Delivery | K75: =IF(G75="","",_xlfn.XLOOKUP(G75,'🚛 FROTA'!B:B,'🚛 FROTA'!K:K,"")) -> Carroceria Cabinado | L75: DELLA VIA | M75: 67857 | N75: 45799 | O75: 3 | P75: 4 | Q75: 69.9975 | R75: Faturado | S75: Serviço | T75: Pago | U75: Corretiva | V75: Pneu | W75: MONTAGEM E ALINHAMENTO PNEUS | X75: Serviço: MONTAGEM, ALINHAMENTO E BALANCEAMENTO DE 02 PNEUS 225/75R16C FIRESTONE | Y75: 02 PNEUS | Z75: 62639 | AA75: DIANTEIRO | AB75: 2 | AC75: 225/75R16C | AE75: FIRESTONE | AG75: Borracharia | AH75: =IF(OR(R75="A VISTA", R75="C. CRÉDITO", R75="ADIANTAMENTO"), N75, IF(R75="Faturado", _xlfn.MINIFS(N:N, C:C, C75)-30, "")) -> 45709
A76: 75 | C76: OS-2025-0025 | D76: {=SUM(--(_xlfn.UNIQUE(_xlfn._xlws.FILTER($M$2:$M$1011 & "", ($C$2:$C$1011 = C76) * ($M$2:$M$1011 <> ""))) <> ""))} -> 2 | E76: =SUMIF(C:C, C76, Q:Q) -> 2677.99 | F76: 1 | G76: EJX0I24 | H76: =_xlfn.XLOOKUP(G76,'🚛 FROTA'!B:B,'🚛 FROTA'!A:A,"") -> 39 | J76: =IF(G76="","",_xlfn.XLOOKUP(G76,'🚛 FROTA'!B:B,'🚛 FROTA'!E:E,"")) -> Express Delivery | K76: =IF(G76="","",_xlfn.XLOOKUP(G76,'🚛 FROTA'!B:B,'🚛 FROTA'!K:K,"")) -> Carroceria Cabinado | L76: DELLA VIA | M76: 62758 | N76: 45799 | O76: 3 | P76: 4 | Q76: 599.5 | R76: Faturado | S76: Compra | T76: Pago | U76: Corretiva | V76: Pneu | W76: FORNEC. PNEUS E BATERIA | X76: FORNECIMENTO: 02 PNEUS 225/75R16C FIRESTONE DIANT. + 01 BATERIA 100A | Y76: 02 PNEUS + 01 BATERIA | Z76: 62639 | AA76: DIANTEIRO | AB76: 2 | AC76: 225/75R16C | AD76: FIRESTONE | AE76: CV500 | AF76: NOVO | AG76: Loja | AH76: =IF(OR(R76="A VISTA", R76="C. CRÉDITO", R76="ADIANTAMENTO"), N76, IF(R76="Faturado", _xlfn.MINIFS(N:N, C:C, C76)-30, "")) -> 45709
A77: 76 | C77: OS-2025-0025 | D77: {=SUM(--(_xlfn.UNIQUE(_xlfn._xlws.FILTER($M$2:$M$1011 & "", ($C$2:$C$1011 = C77) * ($M$2:$M$1011 <> ""))) <> ""))} -> 2 | E77: =SUMIF(C:C, C77, Q:Q) -> 2677.99 | F77: 1 | G77: EJX0I24 | H77: =_xlfn.XLOOKUP(G77,'🚛 FROTA'!B:B,'🚛 FROTA'!A:A,"") -> 39 | J77: =IF(G77="","",_xlfn.XLOOKUP(G77,'🚛 FROTA'!B:B,'🚛 FROTA'!E:E,"")) -> Express Delivery | K77: =IF(G77="","",_xlfn.XLOOKUP(G77,'🚛 FROTA'!B:B,'🚛 FROTA'!K:K,"")) -> Carroceria Cabinado | L77: DELLA VIA | M77: 67857 | N77: 45829 | O77: 4 | P77: 4 | Q77: 69.9975 | R77: Faturado | S77: Serviço | T77: Pago | U77: Corretiva | V77: Pneu | W77: MONTAGEM E ALINHAMENTO PNEUS | X77: Serviço: MONTAGEM, ALINHAMENTO E BALANCEAMENTO DE 02 PNEUS 225/75R16C FIRESTONE | Y77: 02 PNEUS | Z77: 62639 | AA77: DIANTEIRO | AB77: 2 | AC77: 225/75R16C | AE77: FIRESTONE | AG77: Borracharia | AH77: =IF(OR(R77="A VISTA", R77="C. CRÉDITO", R77="ADIANTAMENTO"), N77, IF(R77="Faturado", _xlfn.MINIFS(N:N, C:C, C77)-30, "")) -> 45709
A78: 77 | C78: OS-2025-0025 | D78: {=SUM(--(_xlfn.UNIQUE(_xlfn._xlws.FILTER($M$2:$M$1011 & "", ($C$2:$C$1011 = C78) * ($M$2:$M$1011 <> ""))) <> ""))} -> 2 | E78: =SUMIF(C:C, C78, Q:Q) -> 2677.99 | F78: 1 | G78: EJX0I24 | H78: =_xlfn.XLOOKUP(G78,'🚛 FROTA'!B:B,'🚛 FROTA'!A:A,"") -> 39 | J78: =IF(G78="","",_xlfn.XLOOKUP(G78,'🚛 FROTA'!B:B,'🚛 FROTA'!E:E,"")) -> Express Delivery | K78: =IF(G78="","",_xlfn.XLOOKUP(G78,'🚛 FROTA'!B:B,'🚛 FROTA'!K:K,"")) -> Carroceria Cabinado | L78: DELLA VIA | M78: 62758 | N78: 45829 | O78: 4 | P78: 4 | Q78: 599.5 | R78: Faturado | S78: Compra | T78: Pago | U78: Corretiva | V78: Pneu | W78: FORNEC. PNEUS E BATERIA | X78: FORNECIMENTO: 02 PNEUS 225/75R16C FIRESTONE DIANT. + 01 BATERIA 100A | Y78: 02 PNEUS + 01 BATERIA | Z78: 62639 | AA78: DIANTEIRO | AB78: 2 | AC78: 225/75R16C | AD78: FIRESTONE | AE78: CV500 | AF78: NOVO | AG78: Loja | AH78: =IF(OR(R78="A VISTA", R78="C. CRÉDITO", R78="ADIANTAMENTO"), N78, IF(R78="Faturado", _xlfn.MINIFS(N:N, C:C, C78)-30, "")) -> 45709
A79: 78 | C79: OS-2025-0026 | D79: {=SUM(--(_xlfn.UNIQUE(_xlfn._xlws.FILTER($M$2:$M$1011 & "", ($C$2:$C$1011 = C79) * ($M$2:$M$1011 <> ""))) <> ""))} -> 1 | E79: =SUMIF(C:C, C79, Q:Q) -> 8109.8 | F79: 1 | G79: MAX4116 | H79: =_xlfn.XLOOKUP(G79,'🚛 FROTA'!B:B,'🚛 FROTA'!A:A,"") -> 20 | J79: =IF(G79="","",_xlfn.XLOOKUP(G79,'🚛 FROTA'!B:B,'🚛 FROTA'!E:E,"")) -> 3CX | L79: MORECAP | M79: 178904 | N79: 45743 | O79: 1 | P79: 4 | Q79: 2027.45 | R79: Faturado | S79: Compra | T79: Pago | U79: Corretiva | V79: Pneu | W79: FORNEC. PNEUS | X79: FORNECIMENTO: 02 PNEUS 17.5-25 16PR SUPERLAND TRASEIROS | Y79: 02 PNEUS | AA79: TRASEIRO | AB79: 2 | AC79: 17.5-25 | AD79: SUPERLAND | AE79: G2/L2 TL | AF79: NOVO | AG79: Loja | AH79: =IF(OR(R79="A VISTA", R79="C. CRÉDITO", R79="ADIANTAMENTO"), N79, IF(R79="Faturado", _xlfn.MINIFS(N:N, C:C, C79)-30, "")) -> 45713
